Workbook

Sheet Scoring
B1: LEAGUE SETTINGS & SCORING INPUTS
A2: INPUT YOUR LEAGUE SCORING HERE | I2: LEAGUE & ROSTER SETTINGS
A3: Setting: | B3: Points: | C3: DESCRIPTION | I3: #TEAMS: | J3: QB: | K3: RB: | L3: WR: | M3: TE: | N3: FLEX: | O3: BENCH: | P3: SUPERFLEX:
A4: PASSING | I4: 10 | J4: 1 | K4: 2 | L4: 3 | M4: 1 | N4: 0 | O4: 6 | P4: 0
A5: PassINCMP | B5: 0 | C5: Points Per Pass Incompletion (Use a Negative, Default is 0) | I5: ADVANCED SETTINGS
A6: PassCMP | B6: 0 | C6: Points Per Pass Completion (Default is 0) | I6: Snake/Auction | K6: Auction | L6: ESTIMATED KEEPER SAVINGS
A7: PassYDS | B7: 50 | C7: Passing Yards Per 1 Point (Default is 25) | I7: Budget: | K7: 200 | L7: Est. Total Saved (Auction Keepers) | P7: 0
A8: PassTDs | B8: 6 | C8: Points Per Passing Touchdown (Default is 4)
A9: INTS | B9: -2 | C9: Points Per Interception (Use a Negative, Default is -2)
A10: SACKS | B10: 0 | C10: Points Per Sack (Use a Negative, Default is 0)
A11: RUSHING
A12: RushATT | B12: 0 | C12: Points Per Rush Attempt (Default is 0)
A13: RushYDS | B13: 10 | C13: Rushing Yards Per 1 Point (Default is 10)
A14: RushTDS | B14: 6 | C14: Points Per Rushing Touchdown (Default is 6)
A15: RECEIVING
A16: RB PPR | B16: 0.5 | C16: RB Points Per Reception (Examples: 0 , .5 , 1)
A17: WR PPR | B17: 0.5 | C17: WR Points Per Reception (Examples: 0 , .5 , 1)
A18: TE PPR | B18: 0.5 | C18: TE Points Per Reception (Examples: 0 , .5 , 1)
A19: RecYDS | B19: 10 | C19: Receiving Yards Per 1 Point (Default is 10)
A20: RecTDS | B20: 6 | C20: Points Per Receiving Touchdown (Default is 6)
A21: OTHER:
A22: FL | B22: -2 | C22: Points Per Fumble Lost (Use a Negative, Default is -2)
A23: Pass1D | B23: 0 | C23: Points Per Passing 1st Down (Default is 0)
A24: Rush1D | B24: 0 | C24: Points Per Rushing 1st Down (Default is 0)
A25: Rec1D | B25: 0 | C25: Points Per Receiving 1st Down (Default is 0)
A28: 🔒 CALCULATED VALUES BELOW — DO NOT EDIT (used internally for VBD/Auction math)
A29: QBs: | B29: PassCMP | C29: PassYDS | D29: PassTDs | E29: INTS | F29: RushATT | G29: RushYDS | H29: RushTDS | I29: FL | J29: Pass1D | K29: Rush1D
A30: POINTS | B30: =B6 -> 0 | C30: =B7 -> 50 | D30: =B8 -> 6 | E30: =B9 -> -2 | F30: =B12 -> 0 | G30: =B13 -> 10 | H30: =B14 -> 6 | I30: =B22 -> -2 | J30: =B23 -> 0 | K30: =B24 -> 0
A31: RBs: | B31: RushATT | C31: RushYDS | D31: RushTDS | E31: PPR | F31: RecYDS | G31: RecTDS | H31: FL | I31: Rush1D | J31: Rec1D
A32: POINTS | B32: =B12 -> 0 | C32: =B13 -> 10 | D32: =B14 -> 6 | E32: =B16 -> 0.5 | F32: =B19 -> 10 | G32: =B20 -> 6 | H32: =B22 -> -2 | I32: =B24 -> 0 | J32: =B25 -> 0
A33: WRs: | B33: PPR | C33: RecYDS | D33: RecTDS | E33: RushATT | F33: RushYDS | G33: RushTDS | H33: FL | I33: Rush1D | J33: Rec1D
A34: POINTS | B34: =B17 -> 0.5 | C34: =B19 -> 10 | D34: =B20 -> 6 | E34: =B12 -> 0 | F34: =B13 -> 10 | G34: =B14 -> 6 | H34: =B22 -> -2 | I34: =B24 -> 0 | J34: =B25 -> 0
A35: TEs: | B35: PPR | C35: RecYDS | D35: RecTDS | E35: FL | F35: Rec1D
A36: POINTS | B36: =B18 -> 0.5 | C36: =B19 -> 10 | D36: =B20 -> 6 | E36: =B22 -> -2 | F36: =B25 -> 0
A38: Baseline Calcs
A39: #TEAMS: | B39: QB: | C39: RB: | D39: WR: | E39: TE: | F39: FLEX:
A40: =I4 -> 10 | B40: =J4+P4 -> 1 | C40: =K4 -> 2 | D40: =L4 -> 3 | E40: =M4 -> 1 | F40: =N4+I38 -> 0
A41: Roster | B41: =(J4+P4)*I4 -> 10 | C41: =K4*I4 -> 20 | D41: =L4*I4 -> 30 | E41: =M4*I4 -> 10 | F41: =N4*I4 -> 0
A42: Flex: | B42: 0 | C42: =FLEX!E1 -> 20 | D42: =FLEX!G1 -> 20 | E42: =FLEX!I1 -> 10
A43: Baselines: | B43: =ROUND(B41*1.2,) -> 12 | C43: =ROUND((C41+C42)*1.2,) -> 48 | D43: =ROUND((D41+D42)*1.3,) -> 65 | E43: =ROUND((E41+E42)*1.2,) -> 24
A44: Total Dollars: | B44: =K7*I4+P7 -> 2000
A45: Total Roster: | B45: =SUM(J4:P4)*I4 -> 130
A46: Premium: | B46: =B44-B45 -> 1870
A47: Total VOR: | B47: =SUM(Aggregate!J1+Aggregate!X1+Aggregate!AL1+Aggregate!AZ1) -> 7136.7664
A48: Premium/VOR: | B48: =B46/B47 -> 0.26202343

Sheet DraftSheet
B1: ="DRAFTSHEET - "&Scoring!I4&" Team - "&Scoring!B17&" PPR - "&Scoring!J4&"QB("&Aggregate!B1&")/"&Scoring!K4&"RB("&Aggregate!P1&")/"&Scoring!L4&"WR("&Aggregate!AD1&")/"&Scoring!M4&"TE("&Aggregate!AR1&")/"&Scoring!N4&"[RB/WR/TE]" -> DRAFTSHEET - 10 Team - 0.5 PPR - 1QB(12)/2RB(48)/3WR(65)/1TE(24)/0[RB/WR/TE] | AF1: PLAYER SEARCH
B2: ="Passing: "&Scoring!B8&" PPTD, "&ROUND(1/Scoring!B7,2)&" PPY, "&Scoring!B9&" Int | Rushing: "&Scoring!B14&" PPTD, "&ROUND(1/Scoring!B13,2)&" PPY | Receiving: "&Scoring!B20&" PPTD, "&ROUND(1/Scoring!B19,2)&" PPY, "&Scoring!B17&" PPR | Draft: use 'x' if drafted by someone else, 'o' if drafted by you | Updated: "&TEXT(TODAY(),"yyyy-mm-dd") -> Passing: 6 PPTD, 0.02 PPY, -2 Int | Rushing: 6 PPTD, 0.1 PPY | Receiving: 6 PPTD, 0.1 PPY, 0.5 PPR | Draft: use 'x' if drafted by someone else, 'o' if drafted by you | Updated: 2026-08-30 | AF2: TYPE NAME HERE: | AH2: =IF($AG$2="","",IFERROR(MATCH("*"&$AG$2&"*",C5:C44,0)+4,""))
B3: QUARTERBACK | L3: RUNNING BACK | V3: WIDE RECEIVER | AF3: Position: | AG3: =IF($AG$2="","",IF(AH2<>"","QB",IF(AH3<>"","RB",IF(AH4<>"","WR",IF(AH5<>"","TE","Not Found"))))) | AH3: =IF($AG$2="","",IFERROR(MATCH("*"&$AG$2&"*",M5:M84,0)+4,""))
B4: TIER | C4: NAME | D4: TM/BYE | E4: PTS | F4: VALUE | G4: PS | H4: ECR | I4: DRAFT | L4: TIER | M4: NAME | N4: TM/BYE | O4: PTS | P4: VALUE | Q4: PS | R4: ECR | S4: DRAFT | V4: TIER | W4: NAME | X4: TM/BYE | Y4: PTS | Z4: VALUE | AA4: PS | AB4: ECR | AC4: DRAFT | AF4: Tier: | AG4: {=IF($AG$2="","",IF(AH2<>"",INDEX(B:B,AH2),IF(AH3<>"",INDEX(L:L,AH3),IF(AH4<>"",INDEX(V:V,AH4),IF(AH5<>"",INDEX(B:B,AH5),"")))))} | AH4: =IF($AG$2="","",IFERROR(MATCH("*"&$AG$2&"*",W5:W84,0)+4,""))
B5: =IFERROR(VLOOKUP(DraftSheet!$C5,Aggregate!$B:$M,11,FALSE()),"") -> 1 | C5: =Aggregate!B3 -> Josh Allen | D5: =VLOOKUP(DraftSheet!$C5,Aggregate!B:M,4,FALSE()) -> BUF/7 | E5: =IFERROR(VLOOKUP(DraftSheet!$C5,Aggregate!$B:$M,8,FALSE()),"") -> 285.43762 | F5: =IF(Scoring!$K$6="Auction",IFERROR(VLOOKUP(DraftSheet!$C5,Aggregate!$B:$M,10,FALSE()),""),IFERROR(VLOOKUP(DraftSheet!$C5,Aggregate!$B:$M,9,FALSE()),"")) -> 17.714688 | G5: =SUMIFS($J6:J$44,$I6:I$44,"<>x",$I6:I$44,"<>o",$J6:J$44,">0")/Aggregate!$J$1 -> 0.66816192 | H5: {=IFERROR(INDEX(ECR!$K:$K,MATCH(DraftSheet!$C5,ECR!$C:$C,0)),"ND")} -> 26 | J5: =VLOOKUP(C5,Aggregate!B:J,9,FALSE()) -> 63.790813 | L5: =IFERROR(VLOOKUP(DraftSheet!$M5,Aggregate!$P:$AA,11,FALSE()),"") -> 1 | M5: =Aggregate!P3 -> Jahmyr Gibbs | N5: =VLOOKUP(DraftSheet!$M5,Aggregate!P:AA,4,FALSE()) -> DET/6 | O5: =IFERROR(VLOOKUP(DraftSheet!$M5,Aggregate!$P:$AA,8,FALSE()),"") -> 257.64662 | P5: =IF(Scoring!$K$6="Auction",IFERROR(VLOOKUP(DraftSheet!$M5,Aggregate!$P:$AA,10,FALSE()),""),IFERROR(VLOOKUP(DraftSheet!$M5,Aggregate!$P:$AA,9,FALSE()),"")) -> 47.969201 | Q5: =SUMIFS($T6:T$84,$S6:S$84,"<>x",$S6:S$84,"<>o",$T6:T$84,">0")/Aggregate!$X$1 -> 0.94423057 | R5: {=IFERROR(INDEX(ECR!$K:$K,MATCH(DraftSheet!$M5,ECR!$C:$C,0)),"ND")} -> 1 | T5: =VLOOKUP(M5,Aggregate!P:X,9,FALSE()) -> 179.25573 | V5: =IFERROR(VLOOKUP(DraftSheet!$W5,Aggregate!$AD:$AO,11,FALSE()),"") -> 1 | W5: =Aggregate!AD4 -> Puka Nacua | X5: =VLOOKUP(DraftSheet!$W5,Aggregate!AD:AO,4,FALSE()) -> LAR/11 | Y5: =IFERROR(VLOOKUP(DraftSheet!$W5,Aggregate!$AD:$AO,8,FALSE()),"") -> 236.31248 | Z5: =IF(Scoring!$K$6="Auction",IFERROR(VLOOKUP(DraftSheet!$W5,Aggregate!$AD:$AO,10,FALSE()),""),IFERROR(VLOOKUP(DraftSheet!$W5,Aggregate!$AD:$AO,9,FALSE()),"")) -> 41.559012 | AA5: =SUMIFS($AD6:AD$84,$AC6:AC$84,"<>x",$AC6:AC$84,"<>o",$AD6:AD$84,">0")/Aggregate!$AL$1 -> 0.94791663 | AB5: {=IFERROR(INDEX(ECR!$K:$K,MATCH(DraftSheet!$W5,ECR!$C:$C,0)),"ND")} -> 4 | AD5: =VLOOKUP(W5,Aggregate!AD:AL,9,FALSE()) -> 154.79155 | AF5: Name: | AG5: {=IF($AG$2="","",IF(AH2<>"",INDEX(C:C,AH2),IF(AH3<>"",INDEX(M:M,AH3),IF(AH4<>"",INDEX(W:W,AH4),IF(AH5<>"",INDEX(C:C,AH5),"")))))} | AH5: =IF($AG$2="","",IFERROR(MATCH("*"&$AG$2&"*",C48:C84,0)+47,""))
B6: =IFERROR(VLOOKUP(DraftSheet!$C6,Aggregate!$B:$M,11,FALSE()),"") -> 2 | C6: =Aggregate!B4 -> Lamar Jackson | D6: =VLOOKUP(DraftSheet!$C6,Aggregate!B:M,4,FALSE()) -> BAL/13 | E6: =IFERROR(VLOOKUP(DraftSheet!$C6,Aggregate!$B:$M,8,FALSE()),"") -> 253.12593 | F6: =IF(Scoring!$K$6="Auction",IFERROR(VLOOKUP(DraftSheet!$C6,Aggregate!$B:$M,10,FALSE()),""),IFERROR(VLOOKUP(DraftSheet!$C6,Aggregate!$B:$M,9,FALSE()),"")) -> 9.2482674 | G6: =SUMIFS($J7:J$44,$I7:I$44,"<>x",$I7:I$44,"<>o",$J7:J$44,">0")/Aggregate!$J$1 -> 0.50440838 | H6: {=IFERROR(INDEX(ECR!$K:$K,MATCH(DraftSheet!$C6,ECR!$C:$C,0)),"ND")} -> 37 | J6: =VLOOKUP(C6,Aggregate!B:J,9,FALSE()) -> 31.479122 | L6: =IFERROR(VLOOKUP(DraftSheet!$M6,Aggregate!$P:$AA,11,FALSE()),"") -> 1 | M6: =Aggregate!P4 -> Bijan Robinson | N6: =VLOOKUP(DraftSheet!$M6,Aggregate!P:AA,4,FALSE()) -> ATL/11 | O6: =IFERROR(VLOOKUP(DraftSheet!$M6,Aggregate!$P:$AA,8,FALSE()),"") -> 243.30456 | P6: =IF(Scoring!$K$6="Auction",IFERROR(VLOOKUP(DraftSheet!$M6,Aggregate!$P:$AA,10,FALSE()),""),IFERROR(VLOOKUP(DraftSheet!$M6,Aggregate!$P:$AA,9,FALSE()),"")) -> 44.211245 | Q6: =SUMIFS($T7:T$84,$S7:S$84,"<>x",$S7:S$84,"<>o",$T7:T$84,">0")/Aggregate!$X$1 -> 0.89292318 | R6: {=IFERROR(INDEX(ECR!$K:$K,MATCH(DraftSheet!$M6,ECR!$C:$C,0)),"ND")} -> 2 | T6: =VLOOKUP(M6,Aggregate!P:X,9,FALSE()) -> 164.91367 | V6: =IFERROR(VLOOKUP(DraftSheet!$W6,Aggregate!$AD:$AO,11,FALSE()),"") -> 1 | W6: =Aggregate!AD3 -> Ja'Marr Chase | X6: =VLOOKUP(DraftSheet!$W6,Aggregate!AD:AO,4,FALSE()) -> CIN/6 | Y6: =IFERROR(VLOOKUP(DraftSheet!$W6,Aggregate!$AD:$AO,8,FALSE()),"") -> 234.13723 | Z6: =IF(Scoring!$K$6="Auction",IFERROR(VLOOKUP(DraftSheet!$W6,Aggregate!$AD:$AO,10,FALSE()),""),IFERROR(VLOOKUP(DraftSheet!$W6,Aggregate!$AD:$AO,9,FALSE()),"")) -> 40.989047 | AA6: =SUMIFS($AD7:AD$84,$AC7:AC$84,"<>x",$AC7:AC$84,"<>o",$AD7:AD$84,">0")/Aggregate!$AL$1 -> 0.89814128 | AB6: {=IFERROR(INDEX(ECR!$K:$K,MATCH(DraftSheet!$W6,ECR!$C:$C,0)),"ND")} -> 3 | AD6: =VLOOKUP(W6,Aggregate!AD:AL,9,FALSE()) -> 152.6163 | AF6: TM/BYE: | AG6: {=IF($AG$2="","",IF(AH2<>"",INDEX(D:D,AH2),IF(AH3<>"",INDEX(N:N,AH3),IF(AH4<>"",INDEX(X:X,AH4),IF(AH5<>"",INDEX(D:D,AH5),"")))))}
B7: =IFERROR(VLOOKUP(DraftSheet!$C7,Aggregate!$B:$M,11,FALSE()),"") -> 2 | C7: =Aggregate!B5 -> Drake Maye | D7: =VLOOKUP(DraftSheet!$C7,Aggregate!B:M,4,FALSE()) -> NE/11 | E7: =IFERROR(VLOOKUP(DraftSheet!$C7,Aggregate!$B:$M,8,FALSE()),"") -> 241.33652 | F7: =IF(Scoring!$K$6="Auction",IFERROR(VLOOKUP(DraftSheet!$C7,Aggregate!$B:$M,10,FALSE()),""),IFERROR(VLOOKUP(DraftSheet!$C7,Aggregate!$B:$M,9,FALSE()),"")) -> 6.1591651 | G7: =SUMIFS($J8:J$44,$I8:I$44,"<>x",$I8:I$44,"<>o",$J8:J$44,">0")/Aggregate!$J$1 -> 0.40198304 | H7: {=IFERROR(INDEX(ECR!$K:$K,MATCH(DraftSheet!$C7,ECR!$C:$C,0)),"ND")} -> 45 | J7: =VLOOKUP(C7,Aggregate!B:J,9,FALSE()) -> 19.689709 | L7: =IFERROR(VLOOKUP(DraftSheet!$M7,Aggregate!$P:$AA,11,FALSE()),"") -> 2 | M7: =Aggregate!P5 -> Christian McCaffrey | N7: =VLOOKUP(DraftSheet!$M7,Aggregate!P:AA,4,FALSE()) -> SF/8 | O7: =IFERROR(VLOOKUP(DraftSheet!$M7,Aggregate!$P:$AA,8,FALSE()),"") -> 224.92676 | P7: =IF(Scoring!$K$6="Auction",IFERROR(VLOOKUP(DraftSheet!$M7,Aggregate!$P:$AA,10,FALSE()),""),IFERROR(VLOOKUP(DraftSheet!$M7,Aggregate!$P:$AA,9,FALSE()),"")) -> 39.395833 | Q7: =SUMIFS($T8:T$84,$S8:S$84,"<>x",$S8:S$84,"<>o",$T8:T$84,">0")/Aggregate!$X$1 -> 0.84733344 | R7: {=IFERROR(INDEX(ECR!$K:$K,MATCH(DraftSheet!$M7,ECR!$C:$C,0)),"ND")} -> 7 | T7: =VLOOKUP(M7,Aggregate!P:X,9,FALSE()) -> 146.53588 | V7: =IFERROR(VLOOKUP(DraftSheet!$W7,Aggregate!$AD:$AO,11,FALSE()),"") -> 1 | W7: =Aggregate!AD5 -> Jaxon Smith-Njigba | X7: =VLOOKUP(DraftSheet!$W7,Aggregate!AD:AO,4,FALSE()) -> SEA/11 | Y7: =IFERROR(VLOOKUP(DraftSheet!$W7,Aggregate!$AD:$AO,8,FALSE()),"") -> 228.34417 | Z7: =IF(Scoring!$K$6="Auction",IFERROR(VLOOKUP(DraftSheet!$W7,Aggregate!$AD:$AO,10,FALSE()),""),IFERROR(VLOOKUP(DraftSheet!$W7,Aggregate!$AD:$AO,9,FALSE()),"")) -> 39.47113 | AA7: =SUMIFS($AD8:AD$84,$AC8:AC$84,"<>x",$AC8:AC$84,"<>o",$AD8:AD$84,">0")/Aggregate!$AL$1 -> 0.85025532 | AB7: {=IFERROR(INDEX(ECR!$K:$K,MATCH(DraftSheet!$W7,ECR!$C:$C,0)),"ND")} -> 5 | AD7: =VLOOKUP(W7,Aggregate!AD:AL,9,FALSE()) -> 146.82324 | AF7: PTS: | AG7: {=IF($AG$2="","",IF(AH2<>"",INDEX(E:E,AH2),IF(AH3<>"",INDEX(O:O,AH3),IF(AH4<>"",INDEX(Y:Y,AH4),IF(AH5<>"",INDEX(E:E,AH5),"")))))}
B8: =IFERROR(VLOOKUP(DraftSheet!$C8,Aggregate!$B:$M,11,FALSE()),"") -> 3 | C8: =Aggregate!B7 -> Jayden Daniels | D8: =VLOOKUP(DraftSheet!$C8,Aggregate!B:M,4,FALSE()) -> WAS/7 | E8: =IFERROR(VLOOKUP(DraftSheet!$C8,Aggregate!$B:$M,8,FALSE()),"") -> 239.84478 | F8: =IF(Scoring!$K$6="Auction",IFERROR(VLOOKUP(DraftSheet!$C8,Aggregate!$B:$M,10,FALSE()),""),IFERROR(VLOOKUP(DraftSheet!$C8,Aggregate!$B:$M,9,FALSE()),"")) -> 5.768296 | G8: =SUMIFS($J9:J$44,$I9:I$44,"<>x",$I9:I$44,"<>o",$J9:J$44,">0")/Aggregate!$J$1 -> 0.30731766 | H8: {=IFERROR(INDEX(ECR!$K:$K,MATCH(DraftSheet!$C8,ECR!$C:$C,0)),"ND")} -> 60 | J8: =VLOOKUP(C8,Aggregate!B:J,9,FALSE()) -> 18.197976 | L8: =IFERROR(VLOOKUP(DraftSheet!$M8,Aggregate!$P:$AA,11,FALSE()),"") -> 2 | M8: =Aggregate!P6 -> Jonathan Taylor | N8: =VLOOKUP(DraftSheet!$M8,Aggregate!P:AA,4,FALSE()) -> IND/13 | O8: =IFERROR(VLOOKUP(DraftSheet!$M8,Aggregate!$P:$AA,8,FALSE()),"") -> 222.03426 | P8: =IF(Scoring!$K$6="Auction",IFERROR(VLOOKUP(DraftSheet!$M8,Aggregate!$P:$AA,10,FALSE()),""),IFERROR(VLOOKUP(DraftSheet!$M8,Aggregate!$P:$AA,9,FALSE()),"")) -> 38.63793 | Q8: =SUMIFS($T9:T$84,$S9:S$84,"<>x",$S9:S$84,"<>o",$T9:T$84,">0")/Aggregate!$X$1 -> 0.8026436 | R8: {=IFERROR(INDEX(ECR!$K:$K,MATCH(DraftSheet!$M8,ECR!$C:$C,0)),"ND")} -> 8 | T8: =VLOOKUP(M8,Aggregate!P:X,9,FALSE()) -> 143.64338 | V8: =IFERROR(VLOOKUP(DraftSheet!$W8,Aggregate!$AD:$AO,11,FALSE()),"") -> 1 | W8: =Aggregate!AD6 -> Amon-Ra St. Brown | X8: =VLOOKUP(DraftSheet!$W8,Aggregate!AD:AO,4,FALSE()) -> DET/6 | Y8: =IFERROR(VLOOKUP(DraftSheet!$W8,Aggregate!$AD:$AO,8,FALSE()),"") -> 218.04724 | Z8: =IF(Scoring!$K$6="Auction",IFERROR(VLOOKUP(DraftSheet!$W8,Aggregate!$AD:$AO,10,FALSE()),""),IFERROR(VLOOKUP(DraftSheet!$W8,Aggregate!$AD:$AO,9,FALSE()),"")) -> 36.773092 | AA8: =SUMIFS($AD9:AD$84,$AC9:AC$84,"<>x",$AC9:AC$84,"<>o",$AD9:AD$84,">0")/Aggregate!$AL$1 -> 0.80572768 | AB8: {=IFERROR(INDEX(ECR!$K:$K,MATCH(DraftSheet!$W8,ECR!$C:$C,0)),"ND")} -> 6 | AD8: =VLOOKUP(W8,Aggregate!AD:AL,9,FALSE()) -> 136.52631 | AF8: VALUE: | AG8: {=IF($AG$2="","",IF(AH2<>"",INDEX(F:F,AH2),IF(AH3<>"",INDEX(P:P,AH3),IF(AH4<>"",INDEX(Z:Z,AH4),IF(AH5<>"",INDEX(F:F,AH5),"")))))}
B9: =IFERROR(VLOOKUP(DraftSheet!$C9,Aggregate!$B:$M,11,FALSE()),"") -> 2 | C9: =Aggregate!B8 -> Jalen Hurts | D9: =VLOOKUP(DraftSheet!$C9,Aggregate!B:M,4,FALSE()) -> PHI/10 | E9: =IFERROR(VLOOKUP(DraftSheet!$C9,Aggregate!$B:$M,8,FALSE()),"") -> 243.38374 | F9: =IF(Scoring!$K$6="Auction",IFERROR(VLOOKUP(DraftSheet!$C9,Aggregate!$B:$M,10,FALSE()),""),IFERROR(VLOOKUP(DraftSheet!$C9,Aggregate!$B:$M,9,FALSE()),"")) -> 6.6955854 | G9: =SUMIFS($J10:J$44,$I10:I$44,"<>x",$I10:I$44,"<>o",$J10:J$44,">0")/Aggregate!$J$1 -> 0.19424273 | H9: {=IFERROR(INDEX(ECR!$K:$K,MATCH(DraftSheet!$C9,ECR!$C:$C,0)),"ND")} -> 63 | J9: =VLOOKUP(C9,Aggregate!B:J,9,FALSE()) -> 21.736932 | L9: =IFERROR(VLOOKUP(DraftSheet!$M9,Aggregate!$P:$AA,11,FALSE()),"") -> 3 | M9: =Aggregate!P10 -> De'Von Achane | N9: =VLOOKUP(DraftSheet!$M9,Aggregate!P:AA,4,FALSE()) -> MIA/6 | O9: =IFERROR(VLOOKUP(DraftSheet!$M9,Aggregate!$P:$AA,8,FALSE()),"") -> 197.73382 | P9: =IF(Scoring!$K$6="Auction",IFERROR(VLOOKUP(DraftSheet!$M9,Aggregate!$P:$AA,10,FALSE()),""),IFERROR(VLOOKUP(DraftSheet!$M9,Aggregate!$P:$AA,9,FALSE()),"")) -> 32.270645 | Q9: =SUMIFS($T10:T$84,$S10:S$84,"<>x",$S10:S$84,"<>o",$T10:T$84,">0")/Aggregate!$X$1 -> 0.76551403 | R9: {=IFERROR(INDEX(ECR!$K:$K,MATCH(DraftSheet!$M9,ECR!$C:$C,0)),"ND")} -> 16 | T9: =VLOOKUP(M9,Aggregate!P:X,9,FALSE()) -> 119.34293 | V9: =IFERROR(VLOOKUP(DraftSheet!$W9,Aggregate!$AD:$AO,11,FALSE()),"") -> 2 | W9: =Aggregate!AD8 -> Justin Jefferson | X9: =VLOOKUP(DraftSheet!$W9,Aggregate!AD:AO,4,FALSE()) -> MIN/6 | Y9: =IFERROR(VLOOKUP(DraftSheet!$W9,Aggregate!$AD:$AO,8,FALSE()),"") -> 185.23229 | Z9: =IF(Scoring!$K$6="Auction",IFERROR(VLOOKUP(DraftSheet!$W9,Aggregate!$AD:$AO,10,FALSE()),""),IFERROR(VLOOKUP(DraftSheet!$W9,Aggregate!$AD:$AO,9,FALSE()),"")) -> 28.174807 | AA9: =SUMIFS($AD10:AD$84,$AC10:AC$84,"<>x",$AC10:AC$84,"<>o",$AD10:AD$84,">0")/Aggregate!$AL$1 -> 0.77190253 | AB9: {=IFERROR(INDEX(ECR!$K:$K,MATCH(DraftSheet!$W9,ECR!$C:$C,0)),"ND")} -> 11 | AD9: =VLOOKUP(W9,Aggregate!AD:AL,9,FALSE()) -> 103.71136 | AF9: PS: | AG9: {=IF($AG$2="","",IF(AH2<>"",INDEX(G:G,AH2),IF(AH3<>"",INDEX(Q:Q,AH3),IF(AH4<>"",INDEX(AA:AA,AH4),IF(AH5<>"",INDEX(G:G,AH5),"")))))}
B10: =IFERROR(VLOOKUP(DraftSheet!$C10,Aggregate!$B:$M,11,FALSE()),"") -> 3 | C10: =Aggregate!B6 -> Joe Burrow | D10: =VLOOKUP(DraftSheet!$C10,Aggregate!B:M,4,FALSE()) -> CIN/6 | E10: =IFERROR(VLOOKUP(DraftSheet!$C10,Aggregate!$B:$M,8,FALSE()),"") -> 239.37106 | F10: =IF(Scoring!$K$6="Auction",IFERROR(VLOOKUP(DraftSheet!$C10,Aggregate!$B:$M,10,FALSE()),""),IFERROR(VLOOKUP(DraftSheet!$C10,Aggregate!$B:$M,9,FALSE()),"")) -> 5.6441702 | G10: =SUMIFS($J11:J$44,$I11:I$44,"<>x",$I11:I$44,"<>o",$J11:J$44,">0")/Aggregate!$J$1 -> 0.10204164 | H10: {=IFERROR(INDEX(ECR!$K:$K,MATCH(DraftSheet!$C10,ECR!$C:$C,0)),"ND")} -> 50 | J10: =VLOOKUP(C10,Aggregate!B:J,9,FALSE()) -> 17.724256 | L10: =IFERROR(VLOOKUP(DraftSheet!$M10,Aggregate!$P:$AA,11,FALSE()),"") -> 3 | M10: =Aggregate!P12 -> Derrick Henry | N10: =VLOOKUP(DraftSheet!$M10,Aggregate!P:AA,4,FALSE()) -> BAL/13 | O10: =IFERROR(VLOOKUP(DraftSheet!$M10,Aggregate!$P:$AA,8,FALSE()),"") -> 196.88118 | P10: =IF(Scoring!$K$6="Auction",IFERROR(VLOOKUP(DraftSheet!$M10,Aggregate!$P:$AA,10,FALSE()),""),IFERROR(VLOOKUP(DraftSheet!$M10,Aggregate!$P:$AA,9,FALSE()),"")) -> 32.047231 | Q10: =SUMIFS($T11:T$84,$S11:S$84,"<>x",$S11:S$84,"<>o",$T11:T$84,">0")/Aggregate!$X$1 -> 0.72864973 | R10: {=IFERROR(INDEX(ECR!$K:$K,MATCH(DraftSheet!$M10,ECR!$C:$C,0)),"ND")} -> 20 | T10: =VLOOKUP(M10,Aggregate!P:X,9,FALSE()) -> 118.49029 | V10: =IFERROR(VLOOKUP(DraftSheet!$W10,Aggregate!$AD:$AO,11,FALSE()),"") -> 2 | W10: =Aggregate!AD7 -> CeeDee Lamb | X10: =VLOOKUP(DraftSheet!$W10,Aggregate!AD:AO,4,FALSE()) -> DAL/14 | Y10: =IFERROR(VLOOKUP(DraftSheet!$W10,Aggregate!$AD:$AO,8,FALSE()),"") -> 184.0414 | Z10: =IF(Scoring!$K$6="Auction",IFERROR(VLOOKUP(DraftSheet!$W10,Aggregate!$AD:$AO,10,FALSE()),""),IFERROR(VLOOKUP(DraftSheet!$W10,Aggregate!$AD:$AO,9,FALSE()),"")) -> 27.862767 | AA10: =SUMIFS($AD11:AD$84,$AC11:AC$84,"<>x",$AC11:AC$84,"<>o",$AD11:AD$84,">0")/Aggregate!$AL$1 -> 0.73846579 | AB10: {=IFERROR(INDEX(ECR!$K:$K,MATCH(DraftSheet!$W10,ECR!$C:$C,0)),"ND")} -> 9 | AD10: =VLOOKUP(W10,Aggregate!AD:AL,9,FALSE()) -> 102.52048 | AF10: ECR: | AG10: {=IF($AG$2="","",IF(AH2<>"",INDEX(H:H,AH2),IF(AH3<>"",INDEX(R:R,AH3),IF(AH4<>"",INDEX(AB:AB,AH4),IF(AH5<>"",INDEX(H:H,AH5),"")))))}
B11: =IFERROR(VLOOKUP(DraftSheet!$C11,Aggregate!$B:$M,11,FALSE()),"") -> 4 | C11: =Aggregate!B11 -> Trevor Lawrence | D11: =VLOOKUP(DraftSheet!$C11,Aggregate!B:M,4,FALSE()) -> JAC/7 | E11: =IFERROR(VLOOKUP(DraftSheet!$C11,Aggregate!$B:$M,8,FALSE()),"") -> 227.08694 | F11: =IF(Scoring!$K$6="Auction",IFERROR(VLOOKUP(DraftSheet!$C11,Aggregate!$B:$M,10,FALSE()),""),IFERROR(VLOOKUP(DraftSheet!$C11,Aggregate!$B:$M,9,FALSE()),"")) -> 2.4254426 | G11: =SUMIFS($J12:J$44,$I12:I$44,"<>x",$I12:I$44,"<>o",$J12:J$44,">0")/Aggregate!$J$1 -> 0.073742205 | H11: {=IFERROR(INDEX(ECR!$K:$K,MATCH(DraftSheet!$C11,ECR!$C:$C,0)),"ND")} -> 75 | J11: =VLOOKUP(C11,Aggregate!B:J,9,FALSE()) -> 5.4401341 | L11: =IFERROR(VLOOKUP(DraftSheet!$M11,Aggregate!$P:$AA,11,FALSE()),"") -> 3 | M11: =Aggregate!P7 -> James Cook III | N11: =VLOOKUP(DraftSheet!$M11,Aggregate!P:AA,4,FALSE()) -> BUF/7 | O11: =IFERROR(VLOOKUP(DraftSheet!$M11,Aggregate!$P:$AA,8,FALSE()),"") -> 195.69397 | P11: =IF(Scoring!$K$6="Auction",IFERROR(VLOOKUP(DraftSheet!$M11,Aggregate!$P:$AA,10,FALSE()),""),IFERROR(VLOOKUP(DraftSheet!$M11,Aggregate!$P:$AA,9,FALSE()),"")) -> 31.736156 | Q11: =SUMIFS($T12:T$84,$S12:S$84,"<>x",$S12:S$84,"<>o",$T12:T$84,">0")/Aggregate!$X$1 -> 0.69215479 | R11: {=IFERROR(INDEX(ECR!$K:$K,MATCH(DraftSheet!$M11,ECR!$C:$C,0)),"ND")} -> 10 | T11: =VLOOKUP(M11,Aggregate!P:X,9,FALSE()) -> 117.30308 | V11: =IFERROR(VLOOKUP(DraftSheet!$W11,Aggregate!$AD:$AO,11,FALSE()),"") -> 2 | W11: =Aggregate!AD9 -> Drake London | X11: =VLOOKUP(DraftSheet!$W11,Aggregate!AD:AO,4,FALSE()) -> ATL/11 | Y11: =IFERROR(VLOOKUP(DraftSheet!$W11,Aggregate!$AD:$AO,8,FALSE()),"") -> 181.26158 | Z11: =IF(Scoring!$K$6="Auction",IFERROR(VLOOKUP(DraftSheet!$W11,Aggregate!$AD:$AO,10,FALSE()),""),IFERROR(VLOOKUP(DraftSheet!$W11,Aggregate!$AD:$AO,9,FALSE()),"")) -> 27.134388 | AA11: =SUMIFS($AD12:AD$84,$AC12:AC$84,"<>x",$AC12:AC$84,"<>o",$AD12:AD$84,">0")/Aggregate!$AL$1 -> 0.70593567 | AB11: {=IFERROR(INDEX(ECR!$K:$K,MATCH(DraftSheet!$W11,ECR!$C:$C,0)),"ND")} -> 13 | AD11: =VLOOKUP(W11,Aggregate!AD:AL,9,FALSE()) -> 99.740655 | AF11: Drafted?: | AG11: {=IF($AG$2="","",IF(AH2<>"",IF(INDEX(I:I,AH2)="","Available",INDEX(I:I,AH2)),IF(AH3<>"",IF(INDEX(S:S,AH3)="","Available",INDEX(S:S,AH3)),IF(AH4<>"",IF(INDEX(AC:AC,AH4)="","Available",INDEX(AC:AC,AH4)),IF(AH5<>"",IF(INDEX(I:I,AH5)="","Available",INDEX(I:I,AH5)),"")))))}
B12: =IFERROR(VLOOKUP(DraftSheet!$C12,Aggregate!$B:$M,11,FALSE()),"") -> 4 | C12: =Aggregate!B14 -> Jaxson Dart | D12: =VLOOKUP(DraftSheet!$C12,Aggregate!B:M,4,FALSE()) -> NYG/8 | E12: =IFERROR(VLOOKUP(DraftSheet!$C12,Aggregate!$B:$M,8,FALSE()),"") -> 224.79842 | F12: =IF(Scoring!$K$6="Auction",IFERROR(VLOOKUP(DraftSheet!$C12,Aggregate!$B:$M,10,FALSE()),""),IFERROR(VLOOKUP(DraftSheet!$C12,Aggregate!$B:$M,9,FALSE()),"")) -> 1.8257977 | G12: =SUMIFS($J13:J$44,$I13:I$44,"<>x",$I13:I$44,"<>o",$J13:J$44,">0")/Aggregate!$J$1 -> 0.057347574 | H12: {=IFERROR(INDEX(ECR!$K:$K,MATCH(DraftSheet!$C12,ECR!$C:$C,0)),"ND")} -> 98 | J12: =VLOOKUP(C12,Aggregate!B:J,9,FALSE()) -> 3.1516179 | L12: =IFERROR(VLOOKUP(DraftSheet!$M12,Aggregate!$P:$AA,11,FALSE()),"") -> 3 | M12: =Aggregate!P8 -> Chase Brown | N12: =VLOOKUP(DraftSheet!$M12,Aggregate!P:AA,4,FALSE()) -> CIN/6 | O12: =IFERROR(VLOOKUP(DraftSheet!$M12,Aggregate!$P:$AA,8,FALSE()),"") -> 191.45368 | P12: =IF(Scoring!$K$6="Auction",IFERROR(VLOOKUP(DraftSheet!$M12,Aggregate!$P:$AA,10,FALSE()),""),IFERROR(VLOOKUP(DraftSheet!$M12,Aggregate!$P:$AA,9,FALSE()),"")) -> 30.625099 | Q12: =SUMIFS($T13:T$84,$S13:S$84,"<>x",$S13:S$84,"<>o",$T13:T$84,">0")/Aggregate!$X$1 -> 0.65697908 | R12: {=IFERROR(INDEX(ECR!$K:$K,MATCH(DraftSheet!$M12,ECR!$C:$C,0)),"ND")} -> 12 | T12: =VLOOKUP(M12,Aggregate!P:X,9,FALSE()) -> 113.06279 | V12: =IFERROR(VLOOKUP(DraftSheet!$W12,Aggregate!$AD:$AO,11,FALSE()),"") -> 2 | W12: =Aggregate!AD10 -> A.J. Brown | X12: =VLOOKUP(DraftSheet!$W12,Aggregate!AD:AO,4,FALSE()) -> NE/11 | Y12: =IFERROR(VLOOKUP(DraftSheet!$W12,Aggregate!$AD:$AO,8,FALSE()),"") -> 176.07863 | Z12: =IF(Scoring!$K$6="Auction",IFERROR(VLOOKUP(DraftSheet!$W12,Aggregate!$AD:$AO,10,FALSE()),""),IFERROR(VLOOKUP(DraftSheet!$W12,Aggregate!$AD:$AO,9,FALSE()),"")) -> 25.776334 | AA12: =SUMIFS($AD13:AD$84,$AC13:AC$84,"<>x",$AC13:AC$84,"<>o",$AD13:AD$84,">0")/Aggregate!$AL$1 -> 0.67509596 | AB12: {=IFERROR(INDEX(ECR!$K:$K,MATCH(DraftSheet!$W12,ECR!$C:$C,0)),"ND")} -> 15 | AD12: =VLOOKUP(W12,Aggregate!AD:AL,9,FALSE()) -> 94.557703
B13: =IFERROR(VLOOKUP(DraftSheet!$C13,Aggregate!$B:$M,11,FALSE()),"") -> 4 | C13: =Aggregate!B13 -> Brock Purdy | D13: =VLOOKUP(DraftSheet!$C13,Aggregate!B:M,4,FALSE()) -> SF/8 | E13: =IFERROR(VLOOKUP(DraftSheet!$C13,Aggregate!$B:$M,8,FALSE()),"") -> 221.64681 | F13: =IF(Scoring!$K$6="Auction",IFERROR(VLOOKUP(DraftSheet!$C13,Aggregate!$B:$M,10,FALSE()),""),IFERROR(VLOOKUP(DraftSheet!$C13,Aggregate!$B:$M,9,FALSE()),"")) -> 1 | G13: =SUMIFS($J14:J$44,$I14:I$44,"<>x",$I14:I$44,"<>o",$J14:J$44,">0")/Aggregate!$J$1 -> 0.057347574 | H13: {=IFERROR(INDEX(ECR!$K:$K,MATCH(DraftSheet!$C13,ECR!$C:$C,0)),"ND")} -> 91 | J13: =VLOOKUP(C13,Aggregate!B:J,9,FALSE()) -> 0 | L13: =IFERROR(VLOOKUP(DraftSheet!$M13,Aggregate!$P:$AA,11,FALSE()),"") -> 3 | M13: =Aggregate!P9 -> Saquon Barkley | N13: =VLOOKUP(DraftSheet!$M13,Aggregate!P:AA,4,FALSE()) -> PHI/10 | O13: =IFERROR(VLOOKUP(DraftSheet!$M13,Aggregate!$P:$AA,8,FALSE()),"") -> 188.48853 | P13: =IF(Scoring!$K$6="Auction",IFERROR(VLOOKUP(DraftSheet!$M13,Aggregate!$P:$AA,10,FALSE()),""),IFERROR(VLOOKUP(DraftSheet!$M13,Aggregate!$P:$AA,9,FALSE()),"")) -> 29.848161 | Q13: =SUMIFS($T14:T$84,$S14:S$84,"<>x",$S14:S$84,"<>o",$T14:T$84,">0")/Aggregate!$X$1 -> 0.62272588 | R13: {=IFERROR(INDEX(ECR!$K:$K,MATCH(DraftSheet!$M13,ECR!$C:$C,0)),"ND")} -> 14 | T13: =VLOOKUP(M13,Aggregate!P:X,9,FALSE()) -> 110.09764 | V13: =IFERROR(VLOOKUP(DraftSheet!$W13,Aggregate!$AD:$AO,11,FALSE()),"") -> 2 | W13: =Aggregate!AD15 -> Rashee Rice | X13: =VLOOKUP(DraftSheet!$W13,Aggregate!AD:AO,4,FALSE()) -> KC/5 | Y13: =IFERROR(VLOOKUP(DraftSheet!$W13,Aggregate!$AD:$AO,8,FALSE()),"") -> 174.72545 | Z13: =IF(Scoring!$K$6="Auction",IFERROR(VLOOKUP(DraftSheet!$W13,Aggregate!$AD:$AO,10,FALSE()),""),IFERROR(VLOOKUP(DraftSheet!$W13,Aggregate!$AD:$AO,9,FALSE()),"")) -> 25.421768 | AA13: =SUMIFS($AD14:AD$84,$AC14:AC$84,"<>x",$AC14:AC$84,"<>o",$AD14:AD$84,">0")/Aggregate!$AL$1 -> 0.64469759 | AB13: {=IFERROR(INDEX(ECR!$K:$K,MATCH(DraftSheet!$W13,ECR!$C:$C,0)),"ND")} -> 29 | AD13: =VLOOKUP(W13,Aggregate!AD:AL,9,FALSE()) -> 93.204521
B14: =IFERROR(VLOOKUP(DraftSheet!$C14,Aggregate!$B:$M,11,FALSE()),"") -> 4 | C14: =Aggregate!B12 -> Dak Prescott | D14: =VLOOKUP(DraftSheet!$C14,Aggregate!B:M,4,FALSE()) -> DAL/14 | E14: =IFERROR(VLOOKUP(DraftSheet!$C14,Aggregate!$B:$M,8,FALSE()),"") -> 226.10296 | F14: =IF(Scoring!$K$6="Auction",IFERROR(VLOOKUP(DraftSheet!$C14,Aggregate!$B:$M,10,FALSE()),""),IFERROR(VLOOKUP(DraftSheet!$C14,Aggregate!$B:$M,9,FALSE()),"")) -> 2.167618 | G14: =SUMIFS($J15:J$44,$I15:I$44,"<>x",$I15:I$44,"<>o",$J15:J$44,">0")/Aggregate!$J$1 -> 0.034166757 | H14: {=IFERROR(INDEX(ECR!$K:$K,MATCH(DraftSheet!$C14,ECR!$C:$C,0)),"ND")} -> 77 | J14: =VLOOKUP(C14,Aggregate!B:J,9,FALSE()) -> 4.4561587 | L14: =IFERROR(VLOOKUP(DraftSheet!$M14,Aggregate!$P:$AA,11,FALSE()),"") -> 3 | M14: =Aggregate!P13 -> Kenneth Walker III | N14: =VLOOKUP(DraftSheet!$M14,Aggregate!P:AA,4,FALSE()) -> KC/5 | O14: =IFERROR(VLOOKUP(DraftSheet!$M14,Aggregate!$P:$AA,8,FALSE()),"") -> 178.87723 | P14: =IF(Scoring!$K$6="Auction",IFERROR(VLOOKUP(DraftSheet!$M14,Aggregate!$P:$AA,10,FALSE()),""),IFERROR(VLOOKUP(DraftSheet!$M14,Aggregate!$P:$AA,9,FALSE()),"")) -> 27.329775 | Q14: =SUMIFS($T15:T$84,$S15:S$84,"<>x",$S15:S$84,"<>o",$T15:T$84,">0")/Aggregate!$X$1 -> 0.59146291 | R14: {=IFERROR(INDEX(ECR!$K:$K,MATCH(DraftSheet!$M14,ECR!$C:$C,0)),"ND")} -> 21 | T14: =VLOOKUP(M14,Aggregate!P:X,9,FALSE()) -> 100.48634 | V14: =IFERROR(VLOOKUP(DraftSheet!$W14,Aggregate!$AD:$AO,11,FALSE()),"") -> 2 | W14: =Aggregate!AD12 -> George Pickens | X14: =VLOOKUP(DraftSheet!$W14,Aggregate!AD:AO,4,FALSE()) -> DAL/14 | Y14: =IFERROR(VLOOKUP(DraftSheet!$W14,Aggregate!$AD:$AO,8,FALSE()),"") -> 173.13933 | Z14: =IF(Scoring!$K$6="Auction",IFERROR(VLOOKUP(DraftSheet!$W14,Aggregate!$AD:$AO,10,FALSE()),""),IFERROR(VLOOKUP(DraftSheet!$W14,Aggregate!$AD:$AO,9,FALSE()),"")) -> 25.006168 | AA14: =SUMIFS($AD15:AD$84,$AC15:AC$84,"<>x",$AC15:AC$84,"<>o",$AD15:AD$84,">0")/Aggregate!$AL$1 -> 0.61481653 | AB14: {=IFERROR(INDEX(ECR!$K:$K,MATCH(DraftSheet!$W14,ECR!$C:$C,0)),"ND")} -> 23 | AD14: =VLOOKUP(W14,Aggregate!AD:AL,9,FALSE()) -> 91.618401
B15: =IFERROR(VLOOKUP(DraftSheet!$C15,Aggregate!$B:$M,11,FALSE()),"") -> 4 | C15: =Aggregate!B9 -> Caleb Williams | D15: =VLOOKUP(DraftSheet!$C15,Aggregate!B:M,4,FALSE()) -> CHI/10 | E15: =IFERROR(VLOOKUP(DraftSheet!$C15,Aggregate!$B:$M,8,FALSE()),"") -> 227.06499 | F15: =IF(Scoring!$K$6="Auction",IFERROR(VLOOKUP(DraftSheet!$C15,Aggregate!$B:$M,10,FALSE()),""),IFERROR(VLOOKUP(DraftSheet!$C15,Aggregate!$B:$M,9,FALSE()),"")) -> 2.4196901 | G15: =SUMIFS($J16:J$44,$I16:I$44,"<>x",$I16:I$44,"<>o",$J16:J$44,">0")/Aggregate!$J$1 -> 0.005981532 | H15: {=IFERROR(INDEX(ECR!$K:$K,MATCH(DraftSheet!$C15,ECR!$C:$C,0)),"ND")} -> 67 | J15: =VLOOKUP(C15,Aggregate!B:J,9,FALSE()) -> 5.4181799 | L15: =IFERROR(VLOOKUP(DraftSheet!$M15,Aggregate!$P:$AA,11,FALSE()),"") -> 3 | M15: =Aggregate!P14 -> Ashton Jeanty | N15: =VLOOKUP(DraftSheet!$M15,Aggregate!P:AA,4,FALSE()) -> LV/13 | O15: =IFERROR(VLOOKUP(DraftSheet!$M15,Aggregate!$P:$AA,8,FALSE()),"") -> 178.21088 | P15: =IF(Scoring!$K$6="Auction",IFERROR(VLOOKUP(DraftSheet!$M15,Aggregate!$P:$AA,10,FALSE()),""),IFERROR(VLOOKUP(DraftSheet!$M15,Aggregate!$P:$AA,9,FALSE()),"")) -> 27.155177 | Q15: =SUMIFS($T16:T$84,$S16:S$84,"<>x",$S16:S$84,"<>o",$T16:T$84,">0")/Aggregate!$X$1 -> 0.56040725 | R15: {=IFERROR(INDEX(ECR!$K:$K,MATCH(DraftSheet!$M15,ECR!$C:$C,0)),"ND")} -> 22 | T15: =VLOOKUP(M15,Aggregate!P:X,9,FALSE()) -> 99.819993 | V15: =IFERROR(VLOOKUP(DraftSheet!$W15,Aggregate!$AD:$AO,11,FALSE()),"") -> 2 | W15: =Aggregate!AD13 -> Chris Olave | X15: =VLOOKUP(DraftSheet!$W15,Aggregate!AD:AO,4,FALSE()) -> NO/8 | Y15: =IFERROR(VLOOKUP(DraftSheet!$W15,Aggregate!$AD:$AO,8,FALSE()),"") -> 172.66006 | Z15: =IF(Scoring!$K$6="Auction",IFERROR(VLOOKUP(DraftSheet!$W15,Aggregate!$AD:$AO,10,FALSE()),""),IFERROR(VLOOKUP(DraftSheet!$W15,Aggregate!$AD:$AO,9,FALSE()),"")) -> 24.880588 | AA15: =SUMIFS($AD16:AD$84,$AC16:AC$84,"<>x",$AC16:AC$84,"<>o",$AD16:AD$84,">0")/Aggregate!$AL$1 -> 0.58509177 | AB15: {=IFERROR(INDEX(ECR!$K:$K,MATCH(DraftSheet!$W15,ECR!$C:$C,0)),"ND")} -> 24 | AD15: =VLOOKUP(W15,Aggregate!AD:AL,9,FALSE()) -> 91.139134
B16: =IFERROR(VLOOKUP(DraftSheet!$C16,Aggregate!$B:$M,11,FALSE()),"") -> 4 | C16: =Aggregate!B10 -> Justin Herbert | D16: =VLOOKUP(DraftSheet!$C16,Aggregate!B:M,4,FALSE()) -> LAC/7 | E16: =IFERROR(VLOOKUP(DraftSheet!$C16,Aggregate!$B:$M,8,FALSE()),"") -> 222.79666 | F16: =IF(Scoring!$K$6="Auction",IFERROR(VLOOKUP(DraftSheet!$C16,Aggregate!$B:$M,10,FALSE()),""),IFERROR(VLOOKUP(DraftSheet!$C16,Aggregate!$B:$M,9,FALSE()),"")) -> 1.3012898 | G16: =SUMIFS($J17:J$44,$I17:I$44,"<>x",$I17:I$44,"<>o",$J17:J$44,">0")/Aggregate!$J$1 -> 0 | H16: {=IFERROR(INDEX(ECR!$K:$K,MATCH(DraftSheet!$C16,ECR!$C:$C,0)),"ND")} -> 70 | J16: =VLOOKUP(C16,Aggregate!B:J,9,FALSE()) -> 1.1498584 | L16: =IFERROR(VLOOKUP(DraftSheet!$M16,Aggregate!$P:$AA,11,FALSE()),"") -> 3 | M16: =Aggregate!P19 -> Jeremiyah Love | N16: =VLOOKUP(DraftSheet!$M16,Aggregate!P:AA,4,FALSE()) -> ARI/14 | O16: =IFERROR(VLOOKUP(DraftSheet!$M16,Aggregate!$P:$AA,8,FALSE()),"") -> 176.69801 | P16: =IF(Scoring!$K$6="Auction",IFERROR(VLOOKUP(DraftSheet!$M16,Aggregate!$P:$AA,10,FALSE()),""),IFERROR(VLOOKUP(DraftSheet!$M16,Aggregate!$P:$AA,9,FALSE()),"")) -> 26.758768 | Q16: =SUMIFS($T17:T$84,$S17:S$84,"<>x",$S17:S$84,"<>o",$T17:T$84,">0")/Aggregate!$X$1 -> 0.52982227 | R16: {=IFERROR(INDEX(ECR!$K:$K,MATCH(DraftSheet!$M16,ECR!$C:$C,0)),"ND")} -> 44 | T16: =VLOOKUP(M16,Aggregate!P:X,9,FALSE()) -> 98.307118 | V16: =IFERROR(VLOOKUP(DraftSheet!$W16,Aggregate!$AD:$AO,11,FALSE()),"") -> 2 | W16: =Aggregate!AD11 -> Nico Collins | X16: =VLOOKUP(DraftSheet!$W16,Aggregate!AD:AO,4,FALSE()) -> HOU/8 | Y16: =IFERROR(VLOOKUP(DraftSheet!$W16,Aggregate!$AD:$AO,8,FALSE()),"") -> 170.2458 | Z16: =IF(Scoring!$K$6="Auction",IFERROR(VLOOKUP(DraftSheet!$W16,Aggregate!$AD:$AO,10,FALSE()),""),IFERROR(VLOOKUP(DraftSheet!$W16,Aggregate!$AD:$AO,9,FALSE()),"")) -> 24.247995 | AA16: =SUMIFS($AD17:AD$84,$AC17:AC$84,"<>x",$AC17:AC$84,"<>o",$AD17:AD$84,">0")/Aggregate!$AL$1 -> 0.55615443 | AB16: {=IFERROR(INDEX(ECR!$K:$K,MATCH(DraftSheet!$W16,ECR!$C:$C,0)),"ND")} -> 17 | AD16: =VLOOKUP(W16,Aggregate!AD:AL,9,FALSE()) -> 88.724871
B17: =IFERROR(VLOOKUP(DraftSheet!$C17,Aggregate!$B:$M,11,FALSE()),"") -> 4 | C17: =Aggregate!B16 -> Patrick Mahomes II | D17: =VLOOKUP(DraftSheet!$C17,Aggregate!B:M,4,FALSE()) -> KC/5 | E17: =IFERROR(VLOOKUP(DraftSheet!$C17,Aggregate!$B:$M,8,FALSE()),"") -> 221.32934 | F17: =IF(Scoring!$K$6="Auction",IFERROR(VLOOKUP(DraftSheet!$C17,Aggregate!$B:$M,10,FALSE()),""),IFERROR(VLOOKUP(DraftSheet!$C17,Aggregate!$B:$M,9,FALSE()),"")) -> 1 | G17: =SUMIFS($J18:J$44,$I18:I$44,"<>x",$I18:I$44,"<>o",$J18:J$44,">0")/Aggregate!$J$1 -> 0 | H17: {=IFERROR(INDEX(ECR!$K:$K,MATCH(DraftSheet!$C17,ECR!$C:$C,0)),"ND")} -> 104 | J17: =VLOOKUP(C17,Aggregate!B:J,9,FALSE()) -> -0.31746503 | L17: =IFERROR(VLOOKUP(DraftSheet!$M17,Aggregate!$P:$AA,11,FALSE()),"") -> 3 | M17: =Aggregate!P11 -> Omarion Hampton | N17: =VLOOKUP(DraftSheet!$M17,Aggregate!P:AA,4,FALSE()) -> LAC/7 | O17: =IFERROR(VLOOKUP(DraftSheet!$M17,Aggregate!$P:$AA,8,FALSE()),"") -> 176.54382 | P17: =IF(Scoring!$K$6="Auction",IFERROR(VLOOKUP(DraftSheet!$M17,Aggregate!$P:$AA,10,FALSE()),""),IFERROR(VLOOKUP(DraftSheet!$M17,Aggregate!$P:$AA,9,FALSE()),"")) -> 26.718369 | Q17: =SUMIFS($T18:T$84,$S18:S$84,"<>x",$S18:S$84,"<>o",$T18:T$84,">0")/Aggregate!$X$1 -> 0.49928526 | R17: {=IFERROR(INDEX(ECR!$K:$K,MATCH(DraftSheet!$M17,ECR!$C:$C,0)),"ND")} -> 19 | T17: =VLOOKUP(M17,Aggregate!P:X,9,FALSE()) -> 98.152934 | V17: =IFERROR(VLOOKUP(DraftSheet!$W17,Aggregate!$AD:$AO,11,FALSE()),"") -> 2 | W17: =Aggregate!AD14 -> Malik Nabers | X17: =VLOOKUP(DraftSheet!$W17,Aggregate!AD:AO,4,FALSE()) -> NYG/8 | Y17: =IFERROR(VLOOKUP(DraftSheet!$W17,Aggregate!$AD:$AO,8,FALSE()),"") -> 163.70708 | Z17: =IF(Scoring!$K$6="Auction",IFERROR(VLOOKUP(DraftSheet!$W17,Aggregate!$AD:$AO,10,FALSE()),""),IFERROR(VLOOKUP(DraftSheet!$W17,Aggregate!$AD:$AO,9,FALSE()),"")) -> 22.534697 | AA17: =SUMIFS($AD18:AD$84,$AC18:AC$84,"<>x",$AC18:AC$84,"<>o",$AD18:AD$84,">0")/Aggregate!$AL$1 -> 0.52934966 | AB17: {=IFERROR(INDEX(ECR!$K:$K,MATCH(DraftSheet!$W17,ECR!$C:$C,0)),"ND")} -> 28 | AD17: =VLOOKUP(W17,Aggregate!AD:AL,9,FALSE()) -> 82.18615
B18: =IFERROR(VLOOKUP(DraftSheet!$C18,Aggregate!$B:$M,11,FALSE()),"") -> 4 | C18: =Aggregate!B15 -> Bo Nix | D18: =VLOOKUP(DraftSheet!$C18,Aggregate!B:M,4,FALSE()) -> DEN/10 | E18: =IFERROR(VLOOKUP(DraftSheet!$C18,Aggregate!$B:$M,8,FALSE()),"") -> 217.49639 | F18: =IF(Scoring!$K$6="Auction",IFERROR(VLOOKUP(DraftSheet!$C18,Aggregate!$B:$M,10,FALSE()),""),IFERROR(VLOOKUP(DraftSheet!$C18,Aggregate!$B:$M,9,FALSE()),"")) -> 1 | G18: =SUMIFS($J19:J$44,$I19:I$44,"<>x",$I19:I$44,"<>o",$J19:J$44,">0")/Aggregate!$J$1 -> 0 | H18: {=IFERROR(INDEX(ECR!$K:$K,MATCH(DraftSheet!$C18,ECR!$C:$C,0)),"ND")} -> 103 | J18: =VLOOKUP(C18,Aggregate!B:J,9,FALSE()) -> -4.150412 | L18: =IFERROR(VLOOKUP(DraftSheet!$M18,Aggregate!$P:$AA,11,FALSE()),"") -> 3 | M18: =Aggregate!P18 -> Josh Jacobs | N18: =VLOOKUP(DraftSheet!$M18,Aggregate!P:AA,4,FALSE()) -> GB/11 | O18: =IFERROR(VLOOKUP(DraftSheet!$M18,Aggregate!$P:$AA,8,FALSE()),"") -> 173.90941 | P18: =IF(Scoring!$K$6="Auction",IFERROR(VLOOKUP(DraftSheet!$M18,Aggregate!$P:$AA,10,FALSE()),""),IFERROR(VLOOKUP(DraftSheet!$M18,Aggregate!$P:$AA,9,FALSE()),"")) -> 26.028091 | Q18: =SUMIFS($T19:T$84,$S19:S$84,"<>x",$S19:S$84,"<>o",$T19:T$84,">0")/Aggregate!$X$1 -> 0.46956786 | R18: {=IFERROR(INDEX(ECR!$K:$K,MATCH(DraftSheet!$M18,ECR!$C:$C,0)),"ND")} -> 38 | T18: =VLOOKUP(M18,Aggregate!P:X,9,FALSE()) -> 95.518523 | V18: =IFERROR(VLOOKUP(DraftSheet!$W18,Aggregate!$AD:$AO,11,FALSE()),"") -> 3 | W18: =Aggregate!AD17 -> Zay Flowers | X18: =VLOOKUP(DraftSheet!$W18,Aggregate!AD:AO,4,FALSE()) -> BAL/13 | Y18: =IFERROR(VLOOKUP(DraftSheet!$W18,Aggregate!$AD:$AO,8,FALSE()),"") -> 157.29494 | Z18: =IF(Scoring!$K$6="Auction",IFERROR(VLOOKUP(DraftSheet!$W18,Aggregate!$AD:$AO,10,FALSE()),""),IFERROR(VLOOKUP(DraftSheet!$W18,Aggregate!$AD:$AO,9,FALSE()),"")) -> 20.854566 | AA18: =SUMIFS($AD19:AD$84,$AC19:AC$84,"<>x",$AC19:AC$84,"<>o",$AD19:AD$84,">0")/Aggregate!$AL$1 -> 0.5046362 | AB18: {=IFERROR(INDEX(ECR!$K:$K,MATCH(DraftSheet!$W18,ECR!$C:$C,0)),"ND")} -> 31 | AD18: =VLOOKUP(W18,Aggregate!AD:AL,9,FALSE()) -> 75.774011
B19: =IFERROR(VLOOKUP(DraftSheet!$C19,Aggregate!$B:$M,11,FALSE()),"") -> 4 | C19: =Aggregate!B17 -> Matthew Stafford | D19: =VLOOKUP(DraftSheet!$C19,Aggregate!B:M,4,FALSE()) -> LAR/11 | E19: =IFERROR(VLOOKUP(DraftSheet!$C19,Aggregate!$B:$M,8,FALSE()),"") -> 218.85306 | F19: =IF(Scoring!$K$6="Auction",IFERROR(VLOOKUP(DraftSheet!$C19,Aggregate!$B:$M,10,FALSE()),""),IFERROR(VLOOKUP(DraftSheet!$C19,Aggregate!$B:$M,9,FALSE()),"")) -> 1 | G19: =SUMIFS($J20:J$44,$I20:I$44,"<>x",$I20:I$44,"<>o",$J20:J$44,">0")/Aggregate!$J$1 -> 0 | H19: {=IFERROR(INDEX(ECR!$K:$K,MATCH(DraftSheet!$C19,ECR!$C:$C,0)),"ND")} -> 110 | J19: =VLOOKUP(C19,Aggregate!B:J,9,FALSE()) -> -2.7937438 | L19: =IFERROR(VLOOKUP(DraftSheet!$M19,Aggregate!$P:$AA,11,FALSE()),"") -> 4 | M19: =Aggregate!P15 -> Kyren Williams | N19: =VLOOKUP(DraftSheet!$M19,Aggregate!P:AA,4,FALSE()) -> LAR/11 | O19: =IFERROR(VLOOKUP(DraftSheet!$M19,Aggregate!$P:$AA,8,FALSE()),"") -> 172.45647 | P19: =IF(Scoring!$K$6="Auction",IFERROR(VLOOKUP(DraftSheet!$M19,Aggregate!$P:$AA,10,FALSE()),""),IFERROR(VLOOKUP(DraftSheet!$M19,Aggregate!$P:$AA,9,FALSE()),"")) -> 25.647386 | Q19: =SUMIFS($T20:T$84,$S20:S$84,"<>x",$S20:S$84,"<>o",$T20:T$84,">0")/Aggregate!$X$1 -> 0.4403025 | R19: {=IFERROR(INDEX(ECR!$K:$K,MATCH(DraftSheet!$M19,ECR!$C:$C,0)),"ND")} -> 32 | T19: =VLOOKUP(M19,Aggregate!P:X,9,FALSE()) -> 94.065581 | V19: =IFERROR(VLOOKUP(DraftSheet!$W19,Aggregate!$AD:$AO,11,FALSE()),"") -> 3 | W19: =Aggregate!AD16 -> DeVonta Smith | X19: =VLOOKUP(DraftSheet!$W19,Aggregate!AD:AO,4,FALSE()) -> PHI/10 | Y19: =IFERROR(VLOOKUP(DraftSheet!$W19,Aggregate!$AD:$AO,8,FALSE()),"") -> 154.09493 | Z19: =IF(Scoring!$K$6="Auction",IFERROR(VLOOKUP(DraftSheet!$W19,Aggregate!$AD:$AO,10,FALSE()),""),IFERROR(VLOOKUP(DraftSheet!$W19,Aggregate!$AD:$AO,9,FALSE()),"")) -> 20.016088 | AA19: =SUMIFS($AD20:AD$84,$AC20:AC$84,"<>x",$AC20:AC$84,"<>o",$AD20:AD$84,">0")/Aggregate!$AL$1 -> 0.48096641 | AB19: {=IFERROR(INDEX(ECR!$K:$K,MATCH(DraftSheet!$W19,ECR!$C:$C,0)),"ND")} -> 30 | AD19: =VLOOKUP(W19,Aggregate!AD:AL,9,FALSE()) -> 72.574
B20: =IFERROR(VLOOKUP(DraftSheet!$C20,Aggregate!$B:$M,11,FALSE()),"") -> 5 | C20: =Aggregate!B18 -> Jared Goff | D20: =VLOOKUP(DraftSheet!$C20,Aggregate!B:M,4,FALSE()) -> DET/6 | E20: =IFERROR(VLOOKUP(DraftSheet!$C20,Aggregate!$B:$M,8,FALSE()),"") -> 205.68354 | F20: =IF(Scoring!$K$6="Auction",IFERROR(VLOOKUP(DraftSheet!$C20,Aggregate!$B:$M,10,FALSE()),""),IFERROR(VLOOKUP(DraftSheet!$C20,Aggregate!$B:$M,9,FALSE()),"")) -> 1 | G20: =SUMIFS($J21:J$44,$I21:I$44,"<>x",$I21:I$44,"<>o",$J21:J$44,">0")/Aggregate!$J$1 -> 0 | H20: {=IFERROR(INDEX(ECR!$K:$K,MATCH(DraftSheet!$C20,ECR!$C:$C,0)),"ND")} -> 112 | J20: =VLOOKUP(C20,Aggregate!B:J,9,FALSE()) -> -15.963263 | L20: =IFERROR(VLOOKUP(DraftSheet!$M20,Aggregate!$P:$AA,11,FALSE()),"") -> 4 | M20: =Aggregate!P17 -> Breece Hall | N20: =VLOOKUP(DraftSheet!$M20,Aggregate!P:AA,4,FALSE()) -> NYJ/13 | O20: =IFERROR(VLOOKUP(DraftSheet!$M20,Aggregate!$P:$AA,8,FALSE()),"") -> 169.89471 | P20: =IF(Scoring!$K$6="Auction",IFERROR(VLOOKUP(DraftSheet!$M20,Aggregate!$P:$AA,10,FALSE()),""),IFERROR(VLOOKUP(DraftSheet!$M20,Aggregate!$P:$AA,9,FALSE()),"")) -> 24.976144 | Q20: =SUMIFS($T21:T$84,$S21:S$84,"<>x",$S21:S$84,"<>o",$T21:T$84,">0")/Aggregate!$X$1 -> 0.41183414 | R20: {=IFERROR(INDEX(ECR!$K:$K,MATCH(DraftSheet!$M20,ECR!$C:$C,0)),"ND")} -> 36 | T20: =VLOOKUP(M20,Aggregate!P:X,9,FALSE()) -> 91.503817 | V20: =IFERROR(VLOOKUP(DraftSheet!$W20,Aggregate!$AD:$AO,11,FALSE()),"") -> 3 | W20: =Aggregate!AD19 -> Tetairoa McMillan | X20: =VLOOKUP(DraftSheet!$W20,Aggregate!AD:AO,4,FALSE()) -> CAR/5 | Y20: =IFERROR(VLOOKUP(DraftSheet!$W20,Aggregate!$AD:$AO,8,FALSE()),"") -> 150.77059 | Z20: =IF(Scoring!$K$6="Auction",IFERROR(VLOOKUP(DraftSheet!$W20,Aggregate!$AD:$AO,10,FALSE()),""),IFERROR(VLOOKUP(DraftSheet!$W20,Aggregate!$AD:$AO,9,FALSE()),"")) -> 19.145035 | AA20: =SUMIFS($AD21:AD$84,$AC21:AC$84,"<>x",$AC21:AC$84,"<>o",$AD21:AD$84,">0")/Aggregate!$AL$1 -> 0.45838084 | AB20: {=IFERROR(INDEX(ECR!$K:$K,MATCH(DraftSheet!$W20,ECR!$C:$C,0)),"ND")} -> 35 | AD20: =VLOOKUP(W20,Aggregate!AD:AL,9,FALSE()) -> 69.249667
B21: =IFERROR(VLOOKUP(DraftSheet!$C21,Aggregate!$B:$M,11,FALSE()),"") -> 5 | C21: =Aggregate!B19 -> Baker Mayfield | D21: =VLOOKUP(DraftSheet!$C21,Aggregate!B:M,4,FALSE()) -> TB/10 | E21: =IFERROR(VLOOKUP(DraftSheet!$C21,Aggregate!$B:$M,8,FALSE()),"") -> 196.40535 | F21: =IF(Scoring!$K$6="Auction",IFERROR(VLOOKUP(DraftSheet!$C21,Aggregate!$B:$M,10,FALSE()),""),IFERROR(VLOOKUP(DraftSheet!$C21,Aggregate!$B:$M,9,FALSE()),"")) -> 1 | G21: =SUMIFS($J22:J$44,$I22:I$44,"<>x",$I22:I$44,"<>o",$J22:J$44,">0")/Aggregate!$J$1 -> 0 | H21: {=IFERROR(INDEX(ECR!$K:$K,MATCH(DraftSheet!$C21,ECR!$C:$C,0)),"ND")} -> 120 | J21: =VLOOKUP(C21,Aggregate!B:J,9,FALSE()) -> -25.241452 | L21: =IFERROR(VLOOKUP(DraftSheet!$M21,Aggregate!$P:$AA,11,FALSE()),"") -> 4 | M21: =Aggregate!P16 -> Javonte Williams | N21: =VLOOKUP(DraftSheet!$M21,Aggregate!P:AA,4,FALSE()) -> DAL/14 | O21: =IFERROR(VLOOKUP(DraftSheet!$M21,Aggregate!$P:$AA,8,FALSE()),"") -> 169.56779 | P21: =IF(Scoring!$K$6="Auction",IFERROR(VLOOKUP(DraftSheet!$M21,Aggregate!$P:$AA,10,FALSE()),""),IFERROR(VLOOKUP(DraftSheet!$M21,Aggregate!$P:$AA,9,FALSE()),"")) -> 24.890485 | Q21: =SUMIFS($T22:T$84,$S22:S$84,"<>x",$S22:S$84,"<>o",$T22:T$84,">0")/Aggregate!$X$1 -> 0.38346749 | R21: {=IFERROR(INDEX(ECR!$K:$K,MATCH(DraftSheet!$M21,ECR!$C:$C,0)),"ND")} -> 34 | T21: =VLOOKUP(M21,Aggregate!P:X,9,FALSE()) -> 91.176905 | V21: =IFERROR(VLOOKUP(DraftSheet!$W21,Aggregate!$AD:$AO,11,FALSE()),"") -> 3 | W21: =Aggregate!AD20 -> Garrett Wilson | X21: =VLOOKUP(DraftSheet!$W21,Aggregate!AD:AO,4,FALSE()) -> NYJ/13 | Y21: =IFERROR(VLOOKUP(DraftSheet!$W21,Aggregate!$AD:$AO,8,FALSE()),"") -> 149.87406 | Z21: =IF(Scoring!$K$6="Auction",IFERROR(VLOOKUP(DraftSheet!$W21,Aggregate!$AD:$AO,10,FALSE()),""),IFERROR(VLOOKUP(DraftSheet!$W21,Aggregate!$AD:$AO,9,FALSE()),"")) -> 18.910122 | AA21: =SUMIFS($AD22:AD$84,$AC22:AC$84,"<>x",$AC22:AC$84,"<>o",$AD22:AD$84,">0")/Aggregate!$AL$1 -> 0.43608767 | AB21: {=IFERROR(INDEX(ECR!$K:$K,MATCH(DraftSheet!$W21,ECR!$C:$C,0)),"ND")} -> 39 | AD21: =VLOOKUP(W21,Aggregate!AD:AL,9,FALSE()) -> 68.353134
B22: =IFERROR(VLOOKUP(DraftSheet!$C22,Aggregate!$B:$M,11,FALSE()),"") -> 6 | C22: =Aggregate!B20 -> Kyler Murray | D22: =VLOOKUP(DraftSheet!$C22,Aggregate!B:M,4,FALSE()) -> MIN/6 | E22: =IFERROR(VLOOKUP(DraftSheet!$C22,Aggregate!$B:$M,8,FALSE()),"") -> 192.78124 | F22: =IF(Scoring!$K$6="Auction",IFERROR(VLOOKUP(DraftSheet!$C22,Aggregate!$B:$M,10,FALSE()),""),IFERROR(VLOOKUP(DraftSheet!$C22,Aggregate!$B:$M,9,FALSE()),"")) -> 1 | G22: =SUMIFS($J23:J$44,$I23:I$44,"<>x",$I23:I$44,"<>o",$J23:J$44,">0")/Aggregate!$J$1 -> 0 | H22: {=IFERROR(INDEX(ECR!$K:$K,MATCH(DraftSheet!$C22,ECR!$C:$C,0)),"ND")} -> 122 | J22: =VLOOKUP(C22,Aggregate!B:J,9,FALSE()) -> -28.865568 | L22: =IFERROR(VLOOKUP(DraftSheet!$M22,Aggregate!$P:$AA,11,FALSE()),"") -> 4 | M22: =Aggregate!P20 -> Travis Etienne Jr. | N22: =VLOOKUP(DraftSheet!$M22,Aggregate!P:AA,4,FALSE()) -> NO/8 | O22: =IFERROR(VLOOKUP(DraftSheet!$M22,Aggregate!$P:$AA,8,FALSE()),"") -> 163.64132 | P22: =IF(Scoring!$K$6="Auction",IFERROR(VLOOKUP(DraftSheet!$M22,Aggregate!$P:$AA,10,FALSE()),""),IFERROR(VLOOKUP(DraftSheet!$M22,Aggregate!$P:$AA,9,FALSE()),"")) -> 23.337611 | Q22: =SUMIFS($T23:T$84,$S23:S$84,"<>x",$S23:S$84,"<>o",$T23:T$84,">0")/Aggregate!$X$1 -> 0.35694467 | R22: {=IFERROR(INDEX(ECR!$K:$K,MATCH(DraftSheet!$M22,ECR!$C:$C,0)),"ND")} -> 46 | T22: =VLOOKUP(M22,Aggregate!P:X,9,FALSE()) -> 85.250434 | V22: =IFERROR(VLOOKUP(DraftSheet!$W22,Aggregate!$AD:$AO,11,FALSE()),"") -> 3 | W22: =Aggregate!AD18 -> Tee Higgins | X22: =VLOOKUP(DraftSheet!$W22,Aggregate!AD:AO,4,FALSE()) -> CIN/6 | Y22: =IFERROR(VLOOKUP(DraftSheet!$W22,Aggregate!$AD:$AO,8,FALSE()),"") -> 148.02104 | Z22: =IF(Scoring!$K$6="Auction",IFERROR(VLOOKUP(DraftSheet!$W22,Aggregate!$AD:$AO,10,FALSE()),""),IFERROR(VLOOKUP(DraftSheet!$W22,Aggregate!$AD:$AO,9,FALSE()),"")) -> 18.424587 | AA22: =SUMIFS($AD23:AD$84,$AC23:AC$84,"<>x",$AC23:AC$84,"<>o",$AD23:AD$84,">0")/Aggregate!$AL$1 -> 0.41439886 | AB22: {=IFERROR(INDEX(ECR!$K:$K,MATCH(DraftSheet!$W22,ECR!$C:$C,0)),"ND")} -> 33 | AD22: =VLOOKUP(W22,Aggregate!AD:AL,9,FALSE()) -> 66.500112
B23: =IFERROR(VLOOKUP(DraftSheet!$C23,Aggregate!$B:$M,11,FALSE()),"") -> 6 | C23: =Aggregate!B22 -> Tyler Shough | D23: =VLOOKUP(DraftSheet!$C23,Aggregate!B:M,4,FALSE()) -> NO/8 | E23: =IFERROR(VLOOKUP(DraftSheet!$C23,Aggregate!$B:$M,8,FALSE()),"") -> 185.27069 | F23: =IF(Scoring!$K$6="Auction",IFERROR(VLOOKUP(DraftSheet!$C23,Aggregate!$B:$M,10,FALSE()),""),IFERROR(VLOOKUP(DraftSheet!$C23,Aggregate!$B:$M,9,FALSE()),"")) -> 1 | G23: =SUMIFS($J24:J$44,$I24:I$44,"<>x",$I24:I$44,"<>o",$J24:J$44,">0")/Aggregate!$J$1 -> 0 | H23: {=IFERROR(INDEX(ECR!$K:$K,MATCH(DraftSheet!$C23,ECR!$C:$C,0)),"ND")} -> 127 | J23: =VLOOKUP(C23,Aggregate!B:J,9,FALSE()) -> -36.37612 | L23: =IFERROR(VLOOKUP(DraftSheet!$M23,Aggregate!$P:$AA,11,FALSE()),"") -> 4 | M23: =Aggregate!P22 -> Cam Skattebo | N23: =VLOOKUP(DraftSheet!$M23,Aggregate!P:AA,4,FALSE()) -> NYG/8 | O23: =IFERROR(VLOOKUP(DraftSheet!$M23,Aggregate!$P:$AA,8,FALSE()),"") -> 161.73338 | P23: =IF(Scoring!$K$6="Auction",IFERROR(VLOOKUP(DraftSheet!$M23,Aggregate!$P:$AA,10,FALSE()),""),IFERROR(VLOOKUP(DraftSheet!$M23,Aggregate!$P:$AA,9,FALSE()),"")) -> 22.837686 | Q23: =SUMIFS($T24:T$84,$S24:S$84,"<>x",$S24:S$84,"<>o",$T24:T$84,">0")/Aggregate!$X$1 -> 0.33101543 | R23: {=IFERROR(INDEX(ECR!$K:$K,MATCH(DraftSheet!$M23,ECR!$C:$C,0)),"ND")} -> 52 | T23: =VLOOKUP(M23,Aggregate!P:X,9,FALSE()) -> 83.342493 | V23: =IFERROR(VLOOKUP(DraftSheet!$W23,Aggregate!$AD:$AO,11,FALSE()),"") -> 3 | W23: =Aggregate!AD23 -> Emeka Egbuka | X23: =VLOOKUP(DraftSheet!$W23,Aggregate!AD:AO,4,FALSE()) -> TB/10 | Y23: =IFERROR(VLOOKUP(DraftSheet!$W23,Aggregate!$AD:$AO,8,FALSE()),"") -> 144.3515 | Z23: =IF(Scoring!$K$6="Auction",IFERROR(VLOOKUP(DraftSheet!$W23,Aggregate!$AD:$AO,10,FALSE()),""),IFERROR(VLOOKUP(DraftSheet!$W23,Aggregate!$AD:$AO,9,FALSE()),"")) -> 17.463082 | AA23: =SUMIFS($AD24:AD$84,$AC24:AC$84,"<>x",$AC24:AC$84,"<>o",$AD24:AD$84,">0")/Aggregate!$AL$1 -> 0.39390686 | AB23: {=IFERROR(INDEX(ECR!$K:$K,MATCH(DraftSheet!$W23,ECR!$C:$C,0)),"ND")} -> 43 | AD23: =VLOOKUP(W23,Aggregate!AD:AL,9,FALSE()) -> 62.830574
B24: =IFERROR(VLOOKUP(DraftSheet!$C24,Aggregate!$B:$M,11,FALSE()),"") -> 6 | C24: =Aggregate!B21 -> Jordan Love | D24: =VLOOKUP(DraftSheet!$C24,Aggregate!B:M,4,FALSE()) -> GB/11 | E24: =IFERROR(VLOOKUP(DraftSheet!$C24,Aggregate!$B:$M,8,FALSE()),"") -> 184.55501 | F24: =IF(Scoring!$K$6="Auction",IFERROR(VLOOKUP(DraftSheet!$C24,Aggregate!$B:$M,10,FALSE()),""),IFERROR(VLOOKUP(DraftSheet!$C24,Aggregate!$B:$M,9,FALSE()),"")) -> 1 | G24: =SUMIFS($J25:J$44,$I25:I$44,"<>x",$I25:I$44,"<>o",$J25:J$44,">0")/Aggregate!$J$1 -> 0 | H24: {=IFERROR(INDEX(ECR!$K:$K,MATCH(DraftSheet!$C24,ECR!$C:$C,0)),"ND")} -> 123 | J24: =VLOOKUP(C24,Aggregate!B:J,9,FALSE()) -> -37.091794 | L24: =IFERROR(VLOOKUP(DraftSheet!$M24,Aggregate!$P:$AA,11,FALSE()),"") -> 4 | M24: =Aggregate!P21 -> D'Andre Swift | N24: =VLOOKUP(DraftSheet!$M24,Aggregate!P:AA,4,FALSE()) -> CHI/10 | O24: =IFERROR(VLOOKUP(DraftSheet!$M24,Aggregate!$P:$AA,8,FALSE()),"") -> 158.25015 | P24: =IF(Scoring!$K$6="Auction",IFERROR(VLOOKUP(DraftSheet!$M24,Aggregate!$P:$AA,10,FALSE()),""),IFERROR(VLOOKUP(DraftSheet!$M24,Aggregate!$P:$AA,9,FALSE()),"")) -> 21.924997 | Q24: =SUMIFS($T25:T$84,$S25:S$84,"<>x",$S25:S$84,"<>o",$T25:T$84,">0")/Aggregate!$X$1 -> 0.30616989 | R24: {=IFERROR(INDEX(ECR!$K:$K,MATCH(DraftSheet!$M24,ECR!$C:$C,0)),"ND")} -> 49 | T24: =VLOOKUP(M24,Aggregate!P:X,9,FALSE()) -> 79.859258 | V24: =IFERROR(VLOOKUP(DraftSheet!$W24,Aggregate!$AD:$AO,11,FALSE()),"") -> 3 | W24: =Aggregate!AD25 -> Davante Adams | X24: =VLOOKUP(DraftSheet!$W24,Aggregate!AD:AO,4,FALSE()) -> LAR/11 | Y24: =IFERROR(VLOOKUP(DraftSheet!$W24,Aggregate!$AD:$AO,8,FALSE()),"") -> 140.60684 | Z24: =IF(Scoring!$K$6="Auction",IFERROR(VLOOKUP(DraftSheet!$W24,Aggregate!$AD:$AO,10,FALSE()),""),IFERROR(VLOOKUP(DraftSheet!$W24,Aggregate!$AD:$AO,9,FALSE()),"")) -> 16.481893 | AA24: =SUMIFS($AD25:AD$84,$AC25:AC$84,"<>x",$AC25:AC$84,"<>o",$AD25:AD$84,">0")/Aggregate!$AL$1 -> 0.37463616 | AB24: {=IFERROR(INDEX(ECR!$K:$K,MATCH(DraftSheet!$W24,ECR!$C:$C,0)),"ND")} -> 48 | AD24: =VLOOKUP(W24,Aggregate!AD:AL,9,FALSE()) -> 59.085912
B25: =IFERROR(VLOOKUP(DraftSheet!$C25,Aggregate!$B:$M,11,FALSE()),"") -> 7 | C25: =Aggregate!B23 -> Malik Willis | D25: =VLOOKUP(DraftSheet!$C25,Aggregate!B:M,4,FALSE()) -> MIA/6 | E25: =IFERROR(VLOOKUP(DraftSheet!$C25,Aggregate!$B:$M,8,FALSE()),"") -> 176.08508 | F25: =IF(Scoring!$K$6="Auction",IFERROR(VLOOKUP(DraftSheet!$C25,Aggregate!$B:$M,10,FALSE()),""),IFERROR(VLOOKUP(DraftSheet!$C25,Aggregate!$B:$M,9,FALSE()),"")) -> 1 | G25: =SUMIFS($J26:J$44,$I26:I$44,"<>x",$I26:I$44,"<>o",$J26:J$44,">0")/Aggregate!$J$1 -> 0 | H25: {=IFERROR(INDEX(ECR!$K:$K,MATCH(DraftSheet!$C25,ECR!$C:$C,0)),"ND")} -> 137 | J25: =VLOOKUP(C25,Aggregate!B:J,9,FALSE()) -> -45.561722 | L25: =IFERROR(VLOOKUP(DraftSheet!$M25,Aggregate!$P:$AA,11,FALSE()),"") -> 4 | M25: =Aggregate!P23 -> Bucky Irving | N25: =VLOOKUP(DraftSheet!$M25,Aggregate!P:AA,4,FALSE()) -> TB/10 | O25: =IFERROR(VLOOKUP(DraftSheet!$M25,Aggregate!$P:$AA,8,FALSE()),"") -> 156.50471 | P25: =IF(Scoring!$K$6="Auction",IFERROR(VLOOKUP(DraftSheet!$M25,Aggregate!$P:$AA,10,FALSE()),""),IFERROR(VLOOKUP(DraftSheet!$M25,Aggregate!$P:$AA,9,FALSE()),"")) -> 21.46765 | Q25: =SUMIFS($T26:T$84,$S26:S$84,"<>x",$S26:S$84,"<>o",$T26:T$84,">0")/Aggregate!$X$1 -> 0.28186738 | R25: {=IFERROR(INDEX(ECR!$K:$K,MATCH(DraftSheet!$M25,ECR!$C:$C,0)),"ND")} -> 55 | T25: =VLOOKUP(M25,Aggregate!P:X,9,FALSE()) -> 78.113817 | V25: =IFERROR(VLOOKUP(DraftSheet!$W25,Aggregate!$AD:$AO,11,FALSE()),"") -> 3 | W25: =Aggregate!AD22 -> Ladd McConkey | X25: =VLOOKUP(DraftSheet!$W25,Aggregate!AD:AO,4,FALSE()) -> LAC/7 | Y25: =IFERROR(VLOOKUP(DraftSheet!$W25,Aggregate!$AD:$AO,8,FALSE()),"") -> 139.71119 | Z25: =IF(Scoring!$K$6="Auction",IFERROR(VLOOKUP(DraftSheet!$W25,Aggregate!$AD:$AO,10,FALSE()),""),IFERROR(VLOOKUP(DraftSheet!$W25,Aggregate!$AD:$AO,9,FALSE()),"")) -> 16.247211 | AA25: =SUMIFS($AD26:AD$84,$AC26:AC$84,"<>x",$AC26:AC$84,"<>o",$AD26:AD$84,">0")/Aggregate!$AL$1 -> 0.35565759 | AB25: {=IFERROR(INDEX(ECR!$K:$K,MATCH(DraftSheet!$W25,ECR!$C:$C,0)),"ND")} -> 41 | AD25: =VLOOKUP(W25,Aggregate!AD:AL,9,FALSE()) -> 58.190258
B26: =IFERROR(VLOOKUP(DraftSheet!$C26,Aggregate!$B:$M,11,FALSE()),"") -> 7 | C26: =Aggregate!B27 -> Daniel Jones | D26: =VLOOKUP(DraftSheet!$C26,Aggregate!B:M,4,FALSE()) -> IND/13 | E26: =IFERROR(VLOOKUP(DraftSheet!$C26,Aggregate!$B:$M,8,FALSE()),"") -> 177.24875 | F26: =IF(Scoring!$K$6="Auction",IFERROR(VLOOKUP(DraftSheet!$C26,Aggregate!$B:$M,10,FALSE()),""),IFERROR(VLOOKUP(DraftSheet!$C26,Aggregate!$B:$M,9,FALSE()),"")) -> 1 | G26: =SUMIFS($J27:J$44,$I27:I$44,"<>x",$I27:I$44,"<>o",$J27:J$44,">0")/Aggregate!$J$1 -> 0 | H26: {=IFERROR(INDEX(ECR!$K:$K,MATCH(DraftSheet!$C26,ECR!$C:$C,0)),"ND")} -> 157 | J26: =VLOOKUP(C26,Aggregate!B:J,9,FALSE()) -> -44.398053 | L26: =IFERROR(VLOOKUP(DraftSheet!$M26,Aggregate!$P:$AA,11,FALSE()),"") -> 4 | M26: =Aggregate!P24 -> Quinshon Judkins | N26: =VLOOKUP(DraftSheet!$M26,Aggregate!P:AA,4,FALSE()) -> CLE/11 | O26: =IFERROR(VLOOKUP(DraftSheet!$M26,Aggregate!$P:$AA,8,FALSE()),"") -> 152.89529 | P26: =IF(Scoring!$K$6="Auction",IFERROR(VLOOKUP(DraftSheet!$M26,Aggregate!$P:$AA,10,FALSE()),""),IFERROR(VLOOKUP(DraftSheet!$M26,Aggregate!$P:$AA,9,FALSE()),"")) -> 20.5219 | Q26: =SUMIFS($T27:T$84,$S27:S$84,"<>x",$S27:S$84,"<>o",$T27:T$84,">0")/Aggregate!$X$1 -> 0.25868783 | R26: {=IFERROR(INDEX(ECR!$K:$K,MATCH(DraftSheet!$M26,ECR!$C:$C,0)),"ND")} -> 56 | T26: =VLOOKUP(M26,Aggregate!P:X,9,FALSE()) -> 74.504405 | V26: =IFERROR(VLOOKUP(DraftSheet!$W26,Aggregate!$AD:$AO,11,FALSE()),"") -> 3 | W26: =Aggregate!AD24 -> Terry McLaurin | X26: =VLOOKUP(DraftSheet!$W26,Aggregate!AD:AO,4,FALSE()) -> WAS/7 | Y26: =IFERROR(VLOOKUP(DraftSheet!$W26,Aggregate!$AD:$AO,8,FALSE()),"") -> 137.38664 | Z26: =IF(Scoring!$K$6="Auction",IFERROR(VLOOKUP(DraftSheet!$W26,Aggregate!$AD:$AO,10,FALSE()),""),IFERROR(VLOOKUP(DraftSheet!$W26,Aggregate!$AD:$AO,9,FALSE()),"")) -> 15.638125 | AA26: =SUMIFS($AD27:AD$84,$AC27:AC$84,"<>x",$AC27:AC$84,"<>o",$AD27:AD$84,">0")/Aggregate!$AL$1 -> 0.33743715 | AB26: {=IFERROR(INDEX(ECR!$K:$K,MATCH(DraftSheet!$W26,ECR!$C:$C,0)),"ND")} -> 47 | AD26: =VLOOKUP(W26,Aggregate!AD:AL,9,FALSE()) -> 55.86571
B27: =IFERROR(VLOOKUP(DraftSheet!$C27,Aggregate!$B:$M,11,FALSE()),"") -> 7 | C27: =Aggregate!B24 -> Sam Darnold | D27: =VLOOKUP(DraftSheet!$C27,Aggregate!B:M,4,FALSE()) -> SEA/11 | E27: =IFERROR(VLOOKUP(DraftSheet!$C27,Aggregate!$B:$M,8,FALSE()),"") -> 173.38499 | F27: =IF(Scoring!$K$6="Auction",IFERROR(VLOOKUP(DraftSheet!$C27,Aggregate!$B:$M,10,FALSE()),""),IFERROR(VLOOKUP(DraftSheet!$C27,Aggregate!$B:$M,9,FALSE()),"")) -> 1 | G27: =SUMIFS($J28:J$44,$I28:I$44,"<>x",$I28:I$44,"<>o",$J28:J$44,">0")/Aggregate!$J$1 -> 0 | H27: {=IFERROR(INDEX(ECR!$K:$K,MATCH(DraftSheet!$C27,ECR!$C:$C,0)),"ND")} -> 142 | J27: =VLOOKUP(C27,Aggregate!B:J,9,FALSE()) -> -48.261815 | L27: =IFERROR(VLOOKUP(DraftSheet!$M27,Aggregate!$P:$AA,11,FALSE()),"") -> 5 | M27: =Aggregate!P26 -> Bhayshul Tuten | N27: =VLOOKUP(DraftSheet!$M27,Aggregate!P:AA,4,FALSE()) -> JAC/7 | O27: =IFERROR(VLOOKUP(DraftSheet!$M27,Aggregate!$P:$AA,8,FALSE()),"") -> 147.64936 | P27: =IF(Scoring!$K$6="Auction",IFERROR(VLOOKUP(DraftSheet!$M27,Aggregate!$P:$AA,10,FALSE()),""),IFERROR(VLOOKUP(DraftSheet!$M27,Aggregate!$P:$AA,9,FALSE()),"")) -> 19.147342 | Q27: =SUMIFS($T28:T$84,$S28:S$84,"<>x",$S28:S$84,"<>o",$T28:T$84,">0")/Aggregate!$X$1 -> 0.23714036 | R27: {=IFERROR(INDEX(ECR!$K:$K,MATCH(DraftSheet!$M27,ECR!$C:$C,0)),"ND")} -> 64 | T27: =VLOOKUP(M27,Aggregate!P:X,9,FALSE()) -> 69.258472 | V27: =IFERROR(VLOOKUP(DraftSheet!$W27,Aggregate!$AD:$AO,11,FALSE()),"") -> 3 | W27: =Aggregate!AD21 -> Jaylen Waddle | X27: =VLOOKUP(DraftSheet!$W27,Aggregate!AD:AO,4,FALSE()) -> DEN/10 | Y27: =IFERROR(VLOOKUP(DraftSheet!$W27,Aggregate!$AD:$AO,8,FALSE()),"") -> 136.69467 | Z27: =IF(Scoring!$K$6="Auction",IFERROR(VLOOKUP(DraftSheet!$W27,Aggregate!$AD:$AO,10,FALSE()),""),IFERROR(VLOOKUP(DraftSheet!$W27,Aggregate!$AD:$AO,9,FALSE()),"")) -> 15.456814 | AA27: =SUMIFS($AD28:AD$84,$AC28:AC$84,"<>x",$AC28:AC$84,"<>o",$AD28:AD$84,">0")/Aggregate!$AL$1 -> 0.31944241 | AB27: {=IFERROR(INDEX(ECR!$K:$K,MATCH(DraftSheet!$W27,ECR!$C:$C,0)),"ND")} -> 40 | AD27: =VLOOKUP(W27,Aggregate!AD:AL,9,FALSE()) -> 55.173744
B28: =IFERROR(VLOOKUP(DraftSheet!$C28,Aggregate!$B:$M,11,FALSE()),"") -> 7 | C28: =Aggregate!B25 -> C.J. Stroud | D28: =VLOOKUP(DraftSheet!$C28,Aggregate!B:M,4,FALSE()) -> HOU/8 | E28: =IFERROR(VLOOKUP(DraftSheet!$C28,Aggregate!$B:$M,8,FALSE()),"") -> 168.67489 | F28: =IF(Scoring!$K$6="Auction",IFERROR(VLOOKUP(DraftSheet!$C28,Aggregate!$B:$M,10,FALSE()),""),IFERROR(VLOOKUP(DraftSheet!$C28,Aggregate!$B:$M,9,FALSE()),"")) -> 1 | G28: =SUMIFS($J29:J$44,$I29:I$44,"<>x",$I29:I$44,"<>o",$J29:J$44,">0")/Aggregate!$J$1 -> 0 | H28: {=IFERROR(INDEX(ECR!$K:$K,MATCH(DraftSheet!$C28,ECR!$C:$C,0)),"ND")} -> 147 | J28: =VLOOKUP(C28,Aggregate!B:J,9,FALSE()) -> -52.971911 | L28: =IFERROR(VLOOKUP(DraftSheet!$M28,Aggregate!$P:$AA,11,FALSE()),"") -> 5 | M28: =Aggregate!P28 -> Jadarian Price | N28: =VLOOKUP(DraftSheet!$M28,Aggregate!P:AA,4,FALSE()) -> SEA/11 | O28: =IFERROR(VLOOKUP(DraftSheet!$M28,Aggregate!$P:$AA,8,FALSE()),"") -> 145.73356 | P28: =IF(Scoring!$K$6="Auction",IFERROR(VLOOKUP(DraftSheet!$M28,Aggregate!$P:$AA,10,FALSE()),""),IFERROR(VLOOKUP(DraftSheet!$M28,Aggregate!$P:$AA,9,FALSE()),"")) -> 18.645358 | Q28: =SUMIFS($T29:T$84,$S29:S$84,"<>x",$S29:S$84,"<>o",$T29:T$84,">0")/Aggregate!$X$1 -> 0.21618894 | R28: {=IFERROR(INDEX(ECR!$K:$K,MATCH(DraftSheet!$M28,ECR!$C:$C,0)),"ND")} -> 66 | T28: =VLOOKUP(M28,Aggregate!P:X,9,FALSE()) -> 67.342672 | V28: =IFERROR(VLOOKUP(DraftSheet!$W28,Aggregate!$AD:$AO,11,FALSE()),"") -> 3 | W28: =Aggregate!AD27 -> Jameson Williams | X28: =VLOOKUP(DraftSheet!$W28,Aggregate!AD:AO,4,FALSE()) -> DET/6 | Y28: =IFERROR(VLOOKUP(DraftSheet!$W28,Aggregate!$AD:$AO,8,FALSE()),"") -> 135.87723 | Z28: =IF(Scoring!$K$6="Auction",IFERROR(VLOOKUP(DraftSheet!$W28,Aggregate!$AD:$AO,10,FALSE()),""),IFERROR(VLOOKUP(DraftSheet!$W28,Aggregate!$AD:$AO,9,FALSE()),"")) -> 15.242625 | AA28: =SUMIFS($AD29:AD$84,$AC29:AC$84,"<>x",$AC29:AC$84,"<>o",$AD29:AD$84,">0")/Aggregate!$AL$1 -> 0.30171426 | AB28: {=IFERROR(INDEX(ECR!$K:$K,MATCH(DraftSheet!$W28,ECR!$C:$C,0)),"ND")} -> 54 | AD28: =VLOOKUP(W28,Aggregate!AD:AL,9,FALSE()) -> 54.356303
B29: =IFERROR(VLOOKUP(DraftSheet!$C29,Aggregate!$B:$M,11,FALSE()),"") -> 8 | C29: =Aggregate!B28 -> Bryce Young | D29: =VLOOKUP(DraftSheet!$C29,Aggregate!B:M,4,FALSE()) -> CAR/5 | E29: =IFERROR(VLOOKUP(DraftSheet!$C29,Aggregate!$B:$M,8,FALSE()),"") -> 161.97271 | F29: =IF(Scoring!$K$6="Auction",IFERROR(VLOOKUP(DraftSheet!$C29,Aggregate!$B:$M,10,FALSE()),""),IFERROR(VLOOKUP(DraftSheet!$C29,Aggregate!$B:$M,9,FALSE()),"")) -> 1 | G29: =SUMIFS($J30:J$44,$I30:I$44,"<>x",$I30:I$44,"<>o",$J30:J$44,">0")/Aggregate!$J$1 -> 0 | H29: {=IFERROR(INDEX(ECR!$K:$K,MATCH(DraftSheet!$C29,ECR!$C:$C,0)),"ND")} -> 172 | J29: =VLOOKUP(C29,Aggregate!B:J,9,FALSE()) -> -59.6741 | L29: =IFERROR(VLOOKUP(DraftSheet!$M29,Aggregate!$P:$AA,11,FALSE()),"") -> 5 | M29: =Aggregate!P25 -> David Montgomery | N29: =VLOOKUP(DraftSheet!$M29,Aggregate!P:AA,4,FALSE()) -> HOU/8 | O29: =IFERROR(VLOOKUP(DraftSheet!$M29,Aggregate!$P:$AA,8,FALSE()),"") -> 142.41194 | P29: =IF(Scoring!$K$6="Auction",IFERROR(VLOOKUP(DraftSheet!$M29,Aggregate!$P:$AA,10,FALSE()),""),IFERROR(VLOOKUP(DraftSheet!$M29,Aggregate!$P:$AA,9,FALSE()),"")) -> 17.775014 | Q29: =SUMIFS($T30:T$84,$S30:S$84,"<>x",$S30:S$84,"<>o",$T30:T$84,">0")/Aggregate!$X$1 -> 0.19627093 | R29: {=IFERROR(INDEX(ECR!$K:$K,MATCH(DraftSheet!$M29,ECR!$C:$C,0)),"ND")} -> 57 | T29: =VLOOKUP(M29,Aggregate!P:X,9,FALSE()) -> 64.021047 | V29: =IFERROR(VLOOKUP(DraftSheet!$W29,Aggregate!$AD:$AO,11,FALSE()),"") -> 4 | W29: =Aggregate!AD26 -> Luther Burden III | X29: =VLOOKUP(DraftSheet!$W29,Aggregate!AD:AO,4,FALSE()) -> CHI/10 | Y29: =IFERROR(VLOOKUP(DraftSheet!$W29,Aggregate!$AD:$AO,8,FALSE()),"") -> 131.05068 | Z29: =IF(Scoring!$K$6="Auction",IFERROR(VLOOKUP(DraftSheet!$W29,Aggregate!$AD:$AO,10,FALSE()),""),IFERROR(VLOOKUP(DraftSheet!$W29,Aggregate!$AD:$AO,9,FALSE()),"")) -> 13.977955 | AA29: =SUMIFS($AD30:AD$84,$AC30:AC$84,"<>x",$AC30:AC$84,"<>o",$AD30:AD$84,">0")/Aggregate!$AL$1 -> 0.28556028 | AB29: {=IFERROR(INDEX(ECR!$K:$K,MATCH(DraftSheet!$W29,ECR!$C:$C,0)),"ND")} -> 51 | AD29: =VLOOKUP(W29,Aggregate!AD:AL,9,FALSE()) -> 49.529751
B30: =IFERROR(VLOOKUP(DraftSheet!$C30,Aggregate!$B:$M,11,FALSE()),"") -> 9 | C30: =Aggregate!B26 -> Cam Ward | D30: =VLOOKUP(DraftSheet!$C30,Aggregate!B:M,4,FALSE()) -> TEN/9 | E30: =IFERROR(VLOOKUP(DraftSheet!$C30,Aggregate!$B:$M,8,FALSE()),"") -> 149.03078 | F30: =IF(Scoring!$K$6="Auction",IFERROR(VLOOKUP(DraftSheet!$C30,Aggregate!$B:$M,10,FALSE()),""),IFERROR(VLOOKUP(DraftSheet!$C30,Aggregate!$B:$M,9,FALSE()),"")) -> 1 | G30: =SUMIFS($J31:J$44,$I31:I$44,"<>x",$I31:I$44,"<>o",$J31:J$44,">0")/Aggregate!$J$1 -> 0 | H30: {=IFERROR(INDEX(ECR!$K:$K,MATCH(DraftSheet!$C30,ECR!$C:$C,0)),"ND")} -> 155 | J30: =VLOOKUP(C30,Aggregate!B:J,9,FALSE()) -> -72.61603 | L30: =IFERROR(VLOOKUP(DraftSheet!$M30,Aggregate!$P:$AA,11,FALSE()),"") -> 5 | M30: =Aggregate!P27 -> TreVeyon Henderson | N30: =VLOOKUP(DraftSheet!$M30,Aggregate!P:AA,4,FALSE()) -> NE/11 | O30: =IFERROR(VLOOKUP(DraftSheet!$M30,Aggregate!$P:$AA,8,FALSE()),"") -> 134.56506 | P30: =IF(Scoring!$K$6="Auction",IFERROR(VLOOKUP(DraftSheet!$M30,Aggregate!$P:$AA,10,FALSE()),""),IFERROR(VLOOKUP(DraftSheet!$M30,Aggregate!$P:$AA,9,FALSE()),"")) -> 15.71895 | Q30: =SUMIFS($T31:T$84,$S31:S$84,"<>x",$S31:S$84,"<>o",$T31:T$84,">0")/Aggregate!$X$1 -> 0.17879421 | R30: {=IFERROR(INDEX(ECR!$K:$K,MATCH(DraftSheet!$M30,ECR!$C:$C,0)),"ND")} -> 65 | T30: =VLOOKUP(M30,Aggregate!P:X,9,FALSE()) -> 56.174174 | V30: =IFERROR(VLOOKUP(DraftSheet!$W30,Aggregate!$AD:$AO,11,FALSE()),"") -> 4 | W30: =Aggregate!AD28 -> DJ Moore | X30: =VLOOKUP(DraftSheet!$W30,Aggregate!AD:AO,4,FALSE()) -> BUF/7 | Y30: =IFERROR(VLOOKUP(DraftSheet!$W30,Aggregate!$AD:$AO,8,FALSE()),"") -> 129.23198 | Z30: =IF(Scoring!$K$6="Auction",IFERROR(VLOOKUP(DraftSheet!$W30,Aggregate!$AD:$AO,10,FALSE()),""),IFERROR(VLOOKUP(DraftSheet!$W30,Aggregate!$AD:$AO,9,FALSE()),"")) -> 13.501414 | AA30: =SUMIFS($AD31:AD$84,$AC31:AC$84,"<>x",$AC31:AC$84,"<>o",$AD31:AD$84,">0")/Aggregate!$AL$1 -> 0.26999947 | AB30: {=IFERROR(INDEX(ECR!$K:$K,MATCH(DraftSheet!$W30,ECR!$C:$C,0)),"ND")} -> 58 | AD30: =VLOOKUP(W30,Aggregate!AD:AL,9,FALSE()) -> 47.711054
B31: =IFERROR(VLOOKUP(DraftSheet!$C31,Aggregate!$B:$M,11,FALSE()),"") -> 9 | C31: =Aggregate!B30 -> Geno Smith | D31: =VLOOKUP(DraftSheet!$C31,Aggregate!B:M,4,FALSE()) -> NYJ/13 | E31: =IFERROR(VLOOKUP(DraftSheet!$C31,Aggregate!$B:$M,8,FALSE()),"") -> 145.77205 | F31: =IF(Scoring!$K$6="Auction",IFERROR(VLOOKUP(DraftSheet!$C31,Aggregate!$B:$M,10,FALSE()),""),IFERROR(VLOOKUP(DraftSheet!$C31,Aggregate!$B:$M,9,FALSE()),"")) -> 1 | G31: =SUMIFS($J32:J$44,$I32:I$44,"<>x",$I32:I$44,"<>o",$J32:J$44,">0")/Aggregate!$J$1 -> 0 | H31: {=IFERROR(INDEX(ECR!$K:$K,MATCH(DraftSheet!$C31,ECR!$C:$C,0)),"ND")} -> 195 | J31: =VLOOKUP(C31,Aggregate!B:J,9,FALSE()) -> -75.874759 | L31: =IFERROR(VLOOKUP(DraftSheet!$M31,Aggregate!$P:$AA,11,FALSE()),"") -> 5 | M31: =Aggregate!P30 -> Jaylen Warren | N31: =VLOOKUP(DraftSheet!$M31,Aggregate!P:AA,4,FALSE()) -> PIT/9 | O31: =IFERROR(VLOOKUP(DraftSheet!$M31,Aggregate!$P:$AA,8,FALSE()),"") -> 130.63043 | P31: =IF(Scoring!$K$6="Auction",IFERROR(VLOOKUP(DraftSheet!$M31,Aggregate!$P:$AA,10,FALSE()),""),IFERROR(VLOOKUP(DraftSheet!$M31,Aggregate!$P:$AA,9,FALSE()),"")) -> 14.687984 | Q31: =SUMIFS($T32:T$84,$S32:S$84,"<>x",$S32:S$84,"<>o",$T32:T$84,">0")/Aggregate!$X$1 -> 0.16254162 | R31: {=IFERROR(INDEX(ECR!$K:$K,MATCH(DraftSheet!$M31,ECR!$C:$C,0)),"ND")} -> 74 | T31: =VLOOKUP(M31,Aggregate!P:X,9,FALSE()) -> 52.239544 | V31: =IFERROR(VLOOKUP(DraftSheet!$W31,Aggregate!$AD:$AO,11,FALSE()),"") -> 4 | W31: =Aggregate!AD31 -> Rome Odunze | X31: =VLOOKUP(DraftSheet!$W31,Aggregate!AD:AO,4,FALSE()) -> CHI/10 | Y31: =IFERROR(VLOOKUP(DraftSheet!$W31,Aggregate!$AD:$AO,8,FALSE()),"") -> 127.0741 | Z31: =IF(Scoring!$K$6="Auction",IFERROR(VLOOKUP(DraftSheet!$W31,Aggregate!$AD:$AO,10,FALSE()),""),IFERROR(VLOOKUP(DraftSheet!$W31,Aggregate!$AD:$AO,9,FALSE()),"")) -> 12.935998 | AA31: =SUMIFS($AD32:AD$84,$AC32:AC$84,"<>x",$AC32:AC$84,"<>o",$AD32:AD$84,">0")/Aggregate!$AL$1 -> 0.25514244 | AB31: {=IFERROR(INDEX(ECR!$K:$K,MATCH(DraftSheet!$W31,ECR!$C:$C,0)),"ND")} -> 62 | AD31: =VLOOKUP(W31,Aggregate!AD:AL,9,FALSE()) -> 45.55317
B32: =IFERROR(VLOOKUP(DraftSheet!$C32,Aggregate!$B:$M,11,FALSE()),"") -> 9 | C32: =Aggregate!B29 -> Jacoby Brissett | D32: =VLOOKUP(DraftSheet!$C32,Aggregate!B:M,4,FALSE()) -> ARI/14 | E32: =IFERROR(VLOOKUP(DraftSheet!$C32,Aggregate!$B:$M,8,FALSE()),"") -> 141.66174 | F32: =IF(Scoring!$K$6="Auction",IFERROR(VLOOKUP(DraftSheet!$C32,Aggregate!$B:$M,10,FALSE()),""),IFERROR(VLOOKUP(DraftSheet!$C32,Aggregate!$B:$M,9,FALSE()),"")) -> 1 | G32: =SUMIFS($J33:J$44,$I33:I$44,"<>x",$I33:I$44,"<>o",$J33:J$44,">0")/Aggregate!$J$1 -> 0 | H32: {=IFERROR(INDEX(ECR!$K:$K,MATCH(DraftSheet!$C32,ECR!$C:$C,0)),"ND")} -> 184 | J32: =VLOOKUP(C32,Aggregate!B:J,9,FALSE()) -> -79.985065 | L32: =IFERROR(VLOOKUP(DraftSheet!$M32,Aggregate!$P:$AA,11,FALSE()),"") -> 5 | M32: =Aggregate!P31 -> Tony Pollard | N32: =VLOOKUP(DraftSheet!$M32,Aggregate!P:AA,4,FALSE()) -> TEN/9 | O32: =IFERROR(VLOOKUP(DraftSheet!$M32,Aggregate!$P:$AA,8,FALSE()),"") -> 130.08169 | P32: =IF(Scoring!$K$6="Auction",IFERROR(VLOOKUP(DraftSheet!$M32,Aggregate!$P:$AA,10,FALSE()),""),IFERROR(VLOOKUP(DraftSheet!$M32,Aggregate!$P:$AA,9,FALSE()),"")) -> 14.5442 | Q32: =SUMIFS($T33:T$84,$S33:S$84,"<>x",$S33:S$84,"<>o",$T33:T$84,">0")/Aggregate!$X$1 -> 0.14645976 | R32: {=IFERROR(INDEX(ECR!$K:$K,MATCH(DraftSheet!$M32,ECR!$C:$C,0)),"ND")} -> 79 | T32: =VLOOKUP(M32,Aggregate!P:X,9,FALSE()) -> 51.690798 | V32: =IFERROR(VLOOKUP(DraftSheet!$W32,Aggregate!$AD:$AO,11,FALSE()),"") -> 4 | W32: =Aggregate!AD30 -> Mike Evans | X32: =VLOOKUP(DraftSheet!$W32,Aggregate!AD:AO,4,FALSE()) -> SF/8 | Y32: =IFERROR(VLOOKUP(DraftSheet!$W32,Aggregate!$AD:$AO,8,FALSE()),"") -> 125.6167 | Z32: =IF(Scoring!$K$6="Auction",IFERROR(VLOOKUP(DraftSheet!$W32,Aggregate!$AD:$AO,10,FALSE()),""),IFERROR(VLOOKUP(DraftSheet!$W32,Aggregate!$AD:$AO,9,FALSE()),"")) -> 12.554125 | AA32: =SUMIFS($AD33:AD$84,$AC33:AC$84,"<>x",$AC33:AC$84,"<>o",$AD33:AD$84,">0")/Aggregate!$AL$1 -> 0.24076074 | AB32: {=IFERROR(INDEX(ECR!$K:$K,MATCH(DraftSheet!$W32,ECR!$C:$C,0)),"ND")} -> 61 | AD32: =VLOOKUP(W32,Aggregate!AD:AL,9,FALSE()) -> 44.095772
B33: =IFERROR(VLOOKUP(DraftSheet!$C33,Aggregate!$B:$M,11,FALSE()),"") -> 9 | C33: =Aggregate!B31 -> Aaron Rodgers | D33: =VLOOKUP(DraftSheet!$C33,Aggregate!B:M,4,FALSE()) -> PIT/9 | E33: =IFERROR(VLOOKUP(DraftSheet!$C33,Aggregate!$B:$M,8,FALSE()),"") -> 139.95934 | F33: =IF(Scoring!$K$6="Auction",IFERROR(VLOOKUP(DraftSheet!$C33,Aggregate!$B:$M,10,FALSE()),""),IFERROR(VLOOKUP(DraftSheet!$C33,Aggregate!$B:$M,9,FALSE()),"")) -> 1 | G33: =SUMIFS($J34:J$44,$I34:I$44,"<>x",$I34:I$44,"<>o",$J34:J$44,">0")/Aggregate!$J$1 -> 0 | H33: {=IFERROR(INDEX(ECR!$K:$K,MATCH(DraftSheet!$C33,ECR!$C:$C,0)),"ND")} -> 205 | J33: =VLOOKUP(C33,Aggregate!B:J,9,FALSE()) -> -81.687465 | L33: =IFERROR(VLOOKUP(DraftSheet!$M33,Aggregate!$P:$AA,11,FALSE()),"") -> 5 | M33: =Aggregate!P29 -> Rhamondre Stevenson | N33: =VLOOKUP(DraftSheet!$M33,Aggregate!P:AA,4,FALSE()) -> NE/11 | O33: =IFERROR(VLOOKUP(DraftSheet!$M33,Aggregate!$P:$AA,8,FALSE()),"") -> 130.00033 | P33: =IF(Scoring!$K$6="Auction",IFERROR(VLOOKUP(DraftSheet!$M33,Aggregate!$P:$AA,10,FALSE()),""),IFERROR(VLOOKUP(DraftSheet!$M33,Aggregate!$P:$AA,9,FALSE()),"")) -> 14.522882 | Q33: =SUMIFS($T34:T$84,$S34:S$84,"<>x",$S34:S$84,"<>o",$T34:T$84,">0")/Aggregate!$X$1 -> 0.1304032 | R33: {=IFERROR(INDEX(ECR!$K:$K,MATCH(DraftSheet!$M33,ECR!$C:$C,0)),"ND")} -> 71 | T33: =VLOOKUP(M33,Aggregate!P:X,9,FALSE()) -> 51.60944 | V33: =IFERROR(VLOOKUP(DraftSheet!$W33,Aggregate!$AD:$AO,11,FALSE()),"") -> 4 | W33: =Aggregate!AD29 -> Christian Watson | X33: =VLOOKUP(DraftSheet!$W33,Aggregate!AD:AO,4,FALSE()) -> GB/11 | Y33: =IFERROR(VLOOKUP(DraftSheet!$W33,Aggregate!$AD:$AO,8,FALSE()),"") -> 125.22994 | Z33: =IF(Scoring!$K$6="Auction",IFERROR(VLOOKUP(DraftSheet!$W33,Aggregate!$AD:$AO,10,FALSE()),""),IFERROR(VLOOKUP(DraftSheet!$W33,Aggregate!$AD:$AO,9,FALSE()),"")) -> 12.452784 | AA33: =SUMIFS($AD34:AD$84,$AC34:AC$84,"<>x",$AC34:AC$84,"<>o",$AD34:AD$84,">0")/Aggregate!$AL$1 -> 0.22650517 | AB33: {=IFERROR(INDEX(ECR!$K:$K,MATCH(DraftSheet!$W33,ECR!$C:$C,0)),"ND")} -> 59 | AD33: =VLOOKUP(W33,Aggregate!AD:AL,9,FALSE()) -> 43.709009
B34: =IFERROR(VLOOKUP(DraftSheet!$C34,Aggregate!$B:$M,11,FALSE()),"") -> 10 | C34: =Aggregate!B32 -> Fernando Mendoza | D34: =VLOOKUP(DraftSheet!$C34,Aggregate!B:M,4,FALSE()) -> LV/13 | E34: =IFERROR(VLOOKUP(DraftSheet!$C34,Aggregate!$B:$M,8,FALSE()),"") -> 115.74551 | F34: =IF(Scoring!$K$6="Auction",IFERROR(VLOOKUP(DraftSheet!$C34,Aggregate!$B:$M,10,FALSE()),""),IFERROR(VLOOKUP(DraftSheet!$C34,Aggregate!$B:$M,9,FALSE()),"")) -> 1 | G34: =SUMIFS($J35:J$44,$I35:I$44,"<>x",$I35:I$44,"<>o",$J35:J$44,">0")/Aggregate!$J$1 -> 0 | H34: {=IFERROR(INDEX(ECR!$K:$K,MATCH(DraftSheet!$C34,ECR!$C:$C,0)),"ND")} -> 230 | J34: =VLOOKUP(C34,Aggregate!B:J,9,FALSE()) -> -105.9013 | L34: =IFERROR(VLOOKUP(DraftSheet!$M34,Aggregate!$P:$AA,11,FALSE()),"") -> 5 | M34: =Aggregate!P32 -> Rico Dowdle | N34: =VLOOKUP(DraftSheet!$M34,Aggregate!P:AA,4,FALSE()) -> PIT/9 | O34: =IFERROR(VLOOKUP(DraftSheet!$M34,Aggregate!$P:$AA,8,FALSE()),"") -> 126.02601 | P34: =IF(Scoring!$K$6="Auction",IFERROR(VLOOKUP(DraftSheet!$M34,Aggregate!$P:$AA,10,FALSE()),""),IFERROR(VLOOKUP(DraftSheet!$M34,Aggregate!$P:$AA,9,FALSE()),"")) -> 13.481517 | Q34: =SUMIFS($T35:T$84,$S35:S$84,"<>x",$S35:S$84,"<>o",$T35:T$84,">0")/Aggregate!$X$1 -> 0.11558312 | R34: {=IFERROR(INDEX(ECR!$K:$K,MATCH(DraftSheet!$M34,ECR!$C:$C,0)),"ND")} -> 82 | T34: =VLOOKUP(M34,Aggregate!P:X,9,FALSE()) -> 47.635117 | V34: =IFERROR(VLOOKUP(DraftSheet!$W34,Aggregate!$AD:$AO,11,FALSE()),"") -> 4 | W34: =Aggregate!AD33 -> Marvin Harrison Jr. | X34: =VLOOKUP(DraftSheet!$W34,Aggregate!AD:AO,4,FALSE()) -> ARI/14 | Y34: =IFERROR(VLOOKUP(DraftSheet!$W34,Aggregate!$AD:$AO,8,FALSE()),"") -> 120.34365 | Z34: =IF(Scoring!$K$6="Auction",IFERROR(VLOOKUP(DraftSheet!$W34,Aggregate!$AD:$AO,10,FALSE()),""),IFERROR(VLOOKUP(DraftSheet!$W34,Aggregate!$AD:$AO,9,FALSE()),"")) -> 11.172462 | AA34: =SUMIFS($AD35:AD$84,$AC35:AC$84,"<>x",$AC35:AC$84,"<>o",$AD35:AD$84,">0")/Aggregate!$AL$1 -> 0.21384326 | AB34: {=IFERROR(INDEX(ECR!$K:$K,MATCH(DraftSheet!$W34,ECR!$C:$C,0)),"ND")} -> 72 | AD34: =VLOOKUP(W34,Aggregate!AD:AL,9,FALSE()) -> 38.822721
B35: =IFERROR(VLOOKUP(DraftSheet!$C35,Aggregate!$B:$M,11,FALSE()),"") -> 11 | C35: =Aggregate!B36 -> Deshaun Watson | D35: =VLOOKUP(DraftSheet!$C35,Aggregate!B:M,4,FALSE()) -> CLE/11 | E35: =IFERROR(VLOOKUP(DraftSheet!$C35,Aggregate!$B:$M,8,FALSE()),"") -> 84.637365 | F35: =IF(Scoring!$K$6="Auction",IFERROR(VLOOKUP(DraftSheet!$C35,Aggregate!$B:$M,10,FALSE()),""),IFERROR(VLOOKUP(DraftSheet!$C35,Aggregate!$B:$M,9,FALSE()),"")) -> 1 | G35: =SUMIFS($J36:J$44,$I36:I$44,"<>x",$I36:I$44,"<>o",$J36:J$44,">0")/Aggregate!$J$1 -> 0 | H35: {=IFERROR(INDEX(ECR!$K:$K,MATCH(DraftSheet!$C35,ECR!$C:$C,0)),"ND")} -> 279 | J35: =VLOOKUP(C35,Aggregate!B:J,9,FALSE()) -> -137.00944 | L35: =IFERROR(VLOOKUP(DraftSheet!$M35,Aggregate!$P:$AA,11,FALSE()),"") -> 5 | M35: =Aggregate!P34 -> J.K. Dobbins | N35: =VLOOKUP(DraftSheet!$M35,Aggregate!P:AA,4,FALSE()) -> DEN/10 | O35: =IFERROR(VLOOKUP(DraftSheet!$M35,Aggregate!$P:$AA,8,FALSE()),"") -> 123.50814 | P35: =IF(Scoring!$K$6="Auction",IFERROR(VLOOKUP(DraftSheet!$M35,Aggregate!$P:$AA,10,FALSE()),""),IFERROR(VLOOKUP(DraftSheet!$M35,Aggregate!$P:$AA,9,FALSE()),"")) -> 12.821776 | Q35: =SUMIFS($T36:T$84,$S36:S$84,"<>x",$S36:S$84,"<>o",$T36:T$84,">0")/Aggregate!$X$1 -> 0.1015464 | R35: {=IFERROR(INDEX(ECR!$K:$K,MATCH(DraftSheet!$M35,ECR!$C:$C,0)),"ND")} -> 87 | T35: =VLOOKUP(M35,Aggregate!P:X,9,FALSE()) -> 45.117248 | V35: =IFERROR(VLOOKUP(DraftSheet!$W35,Aggregate!$AD:$AO,11,FALSE()),"") -> 4 | W35: =Aggregate!AD34 -> Carnell Tate | X35: =VLOOKUP(DraftSheet!$W35,Aggregate!AD:AO,4,FALSE()) -> TEN/9 | Y35: =IFERROR(VLOOKUP(DraftSheet!$W35,Aggregate!$AD:$AO,8,FALSE()),"") -> 118.53077 | Z35: =IF(Scoring!$K$6="Auction",IFERROR(VLOOKUP(DraftSheet!$W35,Aggregate!$AD:$AO,10,FALSE()),""),IFERROR(VLOOKUP(DraftSheet!$W35,Aggregate!$AD:$AO,9,FALSE()),"")) -> 10.697446 | AA35: =SUMIFS($AD36:AD$84,$AC36:AC$84,"<>x",$AC36:AC$84,"<>o",$AD36:AD$84,">0")/Aggregate!$AL$1 -> 0.20177261 | AB35: {=IFERROR(INDEX(ECR!$K:$K,MATCH(DraftSheet!$W35,ECR!$C:$C,0)),"ND")} -> 73 | AD35: =VLOOKUP(W35,Aggregate!AD:AL,9,FALSE()) -> 37.009842
B36: =IFERROR(VLOOKUP(DraftSheet!$C36,Aggregate!$B:$M,11,FALSE()),"") -> 11 | C36: =Aggregate!B33 -> Tua Tagovailoa | D36: =VLOOKUP(DraftSheet!$C36,Aggregate!B:M,4,FALSE()) -> ATL/11 | E36: =IFERROR(VLOOKUP(DraftSheet!$C36,Aggregate!$B:$M,8,FALSE()),"") -> 77.558588 | F36: =IF(Scoring!$K$6="Auction",IFERROR(VLOOKUP(DraftSheet!$C36,Aggregate!$B:$M,10,FALSE()),""),IFERROR(VLOOKUP(DraftSheet!$C36,Aggregate!$B:$M,9,FALSE()),"")) -> 1 | G36: =SUMIFS($J37:J$44,$I37:I$44,"<>x",$I37:I$44,"<>o",$J37:J$44,">0")/Aggregate!$J$1 -> 0 | H36: {=IFERROR(INDEX(ECR!$K:$K,MATCH(DraftSheet!$C36,ECR!$C:$C,0)),"ND")} -> 246 | J36: =VLOOKUP(C36,Aggregate!B:J,9,FALSE()) -> -144.08822 | L36: =IFERROR(VLOOKUP(DraftSheet!$M36,Aggregate!$P:$AA,11,FALSE()),"") -> 6 | M36: =Aggregate!P35 -> Chuba Hubbard | N36: =VLOOKUP(DraftSheet!$M36,Aggregate!P:AA,4,FALSE()) -> CAR/5 | O36: =IFERROR(VLOOKUP(DraftSheet!$M36,Aggregate!$P:$AA,8,FALSE()),"") -> 116.85849 | P36: =IF(Scoring!$K$6="Auction",IFERROR(VLOOKUP(DraftSheet!$M36,Aggregate!$P:$AA,10,FALSE()),""),IFERROR(VLOOKUP(DraftSheet!$M36,Aggregate!$P:$AA,9,FALSE()),"")) -> 11.079414 | Q36: =SUMIFS($T37:T$84,$S37:S$84,"<>x",$S37:S$84,"<>o",$T37:T$84,">0")/Aggregate!$X$1 -> 0.089578489 | R36: {=IFERROR(INDEX(ECR!$K:$K,MATCH(DraftSheet!$M36,ECR!$C:$C,0)),"ND")} -> 93 | T36: =VLOOKUP(M36,Aggregate!P:X,9,FALSE()) -> 38.467605 | V36: =IFERROR(VLOOKUP(DraftSheet!$W36,Aggregate!$AD:$AO,11,FALSE()),"") -> 4 | W36: =Aggregate!AD36 -> DK Metcalf | X36: =VLOOKUP(DraftSheet!$W36,Aggregate!AD:AO,4,FALSE()) -> PIT/9 | Y36: =IFERROR(VLOOKUP(DraftSheet!$W36,Aggregate!$AD:$AO,8,FALSE()),"") -> 118.14927 | Z36: =IF(Scoring!$K$6="Auction",IFERROR(VLOOKUP(DraftSheet!$W36,Aggregate!$AD:$AO,10,FALSE()),""),IFERROR(VLOOKUP(DraftSheet!$W36,Aggregate!$AD:$AO,9,FALSE()),"")) -> 10.597483 | AA36: =SUMIFS($AD37:AD$84,$AC37:AC$84,"<>x",$AC37:AC$84,"<>o",$AD37:AD$84,">0")/Aggregate!$AL$1 -> 0.18982639 | AB36: {=IFERROR(INDEX(ECR!$K:$K,MATCH(DraftSheet!$W36,ECR!$C:$C,0)),"ND")} -> 78 | AD36: =VLOOKUP(W36,Aggregate!AD:AL,9,FALSE()) -> 36.628341
B37: =IFERROR(VLOOKUP(DraftSheet!$C37,Aggregate!$B:$M,11,FALSE()),"") -> 11 | C37: =Aggregate!B34 -> Michael Penix Jr. | D37: =VLOOKUP(DraftSheet!$C37,Aggregate!B:M,4,FALSE()) -> ATL/11 | E37: =IFERROR(VLOOKUP(DraftSheet!$C37,Aggregate!$B:$M,8,FALSE()),"") -> 75.040376 | F37: =IF(Scoring!$K$6="Auction",IFERROR(VLOOKUP(DraftSheet!$C37,Aggregate!$B:$M,10,FALSE()),""),IFERROR(VLOOKUP(DraftSheet!$C37,Aggregate!$B:$M,9,FALSE()),"")) -> 1 | G37: =SUMIFS($J38:J$44,$I38:I$44,"<>x",$I38:I$44,"<>o",$J38:J$44,">0")/Aggregate!$J$1 -> 0 | H37: {=IFERROR(INDEX(ECR!$K:$K,MATCH(DraftSheet!$C37,ECR!$C:$C,0)),"ND")} -> 268 | J37: =VLOOKUP(C37,Aggregate!B:J,9,FALSE()) -> -146.60643 | L37: =IFERROR(VLOOKUP(DraftSheet!$M37,Aggregate!$P:$AA,11,FALSE()),"") -> 6 | M37: =Aggregate!P33 -> Jonathon Brooks | N37: =VLOOKUP(DraftSheet!$M37,Aggregate!P:AA,4,FALSE()) -> CAR/5 | O37: =IFERROR(VLOOKUP(DraftSheet!$M37,Aggregate!$P:$AA,8,FALSE()),"") -> 115.59469 | P37: =IF(Scoring!$K$6="Auction",IFERROR(VLOOKUP(DraftSheet!$M37,Aggregate!$P:$AA,10,FALSE()),""),IFERROR(VLOOKUP(DraftSheet!$M37,Aggregate!$P:$AA,9,FALSE()),"")) -> 10.748267 | Q37: =SUMIFS($T38:T$84,$S38:S$84,"<>x",$S38:S$84,"<>o",$T38:T$84,">0")/Aggregate!$X$1 -> 0.078003768 | R37: {=IFERROR(INDEX(ECR!$K:$K,MATCH(DraftSheet!$M37,ECR!$C:$C,0)),"ND")} -> 85 | T37: =VLOOKUP(M37,Aggregate!P:X,9,FALSE()) -> 37.203801 | V37: =IFERROR(VLOOKUP(DraftSheet!$W37,Aggregate!$AD:$AO,11,FALSE()),"") -> 4 | W37: =Aggregate!AD38 -> Courtland Sutton | X37: =VLOOKUP(DraftSheet!$W37,Aggregate!AD:AO,4,FALSE()) -> DEN/10 | Y37: =IFERROR(VLOOKUP(DraftSheet!$W37,Aggregate!$AD:$AO,8,FALSE()),"") -> 116.91232 | Z37: =IF(Scoring!$K$6="Auction",IFERROR(VLOOKUP(DraftSheet!$W37,Aggregate!$AD:$AO,10,FALSE()),""),IFERROR(VLOOKUP(DraftSheet!$W37,Aggregate!$AD:$AO,9,FALSE()),"")) -> 10.273374 | AA37: =SUMIFS($AD38:AD$84,$AC38:AC$84,"<>x",$AC38:AC$84,"<>o",$AD38:AD$84,">0")/Aggregate!$AL$1 -> 0.17828359 | AB37: {=IFERROR(INDEX(ECR!$K:$K,MATCH(DraftSheet!$W37,ECR!$C:$C,0)),"ND")} -> 86 | AD37: =VLOOKUP(W37,Aggregate!AD:AL,9,FALSE()) -> 35.391392
B38: =IFERROR(VLOOKUP(DraftSheet!$C38,Aggregate!$B:$M,11,FALSE()),"") -> 12 | C38: =Aggregate!B37 -> Shedeur Sanders | D38: =VLOOKUP(DraftSheet!$C38,Aggregate!B:M,4,FALSE()) -> CLE/11 | E38: =IFERROR(VLOOKUP(DraftSheet!$C38,Aggregate!$B:$M,8,FALSE()),"") -> 46.371388 | F38: =IF(Scoring!$K$6="Auction",IFERROR(VLOOKUP(DraftSheet!$C38,Aggregate!$B:$M,10,FALSE()),""),IFERROR(VLOOKUP(DraftSheet!$C38,Aggregate!$B:$M,9,FALSE()),"")) -> 1 | G38: =SUMIFS($J39:J$44,$I39:I$44,"<>x",$I39:I$44,"<>o",$J39:J$44,">0")/Aggregate!$J$1 -> 0 | H38: {=IFERROR(INDEX(ECR!$K:$K,MATCH(DraftSheet!$C38,ECR!$C:$C,0)),"ND")} -> 282 | J38: =VLOOKUP(C38,Aggregate!B:J,9,FALSE()) -> -175.27542 | L38: =IFERROR(VLOOKUP(DraftSheet!$M38,Aggregate!$P:$AA,11,FALSE()),"") -> 6 | M38: =Aggregate!P41 -> Kyle Monangai | N38: =VLOOKUP(DraftSheet!$M38,Aggregate!P:AA,4,FALSE()) -> CHI/10 | O38: =IFERROR(VLOOKUP(DraftSheet!$M38,Aggregate!$P:$AA,8,FALSE()),"") -> 107.10465 | P38: =IF(Scoring!$K$6="Auction",IFERROR(VLOOKUP(DraftSheet!$M38,Aggregate!$P:$AA,10,FALSE()),""),IFERROR(VLOOKUP(DraftSheet!$M38,Aggregate!$P:$AA,9,FALSE()),"")) -> 8.5236782 | Q38: =SUMIFS($T39:T$84,$S39:S$84,"<>x",$S39:S$84,"<>o",$T39:T$84,">0")/Aggregate!$X$1 -> 0.06907044 | R38: {=IFERROR(INDEX(ECR!$K:$K,MATCH(DraftSheet!$M38,ECR!$C:$C,0)),"ND")} -> 111 | T38: =VLOOKUP(M38,Aggregate!P:X,9,FALSE()) -> 28.713761 | V38: =IFERROR(VLOOKUP(DraftSheet!$W38,Aggregate!$AD:$AO,11,FALSE()),"") -> 4 | W38: =Aggregate!AD43 -> Alec Pierce | X38: =VLOOKUP(DraftSheet!$W38,Aggregate!AD:AO,4,FALSE()) -> IND/13 | Y38: =IFERROR(VLOOKUP(DraftSheet!$W38,Aggregate!$AD:$AO,8,FALSE()),"") -> 116.68431 | Z38: =IF(Scoring!$K$6="Auction",IFERROR(VLOOKUP(DraftSheet!$W38,Aggregate!$AD:$AO,10,FALSE()),""),IFERROR(VLOOKUP(DraftSheet!$W38,Aggregate!$AD:$AO,9,FALSE()),"")) -> 10.213631 | AA38: =SUMIFS($AD39:AD$84,$AC39:AC$84,"<>x",$AC39:AC$84,"<>o",$AD39:AD$84,">0")/Aggregate!$AL$1 -> 0.16681516 | AB38: {=IFERROR(INDEX(ECR!$K:$K,MATCH(DraftSheet!$W38,ECR!$C:$C,0)),"ND")} -> 97 | AD38: =VLOOKUP(W38,Aggregate!AD:AL,9,FALSE()) -> 35.163385
B39: =IFERROR(VLOOKUP(DraftSheet!$C39,Aggregate!$B:$M,11,FALSE()),"") -> 12 | C39: =Aggregate!B35 -> Kirk Cousins | D39: =VLOOKUP(DraftSheet!$C39,Aggregate!B:M,4,FALSE()) -> LV/13 | E39: =IFERROR(VLOOKUP(DraftSheet!$C39,Aggregate!$B:$M,8,FALSE()),"") -> 39.224471 | F39: =IF(Scoring!$K$6="Auction",IFERROR(VLOOKUP(DraftSheet!$C39,Aggregate!$B:$M,10,FALSE()),""),IFERROR(VLOOKUP(DraftSheet!$C39,Aggregate!$B:$M,9,FALSE()),"")) -> 1 | G39: =SUMIFS($J40:J$44,$I40:I$44,"<>x",$I40:I$44,"<>o",$J40:J$44,">0")/Aggregate!$J$1 -> 0 | H39: {=IFERROR(INDEX(ECR!$K:$K,MATCH(DraftSheet!$C39,ECR!$C:$C,0)),"ND")} -> 270 | J39: =VLOOKUP(C39,Aggregate!B:J,9,FALSE()) -> -182.42234 | L39: =IFERROR(VLOOKUP(DraftSheet!$M39,Aggregate!$P:$AA,11,FALSE()),"") -> 6 | M39: =Aggregate!P38 -> RJ Harvey | N39: =VLOOKUP(DraftSheet!$M39,Aggregate!P:AA,4,FALSE()) -> DEN/10 | O39: =IFERROR(VLOOKUP(DraftSheet!$M39,Aggregate!$P:$AA,8,FALSE()),"") -> 106.89142 | P39: =IF(Scoring!$K$6="Auction",IFERROR(VLOOKUP(DraftSheet!$M39,Aggregate!$P:$AA,10,FALSE()),""),IFERROR(VLOOKUP(DraftSheet!$M39,Aggregate!$P:$AA,9,FALSE()),"")) -> 8.4678059 | Q39: =SUMIFS($T40:T$84,$S40:S$84,"<>x",$S40:S$84,"<>o",$T40:T$84,">0")/Aggregate!$X$1 -> 0.060203453 | R39: {=IFERROR(INDEX(ECR!$K:$K,MATCH(DraftSheet!$M39,ECR!$C:$C,0)),"ND")} -> 100 | T39: =VLOOKUP(M39,Aggregate!P:X,9,FALSE()) -> 28.500527 | V39: =IFERROR(VLOOKUP(DraftSheet!$W39,Aggregate!$AD:$AO,11,FALSE()),"") -> 4 | W39: =Aggregate!AD32 -> Parker Washington | X39: =VLOOKUP(DraftSheet!$W39,Aggregate!AD:AO,4,FALSE()) -> JAC/7 | Y39: =IFERROR(VLOOKUP(DraftSheet!$W39,Aggregate!$AD:$AO,8,FALSE()),"") -> 115.64855 | Z39: =IF(Scoring!$K$6="Auction",IFERROR(VLOOKUP(DraftSheet!$W39,Aggregate!$AD:$AO,10,FALSE()),""),IFERROR(VLOOKUP(DraftSheet!$W39,Aggregate!$AD:$AO,9,FALSE()),"")) -> 9.942238 | AA39: =SUMIFS($AD40:AD$84,$AC40:AC$84,"<>x",$AC40:AC$84,"<>o",$AD40:AD$84,">0")/Aggregate!$AL$1 -> 0.15568454 | AB39: {=IFERROR(INDEX(ECR!$K:$K,MATCH(DraftSheet!$W39,ECR!$C:$C,0)),"ND")} -> 68 | AD39: =VLOOKUP(W39,Aggregate!AD:AL,9,FALSE()) -> 34.127627
B40: =IFERROR(VLOOKUP(DraftSheet!$C40,Aggregate!$B:$M,11,FALSE()),"") -> 13 | C40: =Aggregate!B39 -> J.J. McCarthy | D40: =VLOOKUP(DraftSheet!$C40,Aggregate!B:M,4,FALSE()) -> MIN/6 | E40: =IFERROR(VLOOKUP(DraftSheet!$C40,Aggregate!$B:$M,8,FALSE()),"") -> 15.132612 | F40: =IF(Scoring!$K$6="Auction",IFERROR(VLOOKUP(DraftSheet!$C40,Aggregate!$B:$M,10,FALSE()),""),IFERROR(VLOOKUP(DraftSheet!$C40,Aggregate!$B:$M,9,FALSE()),"")) -> 1 | G40: =SUMIFS($J41:J$44,$I41:I$44,"<>x",$I41:I$44,"<>o",$J41:J$44,">0")/Aggregate!$J$1 -> 0 | H40: {=IFERROR(INDEX(ECR!$K:$K,MATCH(DraftSheet!$C40,ECR!$C:$C,0)),"ND")} -> 333 | J40: =VLOOKUP(C40,Aggregate!B:J,9,FALSE()) -> -206.51419 | L40: =IFERROR(VLOOKUP(DraftSheet!$M40,Aggregate!$P:$AA,11,FALSE()),"") -> 6 | M40: =Aggregate!P37 -> Jacory Croskey-Merritt | N40: =VLOOKUP(DraftSheet!$M40,Aggregate!P:AA,4,FALSE()) -> WAS/7 | O40: =IFERROR(VLOOKUP(DraftSheet!$M40,Aggregate!$P:$AA,8,FALSE()),"") -> 106.09468 | P40: =IF(Scoring!$K$6="Auction",IFERROR(VLOOKUP(DraftSheet!$M40,Aggregate!$P:$AA,10,FALSE()),""),IFERROR(VLOOKUP(DraftSheet!$M40,Aggregate!$P:$AA,9,FALSE()),"")) -> 8.2590423 | Q40: =SUMIFS($T41:T$84,$S41:S$84,"<>x",$S41:S$84,"<>o",$T41:T$84,">0")/Aggregate!$X$1 -> 0.051584343 | R40: {=IFERROR(INDEX(ECR!$K:$K,MATCH(DraftSheet!$M40,ECR!$C:$C,0)),"ND")} -> 99 | T40: =VLOOKUP(M40,Aggregate!P:X,9,FALSE()) -> 27.703791 | V40: =IFERROR(VLOOKUP(DraftSheet!$W40,Aggregate!$AD:$AO,11,FALSE()),"") -> 4 | W40: =Aggregate!AD35 -> Brian Thomas Jr. | X40: =VLOOKUP(DraftSheet!$W40,Aggregate!AD:AO,4,FALSE()) -> JAC/7 | Y40: =IFERROR(VLOOKUP(DraftSheet!$W40,Aggregate!$AD:$AO,8,FALSE()),"") -> 112.94077 | Z40: =IF(Scoring!$K$6="Auction",IFERROR(VLOOKUP(DraftSheet!$W40,Aggregate!$AD:$AO,10,FALSE()),""),IFERROR(VLOOKUP(DraftSheet!$W40,Aggregate!$AD:$AO,9,FALSE()),"")) -> 9.2327351 | AA40: =SUMIFS($AD41:AD$84,$AC41:AC$84,"<>x",$AC41:AC$84,"<>o",$AD41:AD$84,">0")/Aggregate!$AL$1 -> 0.14543705 | AB40: {=IFERROR(INDEX(ECR!$K:$K,MATCH(DraftSheet!$W40,ECR!$C:$C,0)),"ND")} -> 76 | AD40: =VLOOKUP(W40,Aggregate!AD:AL,9,FALSE()) -> 31.419843
B41: =IFERROR(VLOOKUP(DraftSheet!$C41,Aggregate!$B:$M,11,FALSE()),"") -> 13 | C41: =Aggregate!B38 -> Carson Beck | D41: =VLOOKUP(DraftSheet!$C41,Aggregate!B:M,4,FALSE()) -> ARI/14 | E41: =IFERROR(VLOOKUP(DraftSheet!$C41,Aggregate!$B:$M,8,FALSE()),"") -> 14.518212 | F41: =IF(Scoring!$K$6="Auction",IFERROR(VLOOKUP(DraftSheet!$C41,Aggregate!$B:$M,10,FALSE()),""),IFERROR(VLOOKUP(DraftSheet!$C41,Aggregate!$B:$M,9,FALSE()),"")) -> 1 | G41: =SUMIFS(J$42:$J44,I$42:$I44,"<>x",I$42:$I44,"<>o",J$42:$J44,">0")/Aggregate!$J$1 -> 0 | H41: {=IFERROR(INDEX(ECR!$K:$K,MATCH(DraftSheet!$C41,ECR!$C:$C,0)),"ND")} -> 329 | J41: =VLOOKUP(C41,Aggregate!B:J,9,FALSE()) -> -207.12859 | L41: =IFERROR(VLOOKUP(DraftSheet!$M41,Aggregate!$P:$AA,11,FALSE()),"") -> 6 | M41: =Aggregate!P42 -> Rachaad White | N41: =VLOOKUP(DraftSheet!$M41,Aggregate!P:AA,4,FALSE()) -> WAS/7 | O41: =IFERROR(VLOOKUP(DraftSheet!$M41,Aggregate!$P:$AA,8,FALSE()),"") -> 105.61101 | P41: =IF(Scoring!$K$6="Auction",IFERROR(VLOOKUP(DraftSheet!$M41,Aggregate!$P:$AA,10,FALSE()),""),IFERROR(VLOOKUP(DraftSheet!$M41,Aggregate!$P:$AA,9,FALSE()),"")) -> 8.1323105 | Q41: =SUMIFS($T42:T$84,$S42:S$84,"<>x",$S42:S$84,"<>o",$T42:T$84,">0")/Aggregate!$X$1 -> 0.04311571 | R41: {=IFERROR(INDEX(ECR!$K:$K,MATCH(DraftSheet!$M41,ECR!$C:$C,0)),"ND")} -> 114 | T41: =VLOOKUP(M41,Aggregate!P:X,9,FALSE()) -> 27.220125 | V41: =IFERROR(VLOOKUP(DraftSheet!$W41,Aggregate!$AD:$AO,11,FALSE()),"") -> 5 | W41: =Aggregate!AD39 -> Michael Pittman Jr. | X41: =VLOOKUP(DraftSheet!$W41,Aggregate!AD:AO,4,FALSE()) -> PIT/9 | Y41: =IFERROR(VLOOKUP(DraftSheet!$W41,Aggregate!$AD:$AO,8,FALSE()),"") -> 107.95623 | Z41: =IF(Scoring!$K$6="Auction",IFERROR(VLOOKUP(DraftSheet!$W41,Aggregate!$AD:$AO,10,FALSE()),""),IFERROR(VLOOKUP(DraftSheet!$W41,Aggregate!$AD:$AO,9,FALSE()),"")) -> 7.9266692 | AA41: =SUMIFS($AD42:AD$84,$AC42:AC$84,"<>x",$AC42:AC$84,"<>o",$AD42:AD$84,">0")/Aggregate!$AL$1 -> 0.13681526 | AB41: {=IFERROR(INDEX(ECR!$K:$K,MATCH(DraftSheet!$W41,ECR!$C:$C,0)),"ND")} -> 88 | AD41: =VLOOKUP(W41,Aggregate!AD:AL,9,FALSE()) -> 26.435305
B42: =IFERROR(VLOOKUP(DraftSheet!$C42,Aggregate!$B:$M,11,FALSE()),"") -> 13 | C42: =Aggregate!B42 -> Ty Simpson | D42: =VLOOKUP(DraftSheet!$C42,Aggregate!B:M,4,FALSE()) -> LAR/11 | E42: =IFERROR(VLOOKUP(DraftSheet!$C42,Aggregate!$B:$M,8,FALSE()),"") -> 14.309271 | F42: =IF(Scoring!$K$6="Auction",IFERROR(VLOOKUP(DraftSheet!$C42,Aggregate!$B:$M,10,FALSE()),""),IFERROR(VLOOKUP(DraftSheet!$C42,Aggregate!$B:$M,9,FALSE()),"")) -> 1 | G42: =SUMIFS(J42:$J$45,I42:$I$45,"<>x",I42:$I$45,"<>o",J42:$J$45,">0")/Aggregate!$J$1 -> 0 | H42: {=IFERROR(INDEX(ECR!$K:$K,MATCH(DraftSheet!$C42,ECR!$C:$C,0)),"ND")} -> 361 | J42: =VLOOKUP(C42,Aggregate!B:J,9,FALSE()) -> -207.33754 | L42: =IFERROR(VLOOKUP(DraftSheet!$M42,Aggregate!$P:$AA,11,FALSE()),"") -> 6 | M42: =Aggregate!P40 -> Kenny Gainwell | N42: =VLOOKUP(DraftSheet!$M42,Aggregate!P:AA,4,FALSE()) -> TB/10 | O42: =IFERROR(VLOOKUP(DraftSheet!$M42,Aggregate!$P:$AA,8,FALSE()),"") -> 105.51993 | P42: =IF(Scoring!$K$6="Auction",IFERROR(VLOOKUP(DraftSheet!$M42,Aggregate!$P:$AA,10,FALSE()),""),IFERROR(VLOOKUP(DraftSheet!$M42,Aggregate!$P:$AA,9,FALSE()),"")) -> 8.1084433 | Q42: =SUMIFS($T43:T$84,$S43:S$84,"<>x",$S43:S$84,"<>o",$T43:T$84,">0")/Aggregate!$X$1 -> 0.034675416 | R42: {=IFERROR(INDEX(ECR!$K:$K,MATCH(DraftSheet!$M42,ECR!$C:$C,0)),"ND")} -> 109 | T42: =VLOOKUP(M42,Aggregate!P:X,9,FALSE()) -> 27.129037 | V42: =IFERROR(VLOOKUP(DraftSheet!$W42,Aggregate!$AD:$AO,11,FALSE()),"") -> 5 | W42: =Aggregate!AD50 -> KC Concepcion | X42: =VLOOKUP(DraftSheet!$W42,Aggregate!AD:AO,4,FALSE()) -> CLE/11 | Y42: =IFERROR(VLOOKUP(DraftSheet!$W42,Aggregate!$AD:$AO,8,FALSE()),"") -> 107.16802 | Z42: =IF(Scoring!$K$6="Auction",IFERROR(VLOOKUP(DraftSheet!$W42,Aggregate!$AD:$AO,10,FALSE()),""),IFERROR(VLOOKUP(DraftSheet!$W42,Aggregate!$AD:$AO,9,FALSE()),"")) -> 7.7201389 | AA42: =SUMIFS($AD43:AD$84,$AC43:AC$84,"<>x",$AC43:AC$84,"<>o",$AD43:AD$84,">0")/Aggregate!$AL$1 -> 0.12845054 | AB42: {=IFERROR(INDEX(ECR!$K:$K,MATCH(DraftSheet!$W42,ECR!$C:$C,0)),"ND")} -> 121 | AD42: =VLOOKUP(W42,Aggregate!AD:AL,9,FALSE()) -> 25.647092
B43: =IFERROR(VLOOKUP(DraftSheet!$C43,Aggregate!$B:$M,11,FALSE()),"") -> 13 | C43: =Aggregate!B41 -> Justin Fields | D43: =VLOOKUP(DraftSheet!$C43,Aggregate!B:M,4,FALSE()) -> KC/5 | E43: =IFERROR(VLOOKUP(DraftSheet!$C43,Aggregate!$B:$M,8,FALSE()),"") -> 8.8082824 | F43: =IF(Scoring!$K$6="Auction",IFERROR(VLOOKUP(DraftSheet!$C43,Aggregate!$B:$M,10,FALSE()),""),IFERROR(VLOOKUP(DraftSheet!$C43,Aggregate!$B:$M,9,FALSE()),"")) -> 1 | G43: =SUMIFS(J44:$J$44,I44:$I$44,"<>x",I44:$I$44,"<>o",J44:$J$44,">0")/Aggregate!$J$1 -> 0 | H43: {=IFERROR(INDEX(ECR!$K:$K,MATCH(DraftSheet!$C43,ECR!$C:$C,0)),"ND")} -> 357 | J43: =VLOOKUP(C43,Aggregate!B:J,9,FALSE()) -> -212.83852 | L43: =IFERROR(VLOOKUP(DraftSheet!$M43,Aggregate!$P:$AA,11,FALSE()),"") -> 6 | M43: =Aggregate!P43 -> Aaron Jones Sr. | N43: =VLOOKUP(DraftSheet!$M43,Aggregate!P:AA,4,FALSE()) -> MIN/6 | O43: =IFERROR(VLOOKUP(DraftSheet!$M43,Aggregate!$P:$AA,8,FALSE()),"") -> 103.3015 | P43: =IF(Scoring!$K$6="Auction",IFERROR(VLOOKUP(DraftSheet!$M43,Aggregate!$P:$AA,10,FALSE()),""),IFERROR(VLOOKUP(DraftSheet!$M43,Aggregate!$P:$AA,9,FALSE()),"")) -> 7.5271628 | Q43: =SUMIFS($T44:T$84,$S44:S$84,"<>x",$S44:S$84,"<>o",$T44:T$84,">0")/Aggregate!$X$1 -> 0.026925312 | R43: {=IFERROR(INDEX(ECR!$K:$K,MATCH(DraftSheet!$M43,ECR!$C:$C,0)),"ND")} -> 117 | T43: =VLOOKUP(M43,Aggregate!P:X,9,FALSE()) -> 24.910607 | V43: =IFERROR(VLOOKUP(DraftSheet!$W43,Aggregate!$AD:$AO,11,FALSE()),"") -> 5 | W43: =Aggregate!AD40 -> Michael Wilson | X43: =VLOOKUP(DraftSheet!$W43,Aggregate!AD:AO,4,FALSE()) -> ARI/14 | Y43: =IFERROR(VLOOKUP(DraftSheet!$W43,Aggregate!$AD:$AO,8,FALSE()),"") -> 106.17613 | Z43: =IF(Scoring!$K$6="Auction",IFERROR(VLOOKUP(DraftSheet!$W43,Aggregate!$AD:$AO,10,FALSE()),""),IFERROR(VLOOKUP(DraftSheet!$W43,Aggregate!$AD:$AO,9,FALSE()),"")) -> 7.4602414 | AA43: =SUMIFS($AD44:AD$84,$AC44:AC$84,"<>x",$AC44:AC$84,"<>o",$AD44:AD$84,">0")/Aggregate!$AL$1 -> 0.12040932 | AB43: {=IFERROR(INDEX(ECR!$K:$K,MATCH(DraftSheet!$W43,ECR!$C:$C,0)),"ND")} -> 89 | AD43: =VLOOKUP(W43,Aggregate!AD:AL,9,FALSE()) -> 24.655205
B44: =IFERROR(VLOOKUP(DraftSheet!$C44,Aggregate!$B:$M,11,FALSE()),"") -> 13 | C44: =Aggregate!B40 -> Mac Jones | D44: =VLOOKUP(DraftSheet!$C44,Aggregate!B:M,4,FALSE()) -> SF/8 | E44: =IFERROR(VLOOKUP(DraftSheet!$C44,Aggregate!$B:$M,8,FALSE()),"") -> 8.4423529 | F44: =IF(Scoring!$K$6="Auction",IFERROR(VLOOKUP(DraftSheet!$C44,Aggregate!$B:$M,10,FALSE()),""),IFERROR(VLOOKUP(DraftSheet!$C44,Aggregate!$B:$M,9,FALSE()),"")) -> 1 | G44: =SUMIFS(J44:$J$45,I44:$I$45,"<>x",I44:$I$45,"<>o",J44:$J$45,">0")/Aggregate!$J$1 -> 0 | H44: {=IFERROR(INDEX(ECR!$K:$K,MATCH(DraftSheet!$C44,ECR!$C:$C,0)),"ND")} -> 346 | J44: =VLOOKUP(C44,Aggregate!B:J,9,FALSE()) -> -213.20445 | L44: =IFERROR(VLOOKUP(DraftSheet!$M44,Aggregate!$P:$AA,11,FALSE()),"") -> 6 | M44: =Aggregate!P39 -> Jordan Mason | N44: =VLOOKUP(DraftSheet!$M44,Aggregate!P:AA,4,FALSE()) -> MIN/6 | O44: =IFERROR(VLOOKUP(DraftSheet!$M44,Aggregate!$P:$AA,8,FALSE()),"") -> 102.76827 | P44: =IF(Scoring!$K$6="Auction",IFERROR(VLOOKUP(DraftSheet!$M44,Aggregate!$P:$AA,10,FALSE()),""),IFERROR(VLOOKUP(DraftSheet!$M44,Aggregate!$P:$AA,9,FALSE()),"")) -> 7.3874444 | Q44: =SUMIFS($T45:T$84,$S45:S$84,"<>x",$S45:S$84,"<>o",$T45:T$84,">0")/Aggregate!$X$1 -> 0.019341105 | R44: {=IFERROR(INDEX(ECR!$K:$K,MATCH(DraftSheet!$M44,ECR!$C:$C,0)),"ND")} -> 107 | T44: =VLOOKUP(M44,Aggregate!P:X,9,FALSE()) -> 24.377379 | V44: =IFERROR(VLOOKUP(DraftSheet!$W44,Aggregate!$AD:$AO,11,FALSE()),"") -> 5 | W44: =Aggregate!AD49 -> Makai Lemon | X44: =VLOOKUP(DraftSheet!$W44,Aggregate!AD:AO,4,FALSE()) -> PHI/10 | Y44: =IFERROR(VLOOKUP(DraftSheet!$W44,Aggregate!$AD:$AO,8,FALSE()),"") -> 105.2278 | Z44: =IF(Scoring!$K$6="Auction",IFERROR(VLOOKUP(DraftSheet!$W44,Aggregate!$AD:$AO,10,FALSE()),""),IFERROR(VLOOKUP(DraftSheet!$W44,Aggregate!$AD:$AO,9,FALSE()),"")) -> 7.2117568 | AA44: =SUMIFS($AD45:AD$84,$AC45:AC$84,"<>x",$AC45:AC$84,"<>o",$AD45:AD$84,">0")/Aggregate!$AL$1 -> 0.11267739 | AB44: {=IFERROR(INDEX(ECR!$K:$K,MATCH(DraftSheet!$W44,ECR!$C:$C,0)),"ND")} -> 116 | AD44: =VLOOKUP(W44,Aggregate!AD:AL,9,FALSE()) -> 23.706875
L45: =IFERROR(VLOOKUP(DraftSheet!$M45,Aggregate!$P:$AA,11,FALSE()),"") -> 6 | M45: =Aggregate!P36 -> Blake Corum | N45: =VLOOKUP(DraftSheet!$M45,Aggregate!P:AA,4,FALSE()) -> LAR/11 | O45: =IFERROR(VLOOKUP(DraftSheet!$M45,Aggregate!$P:$AA,8,FALSE()),"") -> 101.50004 | P45: =IF(Scoring!$K$6="Auction",IFERROR(VLOOKUP(DraftSheet!$M45,Aggregate!$P:$AA,10,FALSE()),""),IFERROR(VLOOKUP(DraftSheet!$M45,Aggregate!$P:$AA,9,FALSE()),"")) -> 7.0551389 | Q45: =SUMIFS($T46:T$84,$S46:S$84,"<>x",$S46:S$84,"<>o",$T46:T$84,">0")/Aggregate!$X$1 -> 0.012151464 | R45: {=IFERROR(INDEX(ECR!$K:$K,MATCH(DraftSheet!$M45,ECR!$C:$C,0)),"ND")} -> 94 | T45: =VLOOKUP(M45,Aggregate!P:X,9,FALSE()) -> 23.109151 | V45: =IFERROR(VLOOKUP(DraftSheet!$W45,Aggregate!$AD:$AO,11,FALSE()),"") -> 5 | W45: =Aggregate!AD47 -> Jayden Reed | X45: =VLOOKUP(DraftSheet!$W45,Aggregate!AD:AO,4,FALSE()) -> GB/11 | Y45: =IFERROR(VLOOKUP(DraftSheet!$W45,Aggregate!$AD:$AO,8,FALSE()),"") -> 105.17043 | Z45: =IF(Scoring!$K$6="Auction",IFERROR(VLOOKUP(DraftSheet!$W45,Aggregate!$AD:$AO,10,FALSE()),""),IFERROR(VLOOKUP(DraftSheet!$W45,Aggregate!$AD:$AO,9,FALSE()),"")) -> 7.1967229 | AA45: =SUMIFS($AD46:AD$84,$AC46:AC$84,"<>x",$AC46:AC$84,"<>o",$AD46:AD$84,">0")/Aggregate!$AL$1 -> 0.10496418 | AB45: {=IFERROR(INDEX(ECR!$K:$K,MATCH(DraftSheet!$W45,ECR!$C:$C,0)),"ND")} -> 108 | AD45: =VLOOKUP(W45,Aggregate!AD:AL,9,FALSE()) -> 23.649499
B46: TIGHT END | L46: =IFERROR(VLOOKUP(DraftSheet!$M46,Aggregate!$P:$AA,11,FALSE()),"") -> 7 | M46: =Aggregate!P59 -> Mike Washington Jr. | N46: =VLOOKUP(DraftSheet!$M46,Aggregate!P:AA,4,FALSE()) -> LV/13 | O46: =IFERROR(VLOOKUP(DraftSheet!$M46,Aggregate!$P:$AA,8,FALSE()),"") -> 91.059154 | P46: =IF(Scoring!$K$6="Auction",IFERROR(VLOOKUP(DraftSheet!$M46,Aggregate!$P:$AA,10,FALSE()),""),IFERROR(VLOOKUP(DraftSheet!$M46,Aggregate!$P:$AA,9,FALSE()),"")) -> 4.3193822 | Q46: =SUMIFS($T47:T$84,$S47:S$84,"<>x",$S47:S$84,"<>o",$T47:T$84,">0")/Aggregate!$X$1 -> 0.0082101564 | R46: {=IFERROR(INDEX(ECR!$K:$K,MATCH(DraftSheet!$M46,ECR!$C:$C,0)),"ND")} -> 167 | T46: =VLOOKUP(M46,Aggregate!P:X,9,FALSE()) -> 12.668265 | V46: =IFERROR(VLOOKUP(DraftSheet!$W46,Aggregate!$AD:$AO,11,FALSE()),"") -> 5 | W46: =Aggregate!AD37 -> Chris Godwin Jr. | X46: =VLOOKUP(DraftSheet!$W46,Aggregate!AD:AO,4,FALSE()) -> TB/10 | Y46: =IFERROR(VLOOKUP(DraftSheet!$W46,Aggregate!$AD:$AO,8,FALSE()),"") -> 105.08523 | Z46: =IF(Scoring!$K$6="Auction",IFERROR(VLOOKUP(DraftSheet!$W46,Aggregate!$AD:$AO,10,FALSE()),""),IFERROR(VLOOKUP(DraftSheet!$W46,Aggregate!$AD:$AO,9,FALSE()),"")) -> 7.1743989 | AA46: =SUMIFS($AD47:AD$84,$AC47:AC$84,"<>x",$AC47:AC$84,"<>o",$AD47:AD$84,">0")/Aggregate!$AL$1 -> 0.097278752 | AB46: {=IFERROR(INDEX(ECR!$K:$K,MATCH(DraftSheet!$W46,ECR!$C:$C,0)),"ND")} -> 83 | AD46: =VLOOKUP(W46,Aggregate!AD:AL,9,FALSE()) -> 23.564301
B47: TIER | C47: NAME | D47: TM/BYE | E47: PTS | F47: VALUE | G47: PS | H47: ECR | I47: DRAFT | L47: =IFERROR(VLOOKUP(DraftSheet!$M47,Aggregate!$P:$AA,11,FALSE()),"") -> 7 | M47: =Aggregate!P45 -> Woody Marks | N47: =VLOOKUP(DraftSheet!$M47,Aggregate!P:AA,4,FALSE()) -> HOU/8 | O47: =IFERROR(VLOOKUP(DraftSheet!$M47,Aggregate!$P:$AA,8,FALSE()),"") -> 86.283274 | P47: =IF(Scoring!$K$6="Auction",IFERROR(VLOOKUP(DraftSheet!$M47,Aggregate!$P:$AA,10,FALSE()),""),IFERROR(VLOOKUP(DraftSheet!$M47,Aggregate!$P:$AA,9,FALSE()),"")) -> 3.0679896 | Q47: =SUMIFS($T48:T$84,$S48:S$84,"<>x",$S48:S$84,"<>o",$T48:T$84,">0")/Aggregate!$X$1 -> 0.0057547045 | R47: {=IFERROR(INDEX(ECR!$K:$K,MATCH(DraftSheet!$M47,ECR!$C:$C,0)),"ND")} -> 130 | T47: =VLOOKUP(M47,Aggregate!P:X,9,FALSE()) -> 7.8923844 | V47: =IFERROR(VLOOKUP(DraftSheet!$W47,Aggregate!$AD:$AO,11,FALSE()),"") -> 5 | W47: =Aggregate!AD41 -> Quentin Johnston | X47: =VLOOKUP(DraftSheet!$W47,Aggregate!AD:AO,4,FALSE()) -> LAC/7 | Y47: =IFERROR(VLOOKUP(DraftSheet!$W47,Aggregate!$AD:$AO,8,FALSE()),"") -> 104.96892 | Z47: =IF(Scoring!$K$6="Auction",IFERROR(VLOOKUP(DraftSheet!$W47,Aggregate!$AD:$AO,10,FALSE()),""),IFERROR(VLOOKUP(DraftSheet!$W47,Aggregate!$AD:$AO,9,FALSE()),"")) -> 7.1439245 | AA47: =SUMIFS($AD48:AD$84,$AC48:AC$84,"<>x",$AC48:AC$84,"<>o",$AD48:AD$84,">0")/Aggregate!$AL$1 -> 0.089631259 | AB47: {=IFERROR(INDEX(ECR!$K:$K,MATCH(DraftSheet!$W47,ECR!$C:$C,0)),"ND")} -> 90 | AD47: =VLOOKUP(W47,Aggregate!AD:AL,9,FALSE()) -> 23.447996
B48: =IFERROR(VLOOKUP(DraftSheet!$C48,Aggregate!$AR:$BC,11,FALSE()),"") -> 1 | C48: =Aggregate!AR3 -> Brock Bowers | D48: =VLOOKUP(DraftSheet!$C48,Aggregate!AR:BD,4,FALSE()) -> LV/13 | E48: =IFERROR(VLOOKUP(DraftSheet!$C48,Aggregate!$AR:$BC,8,FALSE()),"") -> 163.76189 | F48: =IF(Scoring!$K$6="Auction",IFERROR(VLOOKUP($C48,Aggregate!$AR:$BC,10,FALSE()),""),IFERROR(VLOOKUP($C48,Aggregate!$AR:$BC,9,FALSE()),"")) -> 22.5445 | G48: =SUMIFS($J49:J$84,$I49:I$84,"<>x",$I49:I$84,"<>o",$J49:J$84,">0")/Aggregate!$AZ$1 -> 0.8762067 | H48: {=IFERROR(INDEX(ECR!$K:$K,MATCH(DraftSheet!$C48,ECR!$C:$C,0)),"ND")} -> 18 | J48: =VLOOKUP(C48,Aggregate!AR:AZ,9,FALSE()) -> 82.223562 | L48: =IFERROR(VLOOKUP(DraftSheet!$M48,Aggregate!$P:$AA,11,FALSE()),"") -> 7 | M48: =Aggregate!P47 -> Tyjae Spears | N48: =VLOOKUP(DraftSheet!$M48,Aggregate!P:AA,4,FALSE()) -> TEN/9 | O48: =IFERROR(VLOOKUP(DraftSheet!$M48,Aggregate!$P:$AA,8,FALSE()),"") -> 85.453288 | P48: =IF(Scoring!$K$6="Auction",IFERROR(VLOOKUP(DraftSheet!$M48,Aggregate!$P:$AA,10,FALSE()),""),IFERROR(VLOOKUP(DraftSheet!$M48,Aggregate!$P:$AA,9,FALSE()),"")) -> 2.850514 | Q48: =SUMIFS($T49:T$84,$S49:S$84,"<>x",$S49:S$84,"<>o",$T49:T$84,">0")/Aggregate!$X$1 -> 0.0035574749 | R48: {=IFERROR(INDEX(ECR!$K:$K,MATCH(DraftSheet!$M48,ECR!$C:$C,0)),"ND")} -> 136 | T48: =VLOOKUP(M48,Aggregate!P:X,9,FALSE()) -> 7.0623989 | V48: =IFERROR(VLOOKUP(DraftSheet!$W48,Aggregate!$AD:$AO,11,FALSE()),"") -> 5 | W48: =Aggregate!AD48 -> Jakobi Meyers | X48: =VLOOKUP(DraftSheet!$W48,Aggregate!AD:AO,4,FALSE()) -> JAC/7 | Y48: =IFERROR(VLOOKUP(DraftSheet!$W48,Aggregate!$AD:$AO,8,FALSE()),"") -> 104.53553 | Z48: =IF(Scoring!$K$6="Auction",IFERROR(VLOOKUP(DraftSheet!$W48,Aggregate!$AD:$AO,10,FALSE()),""),IFERROR(VLOOKUP(DraftSheet!$W48,Aggregate!$AD:$AO,9,FALSE()),"")) -> 7.030365 | AA48: =SUMIFS($AD49:AD$84,$AC49:AC$84,"<>x",$AC49:AC$84,"<>o",$AD49:AD$84,">0")/Aggregate!$AL$1 -> 0.082125116 | AB48: {=IFERROR(INDEX(ECR!$K:$K,MATCH(DraftSheet!$W48,ECR!$C:$C,0)),"ND")} -> 113 | AD48: =VLOOKUP(W48,Aggregate!AD:AL,9,FALSE()) -> 23.014602
B49: =IFERROR(VLOOKUP(DraftSheet!$C49,Aggregate!$AR:$BC,11,FALSE()),"") -> 1 | C49: =Aggregate!AR4 -> Trey McBride | D49: =VLOOKUP(DraftSheet!$C49,Aggregate!AR:BD,4,FALSE()) -> ARI/14 | E49: =IFERROR(VLOOKUP($C49,Aggregate!$AR:$BC,8,FALSE()),"") -> 162.15397 | F49: =IF(Scoring!$K$6="Auction",IFERROR(VLOOKUP($C49,Aggregate!$AR:$BC,10,FALSE()),""),IFERROR(VLOOKUP($C49,Aggregate!$AR:$BC,9,FALSE()),"")) -> 22.123185 | G49: =SUMIFS($J50:J$84,$I50:I$84,"<>x",$I50:I$84,"<>o",$J50:J$84,">0")/Aggregate!$AZ$1 -> 0.75483425 | H49: {=IFERROR(INDEX(ECR!$K:$K,MATCH(DraftSheet!$C49,ECR!$C:$C,0)),"ND")} -> 25 | J49: =VLOOKUP(C49,Aggregate!AR:AZ,9,FALSE()) -> 80.615636 | L49: =IFERROR(VLOOKUP(DraftSheet!$M49,Aggregate!$P:$AA,11,FALSE()),"") -> 7 | M49: =Aggregate!P50 -> Jonah Coleman | N49: =VLOOKUP(DraftSheet!$M49,Aggregate!P:AA,4,FALSE()) -> DEN/10 | O49: =IFERROR(VLOOKUP(DraftSheet!$M49,Aggregate!$P:$AA,8,FALSE()),"") -> 84.130257 | P49: =IF(Scoring!$K$6="Auction",IFERROR(VLOOKUP(DraftSheet!$M49,Aggregate!$P:$AA,10,FALSE()),""),IFERROR(VLOOKUP(DraftSheet!$M49,Aggregate!$P:$AA,9,FALSE()),"")) -> 2.5038488 | Q49: =SUMIFS($T50:T$84,$S50:S$84,"<>x",$S50:S$84,"<>o",$T50:T$84,">0")/Aggregate!$X$1 -> 0.0017718622 | R49: {=IFERROR(INDEX(ECR!$K:$K,MATCH(DraftSheet!$M49,ECR!$C:$C,0)),"ND")} -> 143 | T49: =VLOOKUP(M49,Aggregate!P:X,9,FALSE()) -> 5.7393678 | V49: =IFERROR(VLOOKUP(DraftSheet!$W49,Aggregate!$AD:$AO,11,FALSE()),"") -> 5 | W49: =Aggregate!AD46 -> Jordan Addison | X49: =VLOOKUP(DraftSheet!$W49,Aggregate!AD:AO,4,FALSE()) -> MIN/6 | Y49: =IFERROR(VLOOKUP(DraftSheet!$W49,Aggregate!$AD:$AO,8,FALSE()),"") -> 103.51354 | Z49: =IF(Scoring!$K$6="Auction",IFERROR(VLOOKUP(DraftSheet!$W49,Aggregate!$AD:$AO,10,FALSE()),""),IFERROR(VLOOKUP(DraftSheet!$W49,Aggregate!$AD:$AO,9,FALSE()),"")) -> 6.7625809 | AA49: =SUMIFS($AD50:AD$84,$AC50:AC$84,"<>x",$AC50:AC$84,"<>o",$AD50:AD$84,">0")/Aggregate!$AL$1 -> 0.074952291 | AB49: {=IFERROR(INDEX(ECR!$K:$K,MATCH(DraftSheet!$W49,ECR!$C:$C,0)),"ND")} -> 106 | AD49: =VLOOKUP(W49,Aggregate!AD:AL,9,FALSE()) -> 21.992617
B50: =IFERROR(VLOOKUP(DraftSheet!$C50,Aggregate!$AR:$BC,11,FALSE()),"") -> 2 | C50: =Aggregate!AR5 -> Colston Loveland | D50: =VLOOKUP(DraftSheet!$C50,Aggregate!AR:BD,4,FALSE()) -> CHI/10 | E50: =IFERROR(VLOOKUP($C50,Aggregate!$AR:$BC,8,FALSE()),"") -> 138.52445 | F50: =IF(Scoring!$K$6="Auction",IFERROR(VLOOKUP($C50,Aggregate!$AR:$BC,10,FALSE()),""),IFERROR(VLOOKUP($C50,Aggregate!$AR:$BC,9,FALSE()),"")) -> 15.931699 | G50: =SUMIFS($J51:J$84,$I51:I$84,"<>x",$I51:I$84,"<>o",$J51:J$84,">0")/Aggregate!$AZ$1 -> 0.66903767 | H50: {=IFERROR(INDEX(ECR!$K:$K,MATCH(DraftSheet!$C50,ECR!$C:$C,0)),"ND")} -> 42 | J50: =VLOOKUP(C50,Aggregate!AR:AZ,9,FALSE()) -> 56.986123 | L50: =IFERROR(VLOOKUP(DraftSheet!$M50,Aggregate!$P:$AA,11,FALSE()),"") -> 7 | M50: =Aggregate!P51 -> Zach Charbonnet | N50: =VLOOKUP(DraftSheet!$M50,Aggregate!P:AA,4,FALSE()) -> SEA/11 | O50: =IFERROR(VLOOKUP(DraftSheet!$M50,Aggregate!$P:$AA,8,FALSE()),"") -> 81.246052 | P50: =IF(Scoring!$K$6="Auction",IFERROR(VLOOKUP(DraftSheet!$M50,Aggregate!$P:$AA,10,FALSE()),""),IFERROR(VLOOKUP(DraftSheet!$M50,Aggregate!$P:$AA,9,FALSE()),"")) -> 1.7481195 | Q50: =SUMIFS($T50:T$85,$S50:S$85,"<>x",$S50:S$85,"<>o",$T50:T$85,">0")/Aggregate!$X$1 -> 0.0017718622 | R50: {=IFERROR(INDEX(ECR!$K:$K,MATCH(DraftSheet!$M50,ECR!$C:$C,0)),"ND")} -> 145 | T50: =VLOOKUP(M50,Aggregate!P:X,9,FALSE()) -> 2.8551627 | V50: =IFERROR(VLOOKUP(DraftSheet!$W50,Aggregate!$AD:$AO,11,FALSE()),"") -> 5 | W50: =Aggregate!AD58 -> De'Zhaun Stribling | X50: =VLOOKUP(DraftSheet!$W50,Aggregate!AD:AO,4,FALSE()) -> SF/8 | Y50: =IFERROR(VLOOKUP(DraftSheet!$W50,Aggregate!$AD:$AO,8,FALSE()),"") -> 103.4354 | Z50: =IF(Scoring!$K$6="Auction",IFERROR(VLOOKUP(DraftSheet!$W50,Aggregate!$AD:$AO,10,FALSE()),""),IFERROR(VLOOKUP(DraftSheet!$W50,Aggregate!$AD:$AO,9,FALSE()),"")) -> 6.7421061 | AA50: =SUMIFS($AD51:AD$84,$AC51:AC$84,"<>x",$AC51:AC$84,"<>o",$AD51:AD$84,">0")/Aggregate!$AL$1 -> 0.067804951 | AB50: {=IFERROR(INDEX(ECR!$K:$K,MATCH(DraftSheet!$W50,ECR!$C:$C,0)),"ND")} -> 146 | AD50: =VLOOKUP(W50,Aggregate!AD:AL,9,FALSE()) -> 21.914476
B51: =IFERROR(VLOOKUP(DraftSheet!$C51,Aggregate!$AR:$BC,11,FALSE()),"") -> 2 | C51: =Aggregate!AR6 -> Tyler Warren | D51: =VLOOKUP(DraftSheet!$C51,Aggregate!AR:BD,4,FALSE()) -> IND/13 | E51: =IFERROR(VLOOKUP($C51,Aggregate!$AR:$BC,8,FALSE()),"") -> 126.65505 | F51: =IF(Scoring!$K$6="Auction",IFERROR(VLOOKUP($C51,Aggregate!$AR:$BC,10,FALSE()),""),IFERROR(VLOOKUP($C51,Aggregate!$AR:$BC,9,FALSE()),"")) -> 12.821636 | G51: =SUMIFS($J52:J$84,$I52:I$84,"<>x",$I52:I$84,"<>o",$J52:J$84,">0")/Aggregate!$AZ$1 -> 0.60111132 | H51: {=IFERROR(INDEX(ECR!$K:$K,MATCH(DraftSheet!$C51,ECR!$C:$C,0)),"ND")} -> 53 | J51: =VLOOKUP(C51,Aggregate!AR:AZ,9,FALSE()) -> 45.116714 | L51: =IFERROR(VLOOKUP(DraftSheet!$M51,Aggregate!$P:$AA,11,FALSE()),"") -> 7 | M51: =Aggregate!P72 -> Kaelon Black | N51: =VLOOKUP(DraftSheet!$M51,Aggregate!P:AA,4,FALSE()) -> SF/8 | O51: =IFERROR(VLOOKUP(DraftSheet!$M51,Aggregate!$P:$AA,8,FALSE()),"") -> 81.230897 | P51: =IF(Scoring!$K$6="Auction",IFERROR(VLOOKUP(DraftSheet!$M51,Aggregate!$P:$AA,10,FALSE()),""),IFERROR(VLOOKUP(DraftSheet!$M51,Aggregate!$P:$AA,9,FALSE()),"")) -> 1.7441486 | Q51: =SUMIFS($T51:T$85,$S51:S$85,"<>x",$S51:S$85,"<>o",$T51:T$85,">0")/Aggregate!$X$1 -> 0.00088357366 | R51: {=IFERROR(INDEX(ECR!$K:$K,MATCH(DraftSheet!$M51,ECR!$C:$C,0)),"ND")} -> 243 | T51: =VLOOKUP(M51,Aggregate!P:X,9,FALSE()) -> 2.840008 | V51: =IFERROR(VLOOKUP(DraftSheet!$W51,Aggregate!$AD:$AO,11,FALSE()),"") -> 5 | W51: =Aggregate!AD44 -> Wan'Dale Robinson | X51: =VLOOKUP(DraftSheet!$W51,Aggregate!AD:AO,4,FALSE()) -> TEN/9 | Y51: =IFERROR(VLOOKUP(DraftSheet!$W51,Aggregate!$AD:$AO,8,FALSE()),"") -> 102.19491 | Z51: =IF(Scoring!$K$6="Auction",IFERROR(VLOOKUP(DraftSheet!$W51,Aggregate!$AD:$AO,10,FALSE()),""),IFERROR(VLOOKUP(DraftSheet!$W51,Aggregate!$AD:$AO,9,FALSE()),"")) -> 6.4170684 | AA51: =SUMIFS($AD52:AD$84,$AC52:AC$84,"<>x",$AC52:AC$84,"<>o",$AD52:AD$84,">0")/Aggregate!$AL$1 -> 0.061062193 | AB51: {=IFERROR(INDEX(ECR!$K:$K,MATCH(DraftSheet!$W51,ECR!$C:$C,0)),"ND")} -> 101 | AD51: =VLOOKUP(W51,Aggregate!AD:AL,9,FALSE()) -> 20.673985
B52: =IFERROR(VLOOKUP(DraftSheet!$C52,Aggregate!$AR:$BC,11,FALSE()),"") -> 3 | C52: =Aggregate!AR8 -> Harold Fannin Jr. | D52: =VLOOKUP(DraftSheet!$C52,Aggregate!AR:BD,4,FALSE()) -> CLE/11 | E52: =IFERROR(VLOOKUP($C52,Aggregate!$AR:$BC,8,FALSE()),"") -> 119.67358 | F52: =IF(Scoring!$K$6="Auction",IFERROR(VLOOKUP($C52,Aggregate!$AR:$BC,10,FALSE()),""),IFERROR(VLOOKUP($C52,Aggregate!$AR:$BC,9,FALSE()),"")) -> 10.992328 | G52: =SUMIFS($J53:J$84,$I53:I$84,"<>x",$I53:I$84,"<>o",$J53:J$84,">0")/Aggregate!$AZ$1 -> 0.54369604 | H52: {=IFERROR(INDEX(ECR!$K:$K,MATCH(DraftSheet!$C52,ECR!$C:$C,0)),"ND")} -> 80 | J52: =VLOOKUP(C52,Aggregate!AR:AZ,9,FALSE()) -> 38.135248 | L52: =IFERROR(VLOOKUP(DraftSheet!$M52,Aggregate!$P:$AA,11,FALSE()),"") -> 7 | M52: =Aggregate!P44 -> Chris Rodriguez Jr. | N52: =VLOOKUP(DraftSheet!$M52,Aggregate!P:AA,4,FALSE()) -> JAC/7 | O52: =IFERROR(VLOOKUP(DraftSheet!$M52,Aggregate!$P:$AA,8,FALSE()),"") -> 78.390889 | P52: =IF(Scoring!$K$6="Auction",IFERROR(VLOOKUP(DraftSheet!$M52,Aggregate!$P:$AA,10,FALSE()),""),IFERROR(VLOOKUP(DraftSheet!$M52,Aggregate!$P:$AA,9,FALSE()),"")) -> 1 | Q52: =SUMIFS($T53:T$84,$S53:S$84,"<>x",$S53:S$84,"<>o",$T53:T$84,">0")/Aggregate!$X$1 -> 0 | R52: {=IFERROR(INDEX(ECR!$K:$K,MATCH(DraftSheet!$M52,ECR!$C:$C,0)),"ND")} -> 124 | T52: =VLOOKUP(M52,Aggregate!P:X,9,FALSE()) -> 0 | V52: =IFERROR(VLOOKUP(DraftSheet!$W52,Aggregate!$AD:$AO,11,FALSE()),"") -> 5 | W52: =Aggregate!AD51 -> Xavier Worthy | X52: =VLOOKUP(DraftSheet!$W52,Aggregate!AD:AO,4,FALSE()) -> KC/5 | Y52: =IFERROR(VLOOKUP(DraftSheet!$W52,Aggregate!$AD:$AO,8,FALSE()),"") -> 101.42435 | Z52: =IF(Scoring!$K$6="Auction",IFERROR(VLOOKUP(DraftSheet!$W52,Aggregate!$AD:$AO,10,FALSE()),""),IFERROR(VLOOKUP(DraftSheet!$W52,Aggregate!$AD:$AO,9,FALSE()),"")) -> 6.2151639 | AA52: =SUMIFS(AD$64:$AD73,AC$64:$AC73,"<>x",AC$64:$AC73,"<>o",AD$64:$AD73,">0")/Aggregate!$AL$1 -> 0.00389159 | AB52: {=IFERROR(INDEX(ECR!$K:$K,MATCH(DraftSheet!$W52,ECR!$C:$C,0)),"ND")} -> 126 | AD52: =VLOOKUP(W52,Aggregate!AD:AL,9,FALSE()) -> 19.903426
B53: =IFERROR(VLOOKUP(DraftSheet!$C53,Aggregate!$AR:$BC,11,FALSE()),"") -> 3 | C53: =Aggregate!AR7 -> Tucker Kraft | D53: =VLOOKUP(DraftSheet!$C53,Aggregate!AR:BD,4,FALSE()) -> GB/11 | E53: =IFERROR(VLOOKUP($C53,Aggregate!$AR:$BC,8,FALSE()),"") -> 119.17227 | F53: =IF(Scoring!$K$6="Auction",IFERROR(VLOOKUP($C53,Aggregate!$AR:$BC,10,FALSE()),""),IFERROR(VLOOKUP($C53,Aggregate!$AR:$BC,9,FALSE()),"")) -> 10.860974 | G53: =SUMIFS($J54:J$84,$I54:I$84,"<>x",$I54:I$84,"<>o",$J54:J$84,">0")/Aggregate!$AZ$1 -> 0.48703552 | H53: {=IFERROR(INDEX(ECR!$K:$K,MATCH(DraftSheet!$C53,ECR!$C:$C,0)),"ND")} -> 69 | J53: =VLOOKUP(C53,Aggregate!AR:AZ,9,FALSE()) -> 37.633941 | L53: =IFERROR(VLOOKUP(DraftSheet!$M53,Aggregate!$P:$AA,11,FALSE()),"") -> 7 | M53: =Aggregate!P54 -> Alvin Kamara | N53: =VLOOKUP(DraftSheet!$M53,Aggregate!P:AA,4,FALSE()) -> NO/8 | O53: =IFERROR(VLOOKUP(DraftSheet!$M53,Aggregate!$P:$AA,8,FALSE()),"") -> 76.092939 | P53: =IF(Scoring!$K$6="Auction",IFERROR(VLOOKUP(DraftSheet!$M53,Aggregate!$P:$AA,10,FALSE()),""),IFERROR(VLOOKUP(DraftSheet!$M53,Aggregate!$P:$AA,9,FALSE()),"")) -> 1 | Q53: =SUMIFS($T54:T$84,$S54:S$84,"<>x",$S54:S$84,"<>o",$T54:T$84,">0")/Aggregate!$X$1 -> 0 | R53: {=IFERROR(INDEX(ECR!$K:$K,MATCH(DraftSheet!$M53,ECR!$C:$C,0)),"ND")} -> 151 | T53: =VLOOKUP(M53,Aggregate!P:X,9,FALSE()) -> -2.2979503 | V53: =IFERROR(VLOOKUP(DraftSheet!$W53,Aggregate!$AD:$AO,11,FALSE()),"") -> 5 | W53: =Aggregate!AD61 -> Denzel Boston | X53: =VLOOKUP(DraftSheet!$W53,Aggregate!AD:AO,4,FALSE()) -> CLE/11 | Y53: =IFERROR(VLOOKUP(DraftSheet!$W53,Aggregate!$AD:$AO,8,FALSE()),"") -> 101.31438 | Z53: =IF(Scoring!$K$6="Auction",IFERROR(VLOOKUP(DraftSheet!$W53,Aggregate!$AD:$AO,10,FALSE()),""),IFERROR(VLOOKUP(DraftSheet!$W53,Aggregate!$AD:$AO,9,FALSE()),"")) -> 6.1863475 | AA53: =SUMIFS($AD54:AD$84,$AC54:AC$84,"<>x",$AC54:AC$84,"<>o",$AD54:AD$84,">0")/Aggregate!$AL$1 -> 0.048115177 | AB53: {=IFERROR(INDEX(ECR!$K:$K,MATCH(DraftSheet!$W53,ECR!$C:$C,0)),"ND")} -> 161 | AD53: =VLOOKUP(W53,Aggregate!AD:AL,9,FALSE()) -> 19.793449
B54: =IFERROR(VLOOKUP(DraftSheet!$C54,Aggregate!$AR:$BC,11,FALSE()),"") -> 3 | C54: =Aggregate!AR9 -> Sam LaPorta | D54: =VLOOKUP(DraftSheet!$C54,Aggregate!AR:BD,4,FALSE()) -> DET/6 | E54: =IFERROR(VLOOKUP($C54,Aggregate!$AR:$BC,8,FALSE()),"") -> 117.4143 | F54: =IF(Scoring!$K$6="Auction",IFERROR(VLOOKUP($C54,Aggregate!$AR:$BC,10,FALSE()),""),IFERROR(VLOOKUP($C54,Aggregate!$AR:$BC,9,FALSE()),"")) -> 10.400346 | G54: =SUMIFS($J55:J$84,$I55:I$84,"<>x",$I55:I$84,"<>o",$J55:J$84,">0")/Aggregate!$AZ$1 -> 0.43302175 | H54: {=IFERROR(INDEX(ECR!$K:$K,MATCH(DraftSheet!$C54,ECR!$C:$C,0)),"ND")} -> 81 | J54: =VLOOKUP(C54,Aggregate!AR:AZ,9,FALSE()) -> 35.875973 | L54: =IFERROR(VLOOKUP(DraftSheet!$M54,Aggregate!$P:$AA,11,FALSE()),"") -> 7 | M54: =Aggregate!P55 -> Isiah Pacheco | N54: =VLOOKUP(DraftSheet!$M54,Aggregate!P:AA,4,FALSE()) -> DET/6 | O54: =IFERROR(VLOOKUP(DraftSheet!$M54,Aggregate!$P:$AA,8,FALSE()),"") -> 75.361026 | P54: =IF(Scoring!$K$6="Auction",IFERROR(VLOOKUP(DraftSheet!$M54,Aggregate!$P:$AA,10,FALSE()),""),IFERROR(VLOOKUP(DraftSheet!$M54,Aggregate!$P:$AA,9,FALSE()),"")) -> 1 | Q54: =SUMIFS($T55:T$84,$S55:S$84,"<>x",$S55:S$84,"<>o",$T55:T$84,">0")/Aggregate!$X$1 -> 0 | R54: {=IFERROR(INDEX(ECR!$K:$K,MATCH(DraftSheet!$M54,ECR!$C:$C,0)),"ND")} -> 152 | T54: =VLOOKUP(M54,Aggregate!P:X,9,FALSE()) -> -3.0298632 | V54: =IFERROR(VLOOKUP(DraftSheet!$W54,Aggregate!$AD:$AO,11,FALSE()),"") -> 5 | W54: =Aggregate!AD57 -> Deebo Samuel Sr. | X54: =VLOOKUP(DraftSheet!$W54,Aggregate!AD:AO,4,FALSE()) -> SF/8 | Y54: =IFERROR(VLOOKUP(DraftSheet!$W54,Aggregate!$AD:$AO,8,FALSE()),"") -> 99.582971 | Z54: =IF(Scoring!$K$6="Auction",IFERROR(VLOOKUP(DraftSheet!$W54,Aggregate!$AD:$AO,10,FALSE()),""),IFERROR(VLOOKUP(DraftSheet!$W54,Aggregate!$AD:$AO,9,FALSE()),"")) -> 5.7326786 | AA54: =SUMIFS($AD55:AD$84,$AC55:AC$84,"<>x",$AC55:AC$84,"<>o",$AD55:AD$84,">0")/Aggregate!$AL$1 -> 0.042224296 | AB54: {=IFERROR(INDEX(ECR!$K:$K,MATCH(DraftSheet!$W54,ECR!$C:$C,0)),"ND")} -> 138 | AD54: =VLOOKUP(W54,Aggregate!AD:AL,9,FALSE()) -> 18.062044
B55: =IFERROR(VLOOKUP(DraftSheet!$C55,Aggregate!$AR:$BC,11,FALSE()),"") -> 3 | C55: =Aggregate!AR10 -> Kyle Pitts Sr. | D55: =VLOOKUP(DraftSheet!$C55,Aggregate!AR:BD,4,FALSE()) -> ATL/11 | E55: =IFERROR(VLOOKUP($C55,Aggregate!$AR:$BC,8,FALSE()),"") -> 117.1141 | F55: =IF(Scoring!$K$6="Auction",IFERROR(VLOOKUP($C55,Aggregate!$AR:$BC,10,FALSE()),""),IFERROR(VLOOKUP($C55,Aggregate!$AR:$BC,9,FALSE()),"")) -> 10.321686 | G55: =SUMIFS($J56:J$84,$I56:I$84,"<>x",$I56:I$84,"<>o",$J56:J$84,">0")/Aggregate!$AZ$1 -> 0.37945995 | H55: {=IFERROR(INDEX(ECR!$K:$K,MATCH(DraftSheet!$C55,ECR!$C:$C,0)),"ND")} -> 84 | J55: =VLOOKUP(C55,Aggregate!AR:AZ,9,FALSE()) -> 35.575771 | L55: =IFERROR(VLOOKUP(DraftSheet!$M55,Aggregate!$P:$AA,11,FALSE()),"") -> 7 | M55: =Aggregate!P46 -> Tyler Allgeier | N55: =VLOOKUP(DraftSheet!$M55,Aggregate!P:AA,4,FALSE()) -> ARI/14 | O55: =IFERROR(VLOOKUP(DraftSheet!$M55,Aggregate!$P:$AA,8,FALSE()),"") -> 71.666166 | P55: =IF(Scoring!$K$6="Auction",IFERROR(VLOOKUP(DraftSheet!$M55,Aggregate!$P:$AA,10,FALSE()),""),IFERROR(VLOOKUP(DraftSheet!$M55,Aggregate!$P:$AA,9,FALSE()),"")) -> 1 | Q55: =SUMIFS($T56:T$84,$S56:S$84,"<>x",$S56:S$84,"<>o",$T56:T$84,">0")/Aggregate!$X$1 -> 0 | R55: {=IFERROR(INDEX(ECR!$K:$K,MATCH(DraftSheet!$M55,ECR!$C:$C,0)),"ND")} -> 131 | T55: =VLOOKUP(M55,Aggregate!P:X,9,FALSE()) -> -6.7247232 | V55: =IFERROR(VLOOKUP(DraftSheet!$W55,Aggregate!$AD:$AO,11,FALSE()),"") -> 5 | W55: =Aggregate!AD45 -> Stefon Diggs | X55: =VLOOKUP(DraftSheet!$W55,Aggregate!AD:AO,4,FALSE()) -> WAS/7 | Y55: =IFERROR(VLOOKUP(DraftSheet!$W55,Aggregate!$AD:$AO,8,FALSE()),"") -> 98.342118 | Z55: =IF(Scoring!$K$6="Auction",IFERROR(VLOOKUP(DraftSheet!$W55,Aggregate!$AD:$AO,10,FALSE()),""),IFERROR(VLOOKUP(DraftSheet!$W55,Aggregate!$AD:$AO,9,FALSE()),"")) -> 5.407546 | AA55: =SUMIFS($AD56:AD$84,$AC56:AC$84,"<>x",$AC56:AC$84,"<>o",$AD56:AD$84,">0")/Aggregate!$AL$1 -> 0.036738116 | AB55: {=IFERROR(INDEX(ECR!$K:$K,MATCH(DraftSheet!$W55,ECR!$C:$C,0)),"ND")} -> 102 | AD55: =VLOOKUP(W55,Aggregate!AD:AL,9,FALSE()) -> 16.821191
B56: =IFERROR(VLOOKUP(DraftSheet!$C56,Aggregate!$AR:$BC,11,FALSE()),"") -> 3 | C56: =Aggregate!AR11 -> George Kittle | D56: =VLOOKUP(DraftSheet!$C56,Aggregate!AR:BD,4,FALSE()) -> SF/8 | E56: =IFERROR(VLOOKUP($C56,Aggregate!$AR:$BC,8,FALSE()),"") -> 115.88076 | F56: =IF(Scoring!$K$6="Auction",IFERROR(VLOOKUP($C56,Aggregate!$AR:$BC,10,FALSE()),""),IFERROR(VLOOKUP($C56,Aggregate!$AR:$BC,9,FALSE()),"")) -> 9.9985221 | G56: =SUMIFS($J57:J$84,$I57:I$84,"<>x",$I57:I$84,"<>o",$J57:J$84,">0")/Aggregate!$AZ$1 -> 0.32775502 | H56: {=IFERROR(INDEX(ECR!$K:$K,MATCH(DraftSheet!$C56,ECR!$C:$C,0)),"ND")} -> 95 | J56: =VLOOKUP(C56,Aggregate!AR:AZ,9,FALSE()) -> 34.342433 | L56: =IFERROR(VLOOKUP(DraftSheet!$M56,Aggregate!$P:$AA,11,FALSE()),"") -> 7 | M56: =Aggregate!P52 -> Dylan Sampson | N56: =VLOOKUP(DraftSheet!$M56,Aggregate!P:AA,4,FALSE()) -> CLE/11 | O56: =IFERROR(VLOOKUP(DraftSheet!$M56,Aggregate!$P:$AA,8,FALSE()),"") -> 69.552164 | P56: =IF(Scoring!$K$6="Auction",IFERROR(VLOOKUP(DraftSheet!$M56,Aggregate!$P:$AA,10,FALSE()),""),IFERROR(VLOOKUP(DraftSheet!$M56,Aggregate!$P:$AA,9,FALSE()),"")) -> 1 | Q56: =SUMIFS($T57:T$84,$S57:S$84,"<>x",$S57:S$84,"<>o",$T57:T$84,">0")/Aggregate!$X$1 -> 0 | R56: {=IFERROR(INDEX(ECR!$K:$K,MATCH(DraftSheet!$M56,ECR!$C:$C,0)),"ND")} -> 148 | T56: =VLOOKUP(M56,Aggregate!P:X,9,FALSE()) -> -8.8387256 | V56: =IFERROR(VLOOKUP(DraftSheet!$W56,Aggregate!$AD:$AO,11,FALSE()),"") -> 5 | W56: =Aggregate!AD53 -> Matthew Golden | X56: =VLOOKUP(DraftSheet!$W56,Aggregate!AD:AO,4,FALSE()) -> GB/11 | Y56: =IFERROR(VLOOKUP(DraftSheet!$W56,Aggregate!$AD:$AO,8,FALSE()),"") -> 98.099735 | Z56: =IF(Scoring!$K$6="Auction",IFERROR(VLOOKUP(DraftSheet!$W56,Aggregate!$AD:$AO,10,FALSE()),""),IFERROR(VLOOKUP(DraftSheet!$W56,Aggregate!$AD:$AO,9,FALSE()),"")) -> 5.3440362 | AA56: =SUMIFS($AD57:AD$84,$AC57:AC$84,"<>x",$AC57:AC$84,"<>o",$AD57:AD$84,">0")/Aggregate!$AL$1 -> 0.031330987 | AB56: {=IFERROR(INDEX(ECR!$K:$K,MATCH(DraftSheet!$W56,ECR!$C:$C,0)),"ND")} -> 129 | AD56: =VLOOKUP(W56,Aggregate!AD:AL,9,FALSE()) -> 16.578808
B57: =IFERROR(VLOOKUP(DraftSheet!$C57,Aggregate!$AR:$BC,11,FALSE()),"") -> 3 | C57: =Aggregate!AR12 -> Travis Kelce | D57: =VLOOKUP(DraftSheet!$C57,Aggregate!AR:BD,4,FALSE()) -> KC/5 | E57: =IFERROR(VLOOKUP($C57,Aggregate!$AR:$BC,8,FALSE()),"") -> 113.72934 | F57: =IF(Scoring!$K$6="Auction",IFERROR(VLOOKUP($C57,Aggregate!$AR:$BC,10,FALSE()),""),IFERROR(VLOOKUP($C57,Aggregate!$AR:$BC,9,FALSE()),"")) -> 9.4347992 | G57: =SUMIFS($J58:J$84,$I58:I$84,"<>x",$I58:I$84,"<>o",$J58:J$84,">0")/Aggregate!$AZ$1 -> 0.27928921 | H57: {=IFERROR(INDEX(ECR!$K:$K,MATCH(DraftSheet!$C57,ECR!$C:$C,0)),"ND")} -> 105 | J57: =VLOOKUP(C57,Aggregate!AR:AZ,9,FALSE()) -> 32.191011 | L57: =IFERROR(VLOOKUP(DraftSheet!$M57,Aggregate!$P:$AA,11,FALSE()),"") -> 7 | M57: =Aggregate!P53 -> Tyrone Tracy Jr. | N57: =VLOOKUP(DraftSheet!$M57,Aggregate!P:AA,4,FALSE()) -> NYG/8 | O57: =IFERROR(VLOOKUP(DraftSheet!$M57,Aggregate!$P:$AA,8,FALSE()),"") -> 68.534173 | P57: =IF(Scoring!$K$6="Auction",IFERROR(VLOOKUP(DraftSheet!$M57,Aggregate!$P:$AA,10,FALSE()),""),IFERROR(VLOOKUP(DraftSheet!$M57,Aggregate!$P:$AA,9,FALSE()),"")) -> 1 | Q57: =SUMIFS($T58:T$84,$S58:S$84,"<>x",$S58:S$84,"<>o",$T58:T$84,">0")/Aggregate!$X$1 -> 0 | R57: {=IFERROR(INDEX(ECR!$K:$K,MATCH(DraftSheet!$M57,ECR!$C:$C,0)),"ND")} -> 149 | T57: =VLOOKUP(M57,Aggregate!P:X,9,FALSE()) -> -9.8567162 | V57: =IFERROR(VLOOKUP(DraftSheet!$W57,Aggregate!$AD:$AO,11,FALSE()),"") -> 5 | W57: =Aggregate!AD56 -> Romeo Doubs | X57: =VLOOKUP(DraftSheet!$W57,Aggregate!AD:AO,4,FALSE()) -> NE/11 | Y57: =IFERROR(VLOOKUP(DraftSheet!$W57,Aggregate!$AD:$AO,8,FALSE()),"") -> 97.151912 | Z57: =IF(Scoring!$K$6="Auction",IFERROR(VLOOKUP(DraftSheet!$W57,Aggregate!$AD:$AO,10,FALSE()),""),IFERROR(VLOOKUP(DraftSheet!$W57,Aggregate!$AD:$AO,9,FALSE()),"")) -> 5.0956842 | AA57: =SUMIFS($AD58:AD$84,$AC58:AC$84,"<>x",$AC58:AC$84,"<>o",$AD58:AD$84,">0")/Aggregate!$AL$1 -> 0.026232989 | AB57: {=IFERROR(INDEX(ECR!$K:$K,MATCH(DraftSheet!$W57,ECR!$C:$C,0)),"ND")} -> 135 | AD57: =VLOOKUP(W57,Aggregate!AD:AL,9,FALSE()) -> 15.630985
B58: =IFERROR(VLOOKUP(DraftSheet!$C58,Aggregate!$AR:$BC,11,FALSE()),"") -> 3 | C58: =Aggregate!AR14 -> Dallas Goedert | D58: =VLOOKUP(DraftSheet!$C58,Aggregate!AR:BD,4,FALSE()) -> PHI/10 | E58: =IFERROR(VLOOKUP($C58,Aggregate!$AR:$BC,8,FALSE()),"") -> 113.08387 | F58: =IF(Scoring!$K$6="Auction",IFERROR(VLOOKUP($C58,Aggregate!$AR:$BC,10,FALSE()),""),IFERROR(VLOOKUP($C58,Aggregate!$AR:$BC,9,FALSE()),"")) -> 9.2656693 | G58: =SUMIFS($J59:J$84,$I59:I$84,"<>x",$I59:I$84,"<>o",$J59:J$84,">0")/Aggregate!$AZ$1 -> 0.23179521 | H58: {=IFERROR(INDEX(ECR!$K:$K,MATCH(DraftSheet!$C58,ECR!$C:$C,0)),"ND")} -> 118 | J58: =VLOOKUP(C58,Aggregate!AR:AZ,9,FALSE()) -> 31.545535 | L58: =IFERROR(VLOOKUP(DraftSheet!$M58,Aggregate!$P:$AA,11,FALSE()),"") -> 7 | M58: =Aggregate!P57 -> Braelon Allen | N58: =VLOOKUP(DraftSheet!$M58,Aggregate!P:AA,4,FALSE()) -> NYJ/13 | O58: =IFERROR(VLOOKUP(DraftSheet!$M58,Aggregate!$P:$AA,8,FALSE()),"") -> 66.672811 | P58: =IF(Scoring!$K$6="Auction",IFERROR(VLOOKUP(DraftSheet!$M58,Aggregate!$P:$AA,10,FALSE()),""),IFERROR(VLOOKUP(DraftSheet!$M58,Aggregate!$P:$AA,9,FALSE()),"")) -> 1 | Q58: =SUMIFS($T59:T$84,$S59:S$84,"<>x",$S59:S$84,"<>o",$T59:T$84,">0")/Aggregate!$X$1 -> 0 | R58: {=IFERROR(INDEX(ECR!$K:$K,MATCH(DraftSheet!$M58,ECR!$C:$C,0)),"ND")} -> 160 | T58: =VLOOKUP(M58,Aggregate!P:X,9,FALSE()) -> -11.718079 | V58: =IFERROR(VLOOKUP(DraftSheet!$W58,Aggregate!$AD:$AO,11,FALSE()),"") -> 5 | W58: =Aggregate!AD42 -> Josh Downs | X58: =VLOOKUP(DraftSheet!$W58,Aggregate!AD:AO,4,FALSE()) -> IND/13 | Y58: =IFERROR(VLOOKUP(DraftSheet!$W58,Aggregate!$AD:$AO,8,FALSE()),"") -> 97.042008 | Z58: =IF(Scoring!$K$6="Auction",IFERROR(VLOOKUP(DraftSheet!$W58,Aggregate!$AD:$AO,10,FALSE()),""),IFERROR(VLOOKUP(DraftSheet!$W58,Aggregate!$AD:$AO,9,FALSE()),"")) -> 5.0668868 | AA58: =SUMIFS($AD59:AD$84,$AC59:AC$84,"<>x",$AC59:AC$84,"<>o",$AD59:AD$84,">0")/Aggregate!$AL$1 -> 0.021170836 | AB58: {=IFERROR(INDEX(ECR!$K:$K,MATCH(DraftSheet!$W58,ECR!$C:$C,0)),"ND")} -> 96 | AD58: =VLOOKUP(W58,Aggregate!AD:AL,9,FALSE()) -> 15.521081
B59: =IFERROR(VLOOKUP(DraftSheet!$C59,Aggregate!$AR:$BC,11,FALSE()),"") -> 3 | C59: =Aggregate!AR16 -> Mark Andrews | D59: =VLOOKUP(DraftSheet!$C59,Aggregate!AR:BD,4,FALSE()) -> BAL/13 | E59: =IFERROR(VLOOKUP($C59,Aggregate!$AR:$BC,8,FALSE()),"") -> 106.19159 | F59: =IF(Scoring!$K$6="Auction",IFERROR(VLOOKUP($C59,Aggregate!$AR:$BC,10,FALSE()),""),IFERROR(VLOOKUP($C59,Aggregate!$AR:$BC,9,FALSE()),"")) -> 7.4597305 | G59: =SUMIFS($J60:J$84,$I60:I$84,"<>x",$I60:I$84,"<>o",$J60:J$84,">0")/Aggregate!$AZ$1 -> 0.19467802 | H59: {=IFERROR(INDEX(ECR!$K:$K,MATCH(DraftSheet!$C59,ECR!$C:$C,0)),"ND")} -> 125 | J59: =VLOOKUP(C59,Aggregate!AR:AZ,9,FALSE()) -> 24.653255 | L59: =IFERROR(VLOOKUP(DraftSheet!$M59,Aggregate!$P:$AA,11,FALSE()),"") -> 8 | M59: =Aggregate!P49 -> Tank Bigsby | N59: =VLOOKUP(DraftSheet!$M59,Aggregate!P:AA,4,FALSE()) -> PHI/10 | O59: =IFERROR(VLOOKUP(DraftSheet!$M59,Aggregate!$P:$AA,8,FALSE()),"") -> 65.734699 | P59: =IF(Scoring!$K$6="Auction",IFERROR(VLOOKUP(DraftSheet!$M59,Aggregate!$P:$AA,10,FALSE()),""),IFERROR(VLOOKUP(DraftSheet!$M59,Aggregate!$P:$AA,9,FALSE()),"")) -> 1 | Q59: =SUMIFS($T60:T$84,$S60:S$84,"<>x",$S60:S$84,"<>o",$T60:T$84,">0")/Aggregate!$X$1 -> 0 | R59: {=IFERROR(INDEX(ECR!$K:$K,MATCH(DraftSheet!$M59,ECR!$C:$C,0)),"ND")} -> 141 | T59: =VLOOKUP(M59,Aggregate!P:X,9,FALSE()) -> -12.65619 | V59: =IFERROR(VLOOKUP(DraftSheet!$W59,Aggregate!$AD:$AO,11,FALSE()),"") -> 5 | W59: =Aggregate!AD59 -> Rashid Shaheed | X59: =VLOOKUP(DraftSheet!$W59,Aggregate!AD:AO,4,FALSE()) -> SEA/11 | Y59: =IFERROR(VLOOKUP(DraftSheet!$W59,Aggregate!$AD:$AO,8,FALSE()),"") -> 94.954191 | Z59: =IF(Scoring!$K$6="Auction",IFERROR(VLOOKUP(DraftSheet!$W59,Aggregate!$AD:$AO,10,FALSE()),""),IFERROR(VLOOKUP(DraftSheet!$W59,Aggregate!$AD:$AO,9,FALSE()),"")) -> 4.5198299 | AA59: =SUMIFS($AD60:AD$84,$AC60:AC$84,"<>x",$AC60:AC$84,"<>o",$AD60:AD$84,">0")/Aggregate!$AL$1 -> 0.016789617 | AB59: {=IFERROR(INDEX(ECR!$K:$K,MATCH(DraftSheet!$W59,ECR!$C:$C,0)),"ND")} -> 153 | AD59: =VLOOKUP(W59,Aggregate!AD:AL,9,FALSE()) -> 13.433264
B60: =IFERROR(VLOOKUP(DraftSheet!$C60,Aggregate!$AR:$BC,11,FALSE()),"") -> 3 | C60: =Aggregate!AR15 -> Isaiah Likely | D60: =VLOOKUP(DraftSheet!$C60,Aggregate!AR:BD,4,FALSE()) -> NYG/8 | E60: =IFERROR(VLOOKUP($C60,Aggregate!$AR:$BC,8,FALSE()),"") -> 105.5898 | F60: =IF(Scoring!$K$6="Auction",IFERROR(VLOOKUP($C60,Aggregate!$AR:$BC,10,FALSE()),""),IFERROR(VLOOKUP($C60,Aggregate!$AR:$BC,9,FALSE()),"")) -> 7.3020494 | G60: =SUMIFS($J61:J$84,$I61:I$84,"<>x",$I61:I$84,"<>o",$J61:J$84,">0")/Aggregate!$AZ$1 -> 0.15846685 | H60: {=IFERROR(INDEX(ECR!$K:$K,MATCH(DraftSheet!$C60,ECR!$C:$C,0)),"ND")} -> 119 | J60: =VLOOKUP(C60,Aggregate!AR:AZ,9,FALSE()) -> 24.051473 | L60: =IFERROR(VLOOKUP(DraftSheet!$M60,Aggregate!$P:$AA,11,FALSE()),"") -> 8 | M60: =Aggregate!P61 -> Emmett Johnson | N60: =VLOOKUP(DraftSheet!$M60,Aggregate!P:AA,4,FALSE()) -> KC/5 | O60: =IFERROR(VLOOKUP(DraftSheet!$M60,Aggregate!$P:$AA,8,FALSE()),"") -> 65.375122 | P60: =IF(Scoring!$K$6="Auction",IFERROR(VLOOKUP(DraftSheet!$M60,Aggregate!$P:$AA,10,FALSE()),""),IFERROR(VLOOKUP(DraftSheet!$M60,Aggregate!$P:$AA,9,FALSE()),"")) -> 1 | Q60: =SUMIFS($T61:T$84,$S61:S$84,"<>x",$S61:S$84,"<>o",$T61:T$84,">0")/Aggregate!$X$1 -> 0 | R60: {=IFERROR(INDEX(ECR!$K:$K,MATCH(DraftSheet!$M60,ECR!$C:$C,0)),"ND")} -> 176 | T60: =VLOOKUP(M60,Aggregate!P:X,9,FALSE()) -> -13.015768 | V60: =IFERROR(VLOOKUP(DraftSheet!$W60,Aggregate!$AD:$AO,11,FALSE()),"") -> 5 | W60: =Aggregate!AD52 -> Jalen Coker | X60: =VLOOKUP(DraftSheet!$W60,Aggregate!AD:AO,4,FALSE()) -> CAR/5 | Y60: =IFERROR(VLOOKUP(DraftSheet!$W60,Aggregate!$AD:$AO,8,FALSE()),"") -> 94.440485 | Z60: =IF(Scoring!$K$6="Auction",IFERROR(VLOOKUP(DraftSheet!$W60,Aggregate!$AD:$AO,10,FALSE()),""),IFERROR(VLOOKUP(DraftSheet!$W60,Aggregate!$AD:$AO,9,FALSE()),"")) -> 4.385227 | AA60: =SUMIFS($AD61:AD$84,$AC61:AC$84,"<>x",$AC61:AC$84,"<>o",$AD61:AD$84,">0")/Aggregate!$AL$1 -> 0.012575942 | AB60: {=IFERROR(INDEX(ECR!$K:$K,MATCH(DraftSheet!$W60,ECR!$C:$C,0)),"ND")} -> 128 | AD60: =VLOOKUP(W60,Aggregate!AD:AL,9,FALSE()) -> 12.919558
B61: =IFERROR(VLOOKUP(DraftSheet!$C61,Aggregate!$AR:$BC,11,FALSE()),"") -> 3 | C61: =Aggregate!AR13 -> Dalton Kincaid | D61: =VLOOKUP(DraftSheet!$C61,Aggregate!AR:BD,4,FALSE()) -> BUF/7 | E61: =IFERROR(VLOOKUP($C61,Aggregate!$AR:$BC,8,FALSE()),"") -> 105.32556 | F61: =IF(Scoring!$K$6="Auction",IFERROR(VLOOKUP($C61,Aggregate!$AR:$BC,10,FALSE()),""),IFERROR(VLOOKUP($C61,Aggregate!$AR:$BC,9,FALSE()),"")) -> 7.2328108 | G61: =SUMIFS($J62:J$84,$I62:I$84,"<>x",$I62:I$84,"<>o",$J62:J$84,">0")/Aggregate!$AZ$1 -> 0.12265353 | H61: {=IFERROR(INDEX(ECR!$K:$K,MATCH(DraftSheet!$C61,ECR!$C:$C,0)),"ND")} -> 115 | J61: =VLOOKUP(C61,Aggregate!AR:AZ,9,FALSE()) -> 23.787227 | L61: =IFERROR(VLOOKUP(DraftSheet!$M61,Aggregate!$P:$AA,11,FALSE()),"") -> 8 | M61: =Aggregate!P48 -> Keaton Mitchell | N61: =VLOOKUP(DraftSheet!$M61,Aggregate!P:AA,4,FALSE()) -> LAC/7 | O61: =IFERROR(VLOOKUP(DraftSheet!$M61,Aggregate!$P:$AA,8,FALSE()),"") -> 63.715436 | P61: =IF(Scoring!$K$6="Auction",IFERROR(VLOOKUP(DraftSheet!$M61,Aggregate!$P:$AA,10,FALSE()),""),IFERROR(VLOOKUP(DraftSheet!$M61,Aggregate!$P:$AA,9,FALSE()),"")) -> 1 | Q61: =SUMIFS($T62:T$84,$S62:S$84,"<>x",$S62:S$84,"<>o",$T62:T$84,">0")/Aggregate!$X$1 -> 0 | R61: {=IFERROR(INDEX(ECR!$K:$K,MATCH(DraftSheet!$M61,ECR!$C:$C,0)),"ND")} -> 139 | T61: =VLOOKUP(M61,Aggregate!P:X,9,FALSE()) -> -14.675453 | V61: =IFERROR(VLOOKUP(DraftSheet!$W61,Aggregate!$AD:$AO,11,FALSE()),"") -> 5 | W61: =Aggregate!AD54 -> Khalil Shakir | X61: =VLOOKUP(DraftSheet!$W61,Aggregate!AD:AO,4,FALSE()) -> BUF/7 | Y61: =IFERROR(VLOOKUP(DraftSheet!$W61,Aggregate!$AD:$AO,8,FALSE()),"") -> 93.973809 | Z61: =IF(Scoring!$K$6="Auction",IFERROR(VLOOKUP(DraftSheet!$W61,Aggregate!$AD:$AO,10,FALSE()),""),IFERROR(VLOOKUP(DraftSheet!$W61,Aggregate!$AD:$AO,9,FALSE()),"")) -> 4.2629468 | AA61: =SUMIFS($AD62:AD$84,$AC62:AC$84,"<>x",$AC62:AC$84,"<>o",$AD62:AD$84,">0")/Aggregate!$AL$1 -> 0.0085144724 | AB61: {=IFERROR(INDEX(ECR!$K:$K,MATCH(DraftSheet!$W61,ECR!$C:$C,0)),"ND")} -> 133 | AD61: =VLOOKUP(W61,Aggregate!AD:AL,9,FALSE()) -> 12.452882
B62: =IFERROR(VLOOKUP(DraftSheet!$C62,Aggregate!$AR:$BC,11,FALSE()),"") -> 4 | C62: =Aggregate!AR17 -> Jake Ferguson | D62: =VLOOKUP(DraftSheet!$C62,Aggregate!AR:BD,4,FALSE()) -> DAL/14 | E62: =IFERROR(VLOOKUP($C62,Aggregate!$AR:$BC,8,FALSE()),"") -> 101.4703 | F62: =IF(Scoring!$K$6="Auction",IFERROR(VLOOKUP($C62,Aggregate!$AR:$BC,10,FALSE()),""),IFERROR(VLOOKUP($C62,Aggregate!$AR:$BC,9,FALSE()),"")) -> 6.2226421 | G62: =SUMIFS($J63:J$84,$I63:I$84,"<>x",$I63:I$84,"<>o",$J63:J$84,">0")/Aggregate!$AZ$1 -> 0.092644563 | H62: {=IFERROR(INDEX(ECR!$K:$K,MATCH(DraftSheet!$C62,ECR!$C:$C,0)),"ND")} -> 132 | J62: =VLOOKUP(C62,Aggregate!AR:AZ,9,FALSE()) -> 19.931966 | L62: =IFERROR(VLOOKUP(DraftSheet!$M62,Aggregate!$P:$AA,11,FALSE()),"") -> 8 | M62: =Aggregate!P56 -> Brian Robinson Jr. | N62: =VLOOKUP(DraftSheet!$M62,Aggregate!P:AA,4,FALSE()) -> ATL/11 | O62: =IFERROR(VLOOKUP(DraftSheet!$M62,Aggregate!$P:$AA,8,FALSE()),"") -> 63.708006 | P62: =IF(Scoring!$K$6="Auction",IFERROR(VLOOKUP(DraftSheet!$M62,Aggregate!$P:$AA,10,FALSE()),""),IFERROR(VLOOKUP(DraftSheet!$M62,Aggregate!$P:$AA,9,FALSE()),"")) -> 1 | Q62: =SUMIFS($T63:T$84,$S63:S$84,"<>x",$S63:S$84,"<>o",$T63:T$84,">0")/Aggregate!$X$1 -> 0 | R62: {=IFERROR(INDEX(ECR!$K:$K,MATCH(DraftSheet!$M62,ECR!$C:$C,0)),"ND")} -> 158 | T62: =VLOOKUP(M62,Aggregate!P:X,9,FALSE()) -> -14.682883 | V62: =IFERROR(VLOOKUP(DraftSheet!$W62,Aggregate!$AD:$AO,11,FALSE()),"") -> 5 | W62: =Aggregate!AD55 -> Jordyn Tyson | X62: =VLOOKUP(DraftSheet!$W62,Aggregate!AD:AO,4,FALSE()) -> NO/8 | Y62: =IFERROR(VLOOKUP(DraftSheet!$W62,Aggregate!$AD:$AO,8,FALSE()),"") -> 89.531555 | Z62: =IF(Scoring!$K$6="Auction",IFERROR(VLOOKUP(DraftSheet!$W62,Aggregate!$AD:$AO,10,FALSE()),""),IFERROR(VLOOKUP(DraftSheet!$W62,Aggregate!$AD:$AO,9,FALSE()),"")) -> 3.0989723 | AA62: =SUMIFS($AD63:AD$84,$AC63:AC$84,"<>x",$AC63:AC$84,"<>o",$AD63:AD$84,">0")/Aggregate!$AL$1 -> 0.0059018302 | AB62: {=IFERROR(INDEX(ECR!$K:$K,MATCH(DraftSheet!$W62,ECR!$C:$C,0)),"ND")} -> 134 | AD62: =VLOOKUP(W62,Aggregate!AD:AL,9,FALSE()) -> 8.0106282
B63: =IFERROR(VLOOKUP(DraftSheet!$C63,Aggregate!$AR:$BC,11,FALSE()),"") -> 4 | C63: =Aggregate!AR19 -> Hunter Henry | D63: =VLOOKUP(DraftSheet!$C63,Aggregate!AR:BD,4,FALSE()) -> NE/11 | E63: =IFERROR(VLOOKUP($C63,Aggregate!$AR:$BC,8,FALSE()),"") -> 97.289851 | F63: =IF(Scoring!$K$6="Auction",IFERROR(VLOOKUP($C63,Aggregate!$AR:$BC,10,FALSE()),""),IFERROR(VLOOKUP($C63,Aggregate!$AR:$BC,9,FALSE()),"")) -> 5.1272672 | G63: =SUMIFS($J64:J$84,$I64:I$84,"<>x",$I64:I$84,"<>o",$J64:J$84,">0")/Aggregate!$AZ$1 -> 0.068929553 | H63: {=IFERROR(INDEX(ECR!$K:$K,MATCH(DraftSheet!$C63,ECR!$C:$C,0)),"ND")} -> 144 | J63: =VLOOKUP(C63,Aggregate!AR:AZ,9,FALSE()) -> 15.75152 | L63: =IFERROR(VLOOKUP(DraftSheet!$M63,Aggregate!$P:$AA,11,FALSE()),"") -> 8 | M63: =Aggregate!P73 -> Justice Hill | N63: =VLOOKUP(DraftSheet!$M63,Aggregate!P:AA,4,FALSE()) -> BAL/13 | O63: =IFERROR(VLOOKUP(DraftSheet!$M63,Aggregate!$P:$AA,8,FALSE()),"") -> 63.338334 | P63: =IF(Scoring!$K$6="Auction",IFERROR(VLOOKUP(DraftSheet!$M63,Aggregate!$P:$AA,10,FALSE()),""),IFERROR(VLOOKUP(DraftSheet!$M63,Aggregate!$P:$AA,9,FALSE()),"")) -> 1 | Q63: =SUMIFS(T63:$T$85,S63:$S$85,"<>x",S63:$S$85,"<>o",T63:$T$85,">0")/Aggregate!$X$1 -> 0 | R63: {=IFERROR(INDEX(ECR!$K:$K,MATCH(DraftSheet!$M63,ECR!$C:$C,0)),"ND")} -> 244 | T63: =VLOOKUP(M63,Aggregate!P:X,9,FALSE()) -> -15.052555 | V63: =IFERROR(VLOOKUP(DraftSheet!$W63,Aggregate!$AD:$AO,11,FALSE()),"") -> 5 | W63: =Aggregate!AD74 -> Calvin Ridley | X63: =VLOOKUP(DraftSheet!$W63,Aggregate!AD:AO,4,FALSE()) -> TEN/9 | Y63: =IFERROR(VLOOKUP(DraftSheet!$W63,Aggregate!$AD:$AO,8,FALSE()),"") -> 87.684529 | Z63: =IF(Scoring!$K$6="Auction",IFERROR(VLOOKUP(DraftSheet!$W63,Aggregate!$AD:$AO,10,FALSE()),""),IFERROR(VLOOKUP(DraftSheet!$W63,Aggregate!$AD:$AO,9,FALSE()),"")) -> 2.6150082 | AA63: =SUMIFS($AD64:AD$84,$AC64:AC$84,"<>x",$AC64:AC$84,"<>o",$AD64:AD$84,">0")/Aggregate!$AL$1 -> 0.00389159 | AB63: {=IFERROR(INDEX(ECR!$K:$K,MATCH(DraftSheet!$W63,ECR!$C:$C,0)),"ND")} -> 186 | AD63: =VLOOKUP(W63,Aggregate!AD:AL,9,FALSE()) -> 6.1636024
B64: =IFERROR(VLOOKUP(DraftSheet!$C64,Aggregate!$AR:$BC,11,FALSE()),"") -> 4 | C64: =Aggregate!AR18 -> Juwan Johnson | D64: =VLOOKUP(DraftSheet!$C64,Aggregate!AR:BD,4,FALSE()) -> NO/8 | E64: =IFERROR(VLOOKUP($C64,Aggregate!$AR:$BC,8,FALSE()),"") -> 97.071508 | F64: =IF(Scoring!$K$6="Auction",IFERROR(VLOOKUP($C64,Aggregate!$AR:$BC,10,FALSE()),""),IFERROR(VLOOKUP($C64,Aggregate!$AR:$BC,9,FALSE()),"")) -> 5.0700563 | G64: =SUMIFS($J65:J$84,$I65:I$84,"<>x",$I65:I$84,"<>o",$J65:J$84,">0")/Aggregate!$AZ$1 -> 0.045543274 | H64: {=IFERROR(INDEX(ECR!$K:$K,MATCH(DraftSheet!$C64,ECR!$C:$C,0)),"ND")} -> 140 | J64: =VLOOKUP(C64,Aggregate!AR:AZ,9,FALSE()) -> 15.533177 | L64: =IFERROR(VLOOKUP(DraftSheet!$M64,Aggregate!$P:$AA,11,FALSE()),"") -> 8 | M64: =Aggregate!P66 -> Kaytron Allen | N64: =VLOOKUP(DraftSheet!$M64,Aggregate!P:AA,4,FALSE()) -> WAS/7 | O64: =IFERROR(VLOOKUP(DraftSheet!$M64,Aggregate!$P:$AA,8,FALSE()),"") -> 59.346793 | P64: =IF(Scoring!$K$6="Auction",IFERROR(VLOOKUP(DraftSheet!$M64,Aggregate!$P:$AA,10,FALSE()),""),IFERROR(VLOOKUP(DraftSheet!$M64,Aggregate!$P:$AA,9,FALSE()),"")) -> 1 | Q64: =SUMIFS(T65:$T$84,S65:$S$84,"<>x",S65:$S$84,"<>o",T65:$T$84,">0")/Aggregate!$X$1 -> 0 | R64: {=IFERROR(INDEX(ECR!$K:$K,MATCH(DraftSheet!$M64,ECR!$C:$C,0)),"ND")} -> 203 | T64: =VLOOKUP(M64,Aggregate!P:X,9,FALSE()) -> -19.044096 | V64: =IFERROR(VLOOKUP(DraftSheet!$W64,Aggregate!$AD:$AO,11,FALSE()),"") -> 5 | W64: =Aggregate!AD63 -> Jerry Jeudy | X64: =VLOOKUP(DraftSheet!$W64,Aggregate!AD:AO,4,FALSE()) -> CLE/11 | Y64: =IFERROR(VLOOKUP(DraftSheet!$W64,Aggregate!$AD:$AO,8,FALSE()),"") -> 86.255559 | Z64: =IF(Scoring!$K$6="Auction",IFERROR(VLOOKUP(DraftSheet!$W64,Aggregate!$AD:$AO,10,FALSE()),""),IFERROR(VLOOKUP(DraftSheet!$W64,Aggregate!$AD:$AO,9,FALSE()),"")) -> 2.2405845 | AA64: =SUMIFS($AD65:AD$84,$AC65:AC$84,"<>x",$AC65:AC$84,"<>o",$AD65:AD$84,">0")/Aggregate!$AL$1 -> 0.0023474041 | AB64: {=IFERROR(INDEX(ECR!$K:$K,MATCH(DraftSheet!$W64,ECR!$C:$C,0)),"ND")} -> 164 | AD64: =VLOOKUP(W64,Aggregate!AD:AL,9,FALSE()) -> 4.7346318
B65: =IFERROR(VLOOKUP(DraftSheet!$C65,Aggregate!$AR:$BC,11,FALSE()),"") -> 4 | C65: =Aggregate!AR20 -> Brenton Strange | D65: =VLOOKUP(DraftSheet!$C65,Aggregate!AR:BD,4,FALSE()) -> JAC/7 | E65: =IFERROR(VLOOKUP($C65,Aggregate!$AR:$BC,8,FALSE()),"") -> 96.362051 | F65: =IF(Scoring!$K$6="Auction",IFERROR(VLOOKUP($C65,Aggregate!$AR:$BC,10,FALSE()),""),IFERROR(VLOOKUP($C65,Aggregate!$AR:$BC,9,FALSE()),"")) -> 4.8841619 | G65: =SUMIFS($J66:J$84,$I66:I$84,"<>x",$I66:I$84,"<>o",$J66:J$84,">0")/Aggregate!$AZ$1 -> 0.023225131 | H65: {=IFERROR(INDEX(ECR!$K:$K,MATCH(DraftSheet!$C65,ECR!$C:$C,0)),"ND")} -> 150 | J65: =VLOOKUP(C65,Aggregate!AR:AZ,9,FALSE()) -> 14.82372 | L65: =IFERROR(VLOOKUP(DraftSheet!$M65,Aggregate!$P:$AA,11,FALSE()),"") -> 8 | M65: =Aggregate!P64 -> Nicholas Singleton | N65: =VLOOKUP(DraftSheet!$M65,Aggregate!P:AA,4,FALSE()) -> TEN/9 | O65: =IFERROR(VLOOKUP(DraftSheet!$M65,Aggregate!$P:$AA,8,FALSE()),"") -> 58.888125 | P65: =IF(Scoring!$K$6="Auction",IFERROR(VLOOKUP(DraftSheet!$M65,Aggregate!$P:$AA,10,FALSE()),""),IFERROR(VLOOKUP(DraftSheet!$M65,Aggregate!$P:$AA,9,FALSE()),"")) -> 1 | Q65: =SUMIFS($T65:T$85,$S65:S$85,"<>x",$S65:S$85,"<>o",$T65:T$85,">0")/Aggregate!$X$1 -> 0 | R65: {=IFERROR(INDEX(ECR!$K:$K,MATCH(DraftSheet!$M65,ECR!$C:$C,0)),"ND")} -> 190 | T65: =VLOOKUP(M65,Aggregate!P:X,9,FALSE()) -> -19.502764 | V65: =IFERROR(VLOOKUP(DraftSheet!$W65,Aggregate!$AD:$AO,11,FALSE()),"") -> 5 | W65: =Aggregate!AD62 -> Tre Tucker | X65: =VLOOKUP(DraftSheet!$W65,Aggregate!AD:AO,4,FALSE()) -> LV/13 | Y65: =IFERROR(VLOOKUP(DraftSheet!$W65,Aggregate!$AD:$AO,8,FALSE()),"") -> 85.410838 | Z65: =IF(Scoring!$K$6="Auction",IFERROR(VLOOKUP(DraftSheet!$W65,Aggregate!$AD:$AO,10,FALSE()),""),IFERROR(VLOOKUP(DraftSheet!$W65,Aggregate!$AD:$AO,9,FALSE()),"")) -> 2.0192479 | AA65: =SUMIFS(AD65:$AD$85,AC65:$AC$85,"<>x",AC65:$AC$85,"<>o",AD65:$AD$85,">0")/Aggregate!$AL$1 -> 0.0023474041 | AB65: {=IFERROR(INDEX(ECR!$K:$K,MATCH(DraftSheet!$W65,ECR!$C:$C,0)),"ND")} -> 163 | AD65: =VLOOKUP(W65,Aggregate!AD:AL,9,FALSE()) -> 3.8899112
B66: =IFERROR(VLOOKUP(DraftSheet!$C66,Aggregate!$AR:$BC,11,FALSE()),"") -> 4 | C66: =Aggregate!AR22 -> Dalton Schultz | D66: =VLOOKUP(DraftSheet!$C66,Aggregate!AR:BD,4,FALSE()) -> HOU/8 | E66: =IFERROR(VLOOKUP($C66,Aggregate!$AR:$BC,8,FALSE()),"") -> 89.525952 | F66: =IF(Scoring!$K$6="Auction",IFERROR(VLOOKUP($C66,Aggregate!$AR:$BC,10,FALSE()),""),IFERROR(VLOOKUP($C66,Aggregate!$AR:$BC,9,FALSE()),"")) -> 3.0929437 | G66: =SUMIFS(J66:$J$85,I66:$I$85,"<>x",I66:$I$85,"<>o",J66:$J$85,">0")/Aggregate!$AZ$1 -> 0.023225131 | H66: {=IFERROR(INDEX(ECR!$K:$K,MATCH(DraftSheet!$C66,ECR!$C:$C,0)),"ND")} -> 156 | J66: =VLOOKUP(C66,Aggregate!AR:AZ,9,FALSE()) -> 7.9876205 | L66: =IFERROR(VLOOKUP(DraftSheet!$M66,Aggregate!$P:$AA,11,FALSE()),"") -> 8 | M66: =Aggregate!P79 -> Samaje Perine | N66: =VLOOKUP(DraftSheet!$M66,Aggregate!P:AA,4,FALSE()) -> CIN/6 | O66: =IFERROR(VLOOKUP(DraftSheet!$M66,Aggregate!$P:$AA,8,FALSE()),"") -> 56.955459 | P66: =IF(Scoring!$K$6="Auction",IFERROR(VLOOKUP(DraftSheet!$M66,Aggregate!$P:$AA,10,FALSE()),""),IFERROR(VLOOKUP(DraftSheet!$M66,Aggregate!$P:$AA,9,FALSE()),"")) -> 1 | Q66: =SUMIFS($T66:T$85,$S66:S$85,"<>x",$S66:S$85,"<>o",$T66:T$85,">0")/Aggregate!$X$1 -> 0 | R66: {=IFERROR(INDEX(ECR!$K:$K,MATCH(DraftSheet!$M66,ECR!$C:$C,0)),"ND")} -> 260 | T66: =VLOOKUP(M66,Aggregate!P:X,9,FALSE()) -> -21.43543 | V66: =IFERROR(VLOOKUP(DraftSheet!$W66,Aggregate!$AD:$AO,11,FALSE()),"") -> 6 | W66: =Aggregate!AD76 -> Tank Dell | X66: =VLOOKUP(DraftSheet!$W66,Aggregate!AD:AO,4,FALSE()) -> HOU/8 | Y66: =IFERROR(VLOOKUP(DraftSheet!$W66,Aggregate!$AD:$AO,8,FALSE()),"") -> 84.828397 | Z66: =IF(Scoring!$K$6="Auction",IFERROR(VLOOKUP(DraftSheet!$W66,Aggregate!$AD:$AO,10,FALSE()),""),IFERROR(VLOOKUP(DraftSheet!$W66,Aggregate!$AD:$AO,9,FALSE()),"")) -> 1.8666346 | AA66: =SUMIFS($AD67:AD$84,$AC67:AC$84,"<>x",$AC67:AC$84,"<>o",$AD67:AD$84,">0")/Aggregate!$AL$1 -> 0 | AB66: {=IFERROR(INDEX(ECR!$K:$K,MATCH(DraftSheet!$W66,ECR!$C:$C,0)),"ND")} -> 189 | AD66: =VLOOKUP(W66,Aggregate!AD:AL,9,FALSE()) -> 3.30747
B67: =IFERROR(VLOOKUP(DraftSheet!$C67,Aggregate!$AR:$BC,11,FALSE()),"") -> 4 | C67: =Aggregate!AR24 -> T.J. Hockenson | D67: =VLOOKUP(DraftSheet!$C67,Aggregate!AR:BD,4,FALSE()) -> MIN/6 | E67: =IFERROR(VLOOKUP($C67,Aggregate!$AR:$BC,8,FALSE()),"") -> 86.543924 | F67: =IF(Scoring!$K$6="Auction",IFERROR(VLOOKUP($C67,Aggregate!$AR:$BC,10,FALSE()),""),IFERROR(VLOOKUP($C67,Aggregate!$AR:$BC,9,FALSE()),"")) -> 2.3115826 | G67: =SUMIFS($J68:J$84,$I68:I$84,"<>x",$I68:I$84,"<>o",$J68:J$84,">0")/Aggregate!$AZ$1 -> 0.0036629437 | H67: {=IFERROR(INDEX(ECR!$K:$K,MATCH(DraftSheet!$C67,ECR!$C:$C,0)),"ND")} -> 173 | J67: =VLOOKUP(C67,Aggregate!AR:AZ,9,FALSE()) -> 5.0055927 | L67: =IFERROR(VLOOKUP(DraftSheet!$M67,Aggregate!$P:$AA,11,FALSE()),"") -> 8 | M67: =Aggregate!P74 -> Demond Claiborne | N67: =VLOOKUP(DraftSheet!$M67,Aggregate!P:AA,4,FALSE()) -> MIN/6 | O67: =IFERROR(VLOOKUP(DraftSheet!$M67,Aggregate!$P:$AA,8,FALSE()),"") -> 53.931819 | P67: =IF(Scoring!$K$6="Auction",IFERROR(VLOOKUP(DraftSheet!$M67,Aggregate!$P:$AA,10,FALSE()),""),IFERROR(VLOOKUP(DraftSheet!$M67,Aggregate!$P:$AA,9,FALSE()),"")) -> 1 | Q67: =SUMIFS($T68:T$84,$S68:S$84,"<>x",$S68:S$84,"<>o",$T68:T$84,">0")/Aggregate!$X$1 -> 0 | R67: {=IFERROR(INDEX(ECR!$K:$K,MATCH(DraftSheet!$M67,ECR!$C:$C,0)),"ND")} -> 245 | T67: =VLOOKUP(M67,Aggregate!P:X,9,FALSE()) -> -24.45907 | V67: =IFERROR(VLOOKUP(DraftSheet!$W67,Aggregate!$AD:$AO,11,FALSE()),"") -> 6 | W67: =Aggregate!AD65 -> Jalen McMillan | X67: =VLOOKUP(DraftSheet!$W67,Aggregate!AD:AO,4,FALSE()) -> TB/10 | Y67: =IFERROR(VLOOKUP(DraftSheet!$W67,Aggregate!$AD:$AO,8,FALSE()),"") -> 81.520927 | Z67: =IF(Scoring!$K$6="Auction",IFERROR(VLOOKUP(DraftSheet!$W67,Aggregate!$AD:$AO,10,FALSE()),""),IFERROR(VLOOKUP(DraftSheet!$W67,Aggregate!$AD:$AO,9,FALSE()),"")) -> 1 | AA67: =SUMIFS($AD68:AD$84,$AC68:AC$84,"<>x",$AC68:AC$84,"<>o",$AD68:AD$84,">0")/Aggregate!$AL$1 -> 0 | AB67: {=IFERROR(INDEX(ECR!$K:$K,MATCH(DraftSheet!$W67,ECR!$C:$C,0)),"ND")} -> 166 | AD67: =VLOOKUP(W67,Aggregate!AD:AL,9,FALSE()) -> 0
B68: =IFERROR(VLOOKUP(DraftSheet!$C68,Aggregate!$AR:$BC,11,FALSE()),"") -> 5 | C68: =Aggregate!AR30 -> Pat Freiermuth | D68: =VLOOKUP(DraftSheet!$C68,Aggregate!AR:BD,4,FALSE()) -> PIT/9 | E68: =IFERROR(VLOOKUP($C68,Aggregate!$AR:$BC,8,FALSE()),"") -> 83.121445 | F68: =IF(Scoring!$K$6="Auction",IFERROR(VLOOKUP($C68,Aggregate!$AR:$BC,10,FALSE()),""),IFERROR(VLOOKUP($C68,Aggregate!$AR:$BC,9,FALSE()),"")) -> 1.4148129 | G68: =SUMIFS($J69:J$84,$I69:I$84,"<>x",$I69:I$84,"<>o",$J69:J$84,">0")/Aggregate!$AZ$1 -> 0.0012794554 | H68: {=IFERROR(INDEX(ECR!$K:$K,MATCH(DraftSheet!$C68,ECR!$C:$C,0)),"ND")} -> 204 | J68: =VLOOKUP(C68,Aggregate!AR:AZ,9,FALSE()) -> 1.5831139 | L68: =IFERROR(VLOOKUP(DraftSheet!$M68,Aggregate!$P:$AA,11,FALSE()),"") -> 8 | M68: =Aggregate!P80 -> Ty Johnson | N68: =VLOOKUP(DraftSheet!$M68,Aggregate!P:AA,4,FALSE()) -> BUF/7 | O68: =IFERROR(VLOOKUP(DraftSheet!$M68,Aggregate!$P:$AA,8,FALSE()),"") -> 52.365213 | P68: =IF(Scoring!$K$6="Auction",IFERROR(VLOOKUP(DraftSheet!$M68,Aggregate!$P:$AA,10,FALSE()),""),IFERROR(VLOOKUP(DraftSheet!$M68,Aggregate!$P:$AA,9,FALSE()),"")) -> 1 | Q68: =SUMIFS($T69:T$84,$S69:S$84,"<>x",$S69:S$84,"<>o",$T69:T$84,">0")/Aggregate!$X$1 -> 0 | R68: {=IFERROR(INDEX(ECR!$K:$K,MATCH(DraftSheet!$M68,ECR!$C:$C,0)),"ND")} -> 264 | T68: =VLOOKUP(M68,Aggregate!P:X,9,FALSE()) -> -26.025676 | V68: =IFERROR(VLOOKUP(DraftSheet!$W68,Aggregate!$AD:$AO,11,FALSE()),"") -> 6 | W68: =Aggregate!AD64 -> Jauan Jennings | X68: =VLOOKUP(DraftSheet!$W68,Aggregate!AD:AO,4,FALSE()) -> MIN/6 | Y68: =IFERROR(VLOOKUP(DraftSheet!$W68,Aggregate!$AD:$AO,8,FALSE()),"") -> 81.323838 | Z68: =IF(Scoring!$K$6="Auction",IFERROR(VLOOKUP(DraftSheet!$W68,Aggregate!$AD:$AO,10,FALSE()),""),IFERROR(VLOOKUP(DraftSheet!$W68,Aggregate!$AD:$AO,9,FALSE()),"")) -> 1 | AA68: =SUMIFS($AD69:AD$84,$AC69:AC$84,"<>x",$AC69:AC$84,"<>o",$AD69:AD$84,">0")/Aggregate!$AL$1 -> 0 | AB68: {=IFERROR(INDEX(ECR!$K:$K,MATCH(DraftSheet!$W68,ECR!$C:$C,0)),"ND")} -> 165 | AD68: =VLOOKUP(W68,Aggregate!AD:AL,9,FALSE()) -> -0.19708941
B69: =IFERROR(VLOOKUP(DraftSheet!$C69,Aggregate!$AR:$BC,11,FALSE()),"") -> 5 | C69: =Aggregate!AR27 -> Kenyon Sadiq | D69: =VLOOKUP(DraftSheet!$C69,Aggregate!AR:BD,4,FALSE()) -> NYJ/13 | E69: =IFERROR(VLOOKUP($C69,Aggregate!$AR:$BC,8,FALSE()),"") -> 82.049165 | F69: =IF(Scoring!$K$6="Auction",IFERROR(VLOOKUP($C69,Aggregate!$AR:$BC,10,FALSE()),""),IFERROR(VLOOKUP($C69,Aggregate!$AR:$BC,9,FALSE()),"")) -> 1.1338503 | G69: =SUMIFS(J69:$J$84,I69:$I$84,"<>x",I69:$I$84,"<>o",J69:$J$84,">0")/Aggregate!$AZ$1 -> 0.0012794554 | H69: {=IFERROR(INDEX(ECR!$K:$K,MATCH(DraftSheet!$C69,ECR!$C:$C,0)),"ND")} -> 187 | J69: =VLOOKUP(C69,Aggregate!AR:AZ,9,FALSE()) -> 0.51083325 | L69: =IFERROR(VLOOKUP(DraftSheet!$M69,Aggregate!$P:$AA,11,FALSE()),"") -> 8 | M69: =Aggregate!P78 -> Jordan James | N69: =VLOOKUP(DraftSheet!$M69,Aggregate!P:AA,4,FALSE()) -> SF/8 | O69: =IFERROR(VLOOKUP(DraftSheet!$M69,Aggregate!$P:$AA,8,FALSE()),"") -> 47.083922 | P69: =IF(Scoring!$K$6="Auction",IFERROR(VLOOKUP(DraftSheet!$M69,Aggregate!$P:$AA,10,FALSE()),""),IFERROR(VLOOKUP(DraftSheet!$M69,Aggregate!$P:$AA,9,FALSE()),"")) -> 1 | Q69: =SUMIFS(T$66:$T88,S$66:$S88,"<>x",S$66:$S88,"<>o",T$66:$T88,">0")/Aggregate!$X$1 -> 0 | R69: {=IFERROR(INDEX(ECR!$K:$K,MATCH(DraftSheet!$M69,ECR!$C:$C,0)),"ND")} -> 259 | T69: =VLOOKUP(M69,Aggregate!P:X,9,FALSE()) -> -31.306967 | V69: =IFERROR(VLOOKUP(DraftSheet!$W69,Aggregate!$AD:$AO,11,FALSE()),"") -> 6 | W69: =Aggregate!AD72 -> Omar Cooper Jr. | X69: =VLOOKUP(DraftSheet!$W69,Aggregate!AD:AO,4,FALSE()) -> NYJ/13 | Y69: =IFERROR(VLOOKUP(DraftSheet!$W69,Aggregate!$AD:$AO,8,FALSE()),"") -> 80.892108 | Z69: =IF(Scoring!$K$6="Auction",IFERROR(VLOOKUP(DraftSheet!$W69,Aggregate!$AD:$AO,10,FALSE()),""),IFERROR(VLOOKUP(DraftSheet!$W69,Aggregate!$AD:$AO,9,FALSE()),"")) -> 1 | AA69: =SUMIFS($AD70:AD$84,$AC70:AC$84,"<>x",$AC70:AC$84,"<>o",$AD70:AD$84,">0")/Aggregate!$AL$1 -> 0 | AB69: {=IFERROR(INDEX(ECR!$K:$K,MATCH(DraftSheet!$W69,ECR!$C:$C,0)),"ND")} -> 181 | AD69: =VLOOKUP(W69,Aggregate!AD:AL,9,FALSE()) -> -0.62881941
B70: =IFERROR(VLOOKUP(DraftSheet!$C70,Aggregate!$AR:$BC,11,FALSE()),"") -> 5 | C70: =Aggregate!AR29 -> Cade Otton | D70: =VLOOKUP(DraftSheet!$C70,Aggregate!AR:BD,4,FALSE()) -> TB/10 | E70: =IFERROR(VLOOKUP($C70,Aggregate!$AR:$BC,8,FALSE()),"") -> 81.877313 | F70: =IF(Scoring!$K$6="Auction",IFERROR(VLOOKUP($C70,Aggregate!$AR:$BC,10,FALSE()),""),IFERROR(VLOOKUP($C70,Aggregate!$AR:$BC,9,FALSE()),"")) -> 1.0888211 | G70: =SUMIFS($J71:J$84,$I71:I$84,"<>x",$I71:I$84,"<>o",$J71:J$84,">0")/Aggregate!$AZ$1 -> 0 | H70: {=IFERROR(INDEX(ECR!$K:$K,MATCH(DraftSheet!$C70,ECR!$C:$C,0)),"ND")} -> 202 | J70: =VLOOKUP(C70,Aggregate!AR:AZ,9,FALSE()) -> 0.3389816 | L70: =IFERROR(VLOOKUP(DraftSheet!$M70,Aggregate!$P:$AA,11,FALSE()),"") -> 8 | M70: =Aggregate!P63 -> Kimani Vidal | N70: =VLOOKUP(DraftSheet!$M70,Aggregate!P:AA,4,FALSE()) -> LAC/7 | O70: =IFERROR(VLOOKUP(DraftSheet!$M70,Aggregate!$P:$AA,8,FALSE()),"") -> 44.772032 | P70: =IF(Scoring!$K$6="Auction",IFERROR(VLOOKUP(DraftSheet!$M70,Aggregate!$P:$AA,10,FALSE()),""),IFERROR(VLOOKUP(DraftSheet!$M70,Aggregate!$P:$AA,9,FALSE()),"")) -> 1 | Q70: =SUMIFS(T71:$T$84,S71:$S$84,"<>x",S71:$S$84,"<>o",T71:$T$84,">0")/Aggregate!$X$1 -> 0 | R70: {=IFERROR(INDEX(ECR!$K:$K,MATCH(DraftSheet!$M70,ECR!$C:$C,0)),"ND")} -> 185 | T70: =VLOOKUP(M70,Aggregate!P:X,9,FALSE()) -> -33.618857 | V70: =IFERROR(VLOOKUP(DraftSheet!$W70,Aggregate!$AD:$AO,11,FALSE()),"") -> 6 | W70: =Aggregate!AD79 -> Rashod Bateman | X70: =VLOOKUP(DraftSheet!$W70,Aggregate!AD:AO,4,FALSE()) -> BAL/13 | Y70: =IFERROR(VLOOKUP(DraftSheet!$W70,Aggregate!$AD:$AO,8,FALSE()),"") -> 80.704279 | Z70: =IF(Scoring!$K$6="Auction",IFERROR(VLOOKUP(DraftSheet!$W70,Aggregate!$AD:$AO,10,FALSE()),""),IFERROR(VLOOKUP(DraftSheet!$W70,Aggregate!$AD:$AO,9,FALSE()),"")) -> 1 | AA70: =SUMIFS(AD70:$AD$85,AC70:$AC$85,"<>x",AC70:$AC$85,"<>o",AD70:$AD$85,">0")/Aggregate!$AL$1 -> 0 | AB70: {=IFERROR(INDEX(ECR!$K:$K,MATCH(DraftSheet!$W70,ECR!$C:$C,0)),"ND")} -> 198 | AD70: =VLOOKUP(W70,Aggregate!AD:AL,9,FALSE()) -> -0.81664765
B71: =IFERROR(VLOOKUP(DraftSheet!$C71,Aggregate!$AR:$BC,11,FALSE()),"") -> 5 | C71: =Aggregate!AR23 -> AJ Barner | D71: =VLOOKUP(DraftSheet!$C71,Aggregate!AR:BD,4,FALSE()) -> SEA/11 | E71: =IFERROR(VLOOKUP($C71,Aggregate!$AR:$BC,8,FALSE()),"") -> 81.538331 | F71: =IF(Scoring!$K$6="Auction",IFERROR(VLOOKUP($C71,Aggregate!$AR:$BC,10,FALSE()),""),IFERROR(VLOOKUP($C71,Aggregate!$AR:$BC,9,FALSE()),"")) -> 1 | G71: =SUMIFS($J72:J$84,$I72:I$84,"<>x",$I72:I$84,"<>o",$J72:J$84,">0")/Aggregate!$AZ$1 -> 0 | H71: {=IFERROR(INDEX(ECR!$K:$K,MATCH(DraftSheet!$C71,ECR!$C:$C,0)),"ND")} -> 169 | J71: =VLOOKUP(C71,Aggregate!AR:AZ,9,FALSE()) -> 0 | L71: =IFERROR(VLOOKUP(DraftSheet!$M71,Aggregate!$P:$AA,11,FALSE()),"") -> 8 | M71: =Aggregate!P58 -> MarShawn Lloyd | N71: =VLOOKUP(DraftSheet!$M71,Aggregate!P:AA,4,FALSE()) -> GB/11 | O71: =IFERROR(VLOOKUP(DraftSheet!$M71,Aggregate!$P:$AA,8,FALSE()),"") -> 44.340178 | P71: =IF(Scoring!$K$6="Auction",IFERROR(VLOOKUP(DraftSheet!$M71,Aggregate!$P:$AA,10,FALSE()),""),IFERROR(VLOOKUP(DraftSheet!$M71,Aggregate!$P:$AA,9,FALSE()),"")) -> 1 | Q71: =SUMIFS(T71:$T$85,S71:$S$85,"<>x",S71:$S$85,"<>o",T71:$T$85,">0")/Aggregate!$X$1 -> 0 | R71: {=IFERROR(INDEX(ECR!$K:$K,MATCH(DraftSheet!$M71,ECR!$C:$C,0)),"ND")} -> 162 | T71: =VLOOKUP(M71,Aggregate!P:X,9,FALSE()) -> -34.050711 | V71: =IFERROR(VLOOKUP(DraftSheet!$W71,Aggregate!$AD:$AO,11,FALSE()),"") -> 6 | W71: =Aggregate!AD75 -> Keenan Allen | X71: =VLOOKUP(DraftSheet!$W71,Aggregate!AD:AO,4,FALSE()) -> IND/13 | Y71: =IFERROR(VLOOKUP(DraftSheet!$W71,Aggregate!$AD:$AO,8,FALSE()),"") -> 80.250771 | Z71: =IF(Scoring!$K$6="Auction",IFERROR(VLOOKUP(DraftSheet!$W71,Aggregate!$AD:$AO,10,FALSE()),""),IFERROR(VLOOKUP(DraftSheet!$W71,Aggregate!$AD:$AO,9,FALSE()),"")) -> 1 | AA71: =SUMIFS($AD72:AD$84,$AC72:AC$84,"<>x",$AC72:AC$84,"<>o",$AD72:AD$84,">0")/Aggregate!$AL$1 -> 0 | AB71: {=IFERROR(INDEX(ECR!$K:$K,MATCH(DraftSheet!$W71,ECR!$C:$C,0)),"ND")} -> 188 | AD71: =VLOOKUP(W71,Aggregate!AD:AL,9,FALSE()) -> -1.2701559
B72: =IFERROR(VLOOKUP(DraftSheet!$C72,Aggregate!$AR:$BC,11,FALSE()),"") -> 5 | C72: =Aggregate!AR34 -> Greg Dulcich | D72: =VLOOKUP(DraftSheet!$C72,Aggregate!AR:BD,4,FALSE()) -> MIA/6 | E72: =IFERROR(VLOOKUP($C72,Aggregate!$AR:$BC,8,FALSE()),"") -> 81.472823 | F72: =IF(Scoring!$K$6="Auction",IFERROR(VLOOKUP($C72,Aggregate!$AR:$BC,10,FALSE()),""),IFERROR(VLOOKUP($C72,Aggregate!$AR:$BC,9,FALSE()),"")) -> 1 | G72: =SUMIFS($J73:J$84,$I73:I$84,"<>x",$I73:I$84,"<>o",$J73:J$84,">0")/Aggregate!$AZ$1 -> 0 | H72: {=IFERROR(INDEX(ECR!$K:$K,MATCH(DraftSheet!$C72,ECR!$C:$C,0)),"ND")} -> 271 | J72: =VLOOKUP(C72,Aggregate!AR:AZ,9,FALSE()) -> -0.065508809 | L72: =IFERROR(VLOOKUP(DraftSheet!$M72,Aggregate!$P:$AA,11,FALSE()),"") -> 8 | M72: =Aggregate!P68 -> James Conner | N72: =VLOOKUP(DraftSheet!$M72,Aggregate!P:AA,4,FALSE()) -> ARI/14 | O72: =IFERROR(VLOOKUP(DraftSheet!$M72,Aggregate!$P:$AA,8,FALSE()),"") -> 43.86462 | P72: =IF(Scoring!$K$6="Auction",IFERROR(VLOOKUP(DraftSheet!$M72,Aggregate!$P:$AA,10,FALSE()),""),IFERROR(VLOOKUP(DraftSheet!$M72,Aggregate!$P:$AA,9,FALSE()),"")) -> 1 | Q72: =SUMIFS($T73:T$84,$S73:S$84,"<>x",$S73:S$84,"<>o",$T73:T$84,">0")/Aggregate!$X$1 -> 0 | R72: {=IFERROR(INDEX(ECR!$K:$K,MATCH(DraftSheet!$M72,ECR!$C:$C,0)),"ND")} -> 213 | T72: =VLOOKUP(M72,Aggregate!P:X,9,FALSE()) -> -34.526269 | V72: =IFERROR(VLOOKUP(DraftSheet!$W72,Aggregate!$AD:$AO,11,FALSE()),"") -> 6 | W72: =Aggregate!AD69 -> Jalen Nailor | X72: =VLOOKUP(DraftSheet!$W72,Aggregate!AD:AO,4,FALSE()) -> LV/13 | Y72: =IFERROR(VLOOKUP(DraftSheet!$W72,Aggregate!$AD:$AO,8,FALSE()),"") -> 77.918691 | Z72: =IF(Scoring!$K$6="Auction",IFERROR(VLOOKUP(DraftSheet!$W72,Aggregate!$AD:$AO,10,FALSE()),""),IFERROR(VLOOKUP(DraftSheet!$W72,Aggregate!$AD:$AO,9,FALSE()),"")) -> 1 | AA72: =SUMIFS($AD73:AD$84,$AC73:AC$84,"<>x",$AC73:AC$84,"<>o",$AD73:AD$84,">0")/Aggregate!$AL$1 -> 0 | AB72: {=IFERROR(INDEX(ECR!$K:$K,MATCH(DraftSheet!$W72,ECR!$C:$C,0)),"ND")} -> 177 | AD72: =VLOOKUP(W72,Aggregate!AD:AL,9,FALSE()) -> -3.6022359
B73: =IFERROR(VLOOKUP(DraftSheet!$C73,Aggregate!$AR:$BC,11,FALSE()),"") -> 5 | C73: =Aggregate!AR25 -> Terrance Ferguson | D73: =VLOOKUP(DraftSheet!$C73,Aggregate!AR:BD,4,FALSE()) -> LAR/11 | E73: =IFERROR(VLOOKUP($C73,Aggregate!$AR:$BC,8,FALSE()),"") -> 81.026815 | F73: =IF(Scoring!$K$6="Auction",IFERROR(VLOOKUP($C73,Aggregate!$AR:$BC,10,FALSE()),""),IFERROR(VLOOKUP($C73,Aggregate!$AR:$BC,9,FALSE()),"")) -> 1 | G73: =SUMIFS($J74:J$84,$I74:I$84,"<>x",$I74:I$84,"<>o",$J74:J$84,">0")/Aggregate!$AZ$1 -> 0 | H73: {=IFERROR(INDEX(ECR!$K:$K,MATCH(DraftSheet!$C73,ECR!$C:$C,0)),"ND")} -> 174 | J73: =VLOOKUP(C73,Aggregate!AR:AZ,9,FALSE()) -> -0.51151651 | L73: =IFERROR(VLOOKUP(DraftSheet!$M73,Aggregate!$P:$AA,11,FALSE()),"") -> 8 | M73: =Aggregate!P65 -> Jaydon Blue | N73: =VLOOKUP(DraftSheet!$M73,Aggregate!P:AA,4,FALSE()) -> DAL/14 | O73: =IFERROR(VLOOKUP(DraftSheet!$M73,Aggregate!$P:$AA,8,FALSE()),"") -> 42.76707 | P73: =IF(Scoring!$K$6="Auction",IFERROR(VLOOKUP(DraftSheet!$M73,Aggregate!$P:$AA,10,FALSE()),""),IFERROR(VLOOKUP(DraftSheet!$M73,Aggregate!$P:$AA,9,FALSE()),"")) -> 1 | Q73: =SUMIFS($T74:T$84,$S74:S$84,"<>x",$S74:S$84,"<>o",$T74:T$84,">0")/Aggregate!$X$1 -> 0 | R73: {=IFERROR(INDEX(ECR!$K:$K,MATCH(DraftSheet!$M73,ECR!$C:$C,0)),"ND")} -> 197 | T73: =VLOOKUP(M73,Aggregate!P:X,9,FALSE()) -> -35.623819 | V73: =IFERROR(VLOOKUP(DraftSheet!$W73,Aggregate!$AD:$AO,11,FALSE()),"") -> 6 | W73: =Aggregate!AD60 -> Adonai Mitchell | X73: =VLOOKUP(DraftSheet!$W73,Aggregate!AD:AO,4,FALSE()) -> NYJ/13 | Y73: =IFERROR(VLOOKUP(DraftSheet!$W73,Aggregate!$AD:$AO,8,FALSE()),"") -> 74.073132 | Z73: =IF(Scoring!$K$6="Auction",IFERROR(VLOOKUP(DraftSheet!$W73,Aggregate!$AD:$AO,10,FALSE()),""),IFERROR(VLOOKUP(DraftSheet!$W73,Aggregate!$AD:$AO,9,FALSE()),"")) -> 1 | AA73: =SUMIFS($AD74:AD$84,$AC74:AC$84,"<>x",$AC74:AC$84,"<>o",$AD74:AD$84,">0")/Aggregate!$AL$1 -> 0 | AB73: {=IFERROR(INDEX(ECR!$K:$K,MATCH(DraftSheet!$W73,ECR!$C:$C,0)),"ND")} -> 159 | AD73: =VLOOKUP(W73,Aggregate!AD:AL,9,FALSE()) -> -7.4477947
B74: =IFERROR(VLOOKUP(DraftSheet!$C74,Aggregate!$AR:$BC,11,FALSE()),"") -> 5 | C74: =Aggregate!AR21 -> Chig Okonkwo | D74: =VLOOKUP(DraftSheet!$C74,Aggregate!AR:BD,4,FALSE()) -> WAS/7 | E74: =IFERROR(VLOOKUP($C74,Aggregate!$AR:$BC,8,FALSE()),"") -> 80.964611 | F74: =IF(Scoring!$K$6="Auction",IFERROR(VLOOKUP($C74,Aggregate!$AR:$BC,10,FALSE()),""),IFERROR(VLOOKUP($C74,Aggregate!$AR:$BC,9,FALSE()),"")) -> 1 | G74: =SUMIFS($J75:J$84,$I75:I$84,"<>x",$I75:I$84,"<>o",$J75:J$84,">0")/Aggregate!$AZ$1 -> 0 | H74: {=IFERROR(INDEX(ECR!$K:$K,MATCH(DraftSheet!$C74,ECR!$C:$C,0)),"ND")} -> 154 | J74: =VLOOKUP(C74,Aggregate!AR:AZ,9,FALSE()) -> -0.57371993 | L74: =IFERROR(VLOOKUP(DraftSheet!$M74,Aggregate!$P:$AA,11,FALSE()),"") -> 8 | M74: =Aggregate!P67 -> Emanuel Wilson | N74: =VLOOKUP(DraftSheet!$M74,Aggregate!P:AA,4,FALSE()) -> SEA/11 | O74: =IFERROR(VLOOKUP(DraftSheet!$M74,Aggregate!$P:$AA,8,FALSE()),"") -> 41.082102 | P74: =IF(Scoring!$K$6="Auction",IFERROR(VLOOKUP(DraftSheet!$M74,Aggregate!$P:$AA,10,FALSE()),""),IFERROR(VLOOKUP(DraftSheet!$M74,Aggregate!$P:$AA,9,FALSE()),"")) -> 1 | Q74: =SUMIFS($T75:T$84,$S75:S$84,"<>x",$S75:S$84,"<>o",$T75:T$84,">0")/Aggregate!$X$1 -> 0 | R74: {=IFERROR(INDEX(ECR!$K:$K,MATCH(DraftSheet!$M74,ECR!$C:$C,0)),"ND")} -> 208 | T74: =VLOOKUP(M74,Aggregate!P:X,9,FALSE()) -> -37.308787 | V74: =IFERROR(VLOOKUP(DraftSheet!$W74,Aggregate!$AD:$AO,11,FALSE()),"") -> 6 | W74: =Aggregate!AD68 -> Kayshon Boutte | X74: =VLOOKUP(DraftSheet!$W74,Aggregate!AD:AO,4,FALSE()) -> HOU/8 | Y74: =IFERROR(VLOOKUP(DraftSheet!$W74,Aggregate!$AD:$AO,8,FALSE()),"") -> 71.705382 | Z74: =IF(Scoring!$K$6="Auction",IFERROR(VLOOKUP(DraftSheet!$W74,Aggregate!$AD:$AO,10,FALSE()),""),IFERROR(VLOOKUP(DraftSheet!$W74,Aggregate!$AD:$AO,9,FALSE()),"")) -> 1 | AA74: =SUMIFS($AD75:AD$84,$AC75:AC$84,"<>x",$AC75:AC$84,"<>o",$AD75:AD$84,">0")/Aggregate!$AL$1 -> 0 | AB74: {=IFERROR(INDEX(ECR!$K:$K,MATCH(DraftSheet!$W74,ECR!$C:$C,0)),"ND")} -> 175 | AD74: =VLOOKUP(W74,Aggregate!AD:AL,9,FALSE()) -> -9.8155447
B75: =IFERROR(VLOOKUP(DraftSheet!$C75,Aggregate!$AR:$BC,11,FALSE()),"") -> 5 | C75: =Aggregate!AR28 -> Gunnar Helm | D75: =VLOOKUP(DraftSheet!$C75,Aggregate!AR:BD,4,FALSE()) -> TEN/9 | E75: =IFERROR(VLOOKUP($C75,Aggregate!$AR:$BC,8,FALSE()),"") -> 72.349864 | F75: =IF(Scoring!$K$6="Auction",IFERROR(VLOOKUP($C75,Aggregate!$AR:$BC,10,FALSE()),""),IFERROR(VLOOKUP($C75,Aggregate!$AR:$BC,9,FALSE()),"")) -> 1 | G75: =SUMIFS($J76:J$84,$I76:I$84,"<>x",$I76:I$84,"<>o",$J76:J$84,">0")/Aggregate!$AZ$1 -> 0 | H75: {=IFERROR(INDEX(ECR!$K:$K,MATCH(DraftSheet!$C75,ECR!$C:$C,0)),"ND")} -> 192 | J75: =VLOOKUP(C75,Aggregate!AR:AZ,9,FALSE()) -> -9.1884669 | L75: =IFERROR(VLOOKUP(DraftSheet!$M75,Aggregate!$P:$AA,11,FALSE()),"") -> 9 | M75: =Aggregate!P76 -> Chris Brooks | N75: =VLOOKUP(DraftSheet!$M75,Aggregate!P:AA,4,FALSE()) -> GB/11 | O75: =IFERROR(VLOOKUP(DraftSheet!$M75,Aggregate!$P:$AA,8,FALSE()),"") -> 40.665752 | P75: =IF(Scoring!$K$6="Auction",IFERROR(VLOOKUP(DraftSheet!$M75,Aggregate!$P:$AA,10,FALSE()),""),IFERROR(VLOOKUP(DraftSheet!$M75,Aggregate!$P:$AA,9,FALSE()),"")) -> 1 | Q75: =SUMIFS($T76:T$84,$S76:S$84,"<>x",$S76:S$84,"<>o",$T76:T$84,">0")/Aggregate!$X$1 -> 0 | R75: {=IFERROR(INDEX(ECR!$K:$K,MATCH(DraftSheet!$M75,ECR!$C:$C,0)),"ND")} -> 255 | T75: =VLOOKUP(M75,Aggregate!P:X,9,FALSE()) -> -37.725137 | V75: =IFERROR(VLOOKUP(DraftSheet!$W75,Aggregate!$AD:$AO,11,FALSE()),"") -> 6 | W75: =Aggregate!AD82 -> Cooper Kupp | X75: =VLOOKUP(DraftSheet!$W75,Aggregate!AD:AO,4,FALSE()) -> SEA/11 | Y75: =IFERROR(VLOOKUP(DraftSheet!$W75,Aggregate!$AD:$AO,8,FALSE()),"") -> 71.628471 | Z75: =IF(Scoring!$K$6="Auction",IFERROR(VLOOKUP(DraftSheet!$W75,Aggregate!$AD:$AO,10,FALSE()),""),IFERROR(VLOOKUP(DraftSheet!$W75,Aggregate!$AD:$AO,9,FALSE()),"")) -> 1 | AA75: =SUMIFS(AD75:$AD$85,AC75:$AC$85,"<>x",AC75:$AC$85,"<>o",AD75:$AD$85,">0")/Aggregate!$AL$1 -> 0 | AB75: {=IFERROR(INDEX(ECR!$K:$K,MATCH(DraftSheet!$W75,ECR!$C:$C,0)),"ND")} -> 218 | AD75: =VLOOKUP(W75,Aggregate!AD:AL,9,FALSE()) -> -9.8924559
B76: =IFERROR(VLOOKUP(DraftSheet!$C76,Aggregate!$AR:$BC,11,FALSE()),"") -> 5 | C76: =Aggregate!AR32 -> Evan Engram | D76: =VLOOKUP(DraftSheet!$C76,Aggregate!AR:BD,4,FALSE()) -> DEN/10 | E76: =IFERROR(VLOOKUP($C76,Aggregate!$AR:$BC,8,FALSE()),"") -> 71.940454 | F76: =IF(Scoring!$K$6="Auction",IFERROR(VLOOKUP($C76,Aggregate!$AR:$BC,10,FALSE()),""),IFERROR(VLOOKUP($C76,Aggregate!$AR:$BC,9,FALSE()),"")) -> 1 | G76: =SUMIFS($J77:J$84,$I77:I$84,"<>x",$I77:I$84,"<>o",$J77:J$84,">0")/Aggregate!$AZ$1 -> 0 | H76: {=IFERROR(INDEX(ECR!$K:$K,MATCH(DraftSheet!$C76,ECR!$C:$C,0)),"ND")} -> 233 | J76: =VLOOKUP(C76,Aggregate!AR:AZ,9,FALSE()) -> -9.5978778 | L76: =IFERROR(VLOOKUP(DraftSheet!$M76,Aggregate!$P:$AA,11,FALSE()),"") -> 9 | M76: =Aggregate!P77 -> Najee Harris | N76: =VLOOKUP(DraftSheet!$M76,Aggregate!P:AA,4,FALSE()) -> NYG/8 | O76: =IFERROR(VLOOKUP(DraftSheet!$M76,Aggregate!$P:$AA,8,FALSE()),"") -> 39.655192 | P76: =IF(Scoring!$K$6="Auction",IFERROR(VLOOKUP(DraftSheet!$M76,Aggregate!$P:$AA,10,FALSE()),""),IFERROR(VLOOKUP(DraftSheet!$M76,Aggregate!$P:$AA,9,FALSE()),"")) -> 1 | Q76: =SUMIFS($T77:T$84,$S77:S$84,"<>x",$S77:S$84,"<>o",$T77:T$84,">0")/Aggregate!$X$1 -> 0 | R76: {=IFERROR(INDEX(ECR!$K:$K,MATCH(DraftSheet!$M76,ECR!$C:$C,0)),"ND")} -> 258 | T76: =VLOOKUP(M76,Aggregate!P:X,9,FALSE()) -> -38.735697 | V76: =IFERROR(VLOOKUP(DraftSheet!$W76,Aggregate!$AD:$AO,11,FALSE()),"") -> 6 | W76: =Aggregate!AD67 -> Dontayvion Wicks | X76: =VLOOKUP(DraftSheet!$W76,Aggregate!AD:AO,4,FALSE()) -> PHI/10 | Y76: =IFERROR(VLOOKUP(DraftSheet!$W76,Aggregate!$AD:$AO,8,FALSE()),"") -> 69.301456 | Z76: =IF(Scoring!$K$6="Auction",IFERROR(VLOOKUP(DraftSheet!$W76,Aggregate!$AD:$AO,10,FALSE()),""),IFERROR(VLOOKUP(DraftSheet!$W76,Aggregate!$AD:$AO,9,FALSE()),"")) -> 1 | AA76: =SUMIFS(AD77:$AD$84,AC77:$AC$84,"<>x",AC77:$AC$84,"<>o",AD77:$AD$84,">0")/Aggregate!$AL$1 -> 0 | AB76: {=IFERROR(INDEX(ECR!$K:$K,MATCH(DraftSheet!$W76,ECR!$C:$C,0)),"ND")} -> 171 | AD76: =VLOOKUP(W76,Aggregate!AD:AL,9,FALSE()) -> -12.219471
B77: =IFERROR(VLOOKUP(DraftSheet!$C77,Aggregate!$AR:$BC,11,FALSE()),"") -> 5 | C77: =Aggregate!AR31 -> David Njoku | D77: =VLOOKUP(DraftSheet!$C77,Aggregate!AR:BD,4,FALSE()) -> LAC/7 | E77: =IFERROR(VLOOKUP($C77,Aggregate!$AR:$BC,8,FALSE()),"") -> 71.28872 | F77: =IF(Scoring!$K$6="Auction",IFERROR(VLOOKUP($C77,Aggregate!$AR:$BC,10,FALSE()),""),IFERROR(VLOOKUP($C77,Aggregate!$AR:$BC,9,FALSE()),"")) -> 1 | G77: =SUMIFS(J77:$J$85,I77:$I$85,"<>x",I77:$I$85,"<>o",J77:$J$85,">0")/Aggregate!$AZ$1 -> 0 | H77: {=IFERROR(INDEX(ECR!$K:$K,MATCH(DraftSheet!$C77,ECR!$C:$C,0)),"ND")} -> 227 | J77: =VLOOKUP(C77,Aggregate!AR:AZ,9,FALSE()) -> -10.249612 | L77: =IFERROR(VLOOKUP(DraftSheet!$M77,Aggregate!$P:$AA,11,FALSE()),"") -> 9 | M77: =Aggregate!P70 -> Jaylen Wright | N77: =VLOOKUP(DraftSheet!$M77,Aggregate!P:AA,4,FALSE()) -> MIA/6 | O77: =IFERROR(VLOOKUP(DraftSheet!$M77,Aggregate!$P:$AA,8,FALSE()),"") -> 39.025449 | P77: =IF(Scoring!$K$6="Auction",IFERROR(VLOOKUP(DraftSheet!$M77,Aggregate!$P:$AA,10,FALSE()),""),IFERROR(VLOOKUP(DraftSheet!$M77,Aggregate!$P:$AA,9,FALSE()),"")) -> 1 | Q77: =SUMIFS($T78:T$84,$S78:S$84,"<>x",$S78:S$84,"<>o",$T78:T$84,">0")/Aggregate!$X$1 -> 0 | R77: {=IFERROR(INDEX(ECR!$K:$K,MATCH(DraftSheet!$M77,ECR!$C:$C,0)),"ND")} -> 222 | T77: =VLOOKUP(M77,Aggregate!P:X,9,FALSE()) -> -39.36544 | V77: =IFERROR(VLOOKUP(DraftSheet!$W77,Aggregate!$AD:$AO,11,FALSE()),"") -> 6 | W77: =Aggregate!AD73 -> Malik Washington | X77: =VLOOKUP(DraftSheet!$W77,Aggregate!AD:AO,4,FALSE()) -> MIA/6 | Y77: =IFERROR(VLOOKUP(DraftSheet!$W77,Aggregate!$AD:$AO,8,FALSE()),"") -> 68.413324 | Z77: =IF(Scoring!$K$6="Auction",IFERROR(VLOOKUP(DraftSheet!$W77,Aggregate!$AD:$AO,10,FALSE()),""),IFERROR(VLOOKUP(DraftSheet!$W77,Aggregate!$AD:$AO,9,FALSE()),"")) -> 1 | AA77: =SUMIFS(AD77:$AD$85,AC77:$AC$85,"<>x",AC77:$AC$85,"<>o",AD77:$AD$85,">0")/Aggregate!$AL$1 -> 0 | AB77: {=IFERROR(INDEX(ECR!$K:$K,MATCH(DraftSheet!$W77,ECR!$C:$C,0)),"ND")} -> 182 | AD77: =VLOOKUP(W77,Aggregate!AD:AL,9,FALSE()) -> -13.107604
B78: =IFERROR(VLOOKUP(DraftSheet!$C78,Aggregate!$AR:$BC,11,FALSE()),"") -> 5 | C78: =Aggregate!AR26 -> Oronde Gadsden II | D78: =VLOOKUP(DraftSheet!$C78,Aggregate!AR:BD,4,FALSE()) -> LAC/7 | E78: =IFERROR(VLOOKUP($C78,Aggregate!$AR:$BC,8,FALSE()),"") -> 70.774289 | F78: =IF(Scoring!$K$6="Auction",IFERROR(VLOOKUP($C78,Aggregate!$AR:$BC,10,FALSE()),""),IFERROR(VLOOKUP($C78,Aggregate!$AR:$BC,9,FALSE()),"")) -> 1 | G78: =SUMIFS($J79:J$84,$I79:I$84,"<>x",$I79:I$84,"<>o",$J79:J$84,">0")/Aggregate!$AZ$1 -> 0 | H78: {=IFERROR(INDEX(ECR!$K:$K,MATCH(DraftSheet!$C78,ECR!$C:$C,0)),"ND")} -> 178 | J78: =VLOOKUP(C78,Aggregate!AR:AZ,9,FALSE()) -> -10.764042 | L78: =IFERROR(VLOOKUP(DraftSheet!$M78,Aggregate!$P:$AA,11,FALSE()),"") -> 9 | M78: =Aggregate!P69 -> George Holani | N78: =VLOOKUP(DraftSheet!$M78,Aggregate!P:AA,4,FALSE()) -> SEA/11 | O78: =IFERROR(VLOOKUP(DraftSheet!$M78,Aggregate!$P:$AA,8,FALSE()),"") -> 34.479787 | P78: =IF(Scoring!$K$6="Auction",IFERROR(VLOOKUP(DraftSheet!$M78,Aggregate!$P:$AA,10,FALSE()),""),IFERROR(VLOOKUP(DraftSheet!$M78,Aggregate!$P:$AA,9,FALSE()),"")) -> 1 | Q78: =SUMIFS($T79:T$84,$S79:S$84,"<>x",$S79:S$84,"<>o",$T79:T$84,">0")/Aggregate!$X$1 -> 0 | R78: {=IFERROR(INDEX(ECR!$K:$K,MATCH(DraftSheet!$M78,ECR!$C:$C,0)),"ND")} -> 219 | T78: =VLOOKUP(M78,Aggregate!P:X,9,FALSE()) -> -43.911102 | V78: =IFERROR(VLOOKUP(DraftSheet!$W78,Aggregate!$AD:$AO,11,FALSE()),"") -> 6 | W78: =Aggregate!AD78 -> Travis Hunter | X78: =VLOOKUP(DraftSheet!$W78,Aggregate!AD:AO,4,FALSE()) -> JAC/7 | Y78: =IFERROR(VLOOKUP(DraftSheet!$W78,Aggregate!$AD:$AO,8,FALSE()),"") -> 67.946647 | Z78: =IF(Scoring!$K$6="Auction",IFERROR(VLOOKUP(DraftSheet!$W78,Aggregate!$AD:$AO,10,FALSE()),""),IFERROR(VLOOKUP(DraftSheet!$W78,Aggregate!$AD:$AO,9,FALSE()),"")) -> 1 | AA78: =SUMIFS($AD79:AD$84,$AC79:AC$84,"<>x",$AC79:AC$84,"<>o",$AD79:AD$84,">0")/Aggregate!$AL$1 -> 0 | AB78: {=IFERROR(INDEX(ECR!$K:$K,MATCH(DraftSheet!$W78,ECR!$C:$C,0)),"ND")} -> 193 | AD78: =VLOOKUP(W78,Aggregate!AD:AL,9,FALSE()) -> -13.57428
B79: =IFERROR(VLOOKUP(DraftSheet!$C79,Aggregate!$AR:$BC,11,FALSE()),"") -> 6 | C79: =Aggregate!AR38 -> Mike Gesicki | D79: =VLOOKUP(DraftSheet!$C79,Aggregate!AR:BD,4,FALSE()) -> CIN/6 | E79: =IFERROR(VLOOKUP($C79,Aggregate!$AR:$BC,8,FALSE()),"") -> 65.589602 | F79: =IF(Scoring!$K$6="Auction",IFERROR(VLOOKUP($C79,Aggregate!$AR:$BC,10,FALSE()),""),IFERROR(VLOOKUP($C79,Aggregate!$AR:$BC,9,FALSE()),"")) -> 1 | G79: =SUMIFS($J80:J$84,$I80:I$84,"<>x",$I80:I$84,"<>o",$J80:J$84,">0")/Aggregate!$AZ$1 -> 0 | H79: {=IFERROR(INDEX(ECR!$K:$K,MATCH(DraftSheet!$C79,ECR!$C:$C,0)),"ND")} -> 305 | J79: =VLOOKUP(C79,Aggregate!AR:AZ,9,FALSE()) -> -15.94873 | L79: =IFERROR(VLOOKUP(DraftSheet!$M79,Aggregate!$P:$AA,11,FALSE()),"") -> 9 | M79: =Aggregate!P60 -> Ray Davis | N79: =VLOOKUP(DraftSheet!$M79,Aggregate!P:AA,4,FALSE()) -> BUF/7 | O79: =IFERROR(VLOOKUP(DraftSheet!$M79,Aggregate!$P:$AA,8,FALSE()),"") -> 34.249439 | P79: =IF(Scoring!$K$6="Auction",IFERROR(VLOOKUP(DraftSheet!$M79,Aggregate!$P:$AA,10,FALSE()),""),IFERROR(VLOOKUP(DraftSheet!$M79,Aggregate!$P:$AA,9,FALSE()),"")) -> 1 | Q79: =SUMIFS($T80:T$84,$S80:S$84,"<>x",$S80:S$84,"<>o",$T80:T$84,">0")/Aggregate!$X$1 -> 0 | R79: {=IFERROR(INDEX(ECR!$K:$K,MATCH(DraftSheet!$M79,ECR!$C:$C,0)),"ND")} -> 168 | T79: =VLOOKUP(M79,Aggregate!P:X,9,FALSE()) -> -44.14145 | V79: =IFERROR(VLOOKUP(DraftSheet!$W79,Aggregate!$AD:$AO,11,FALSE()),"") -> 6 | W79: =Aggregate!AD77 -> Jaylin Noel | X79: =VLOOKUP(DraftSheet!$W79,Aggregate!AD:AO,4,FALSE()) -> HOU/8 | Y79: =IFERROR(VLOOKUP(DraftSheet!$W79,Aggregate!$AD:$AO,8,FALSE()),"") -> 67.561802 | Z79: =IF(Scoring!$K$6="Auction",IFERROR(VLOOKUP(DraftSheet!$W79,Aggregate!$AD:$AO,10,FALSE()),""),IFERROR(VLOOKUP(DraftSheet!$W79,Aggregate!$AD:$AO,9,FALSE()),"")) -> 1 | AA79: =SUMIFS($AD80:AD$84,$AC80:AC$84,"<>x",$AC80:AC$84,"<>o",$AD80:AD$84,">0")/Aggregate!$AL$1 -> 0 | AB79: {=IFERROR(INDEX(ECR!$K:$K,MATCH(DraftSheet!$W79,ECR!$C:$C,0)),"ND")} -> 191 | AD79: =VLOOKUP(W79,Aggregate!AD:AL,9,FALSE()) -> -13.959125
B80: =IFERROR(VLOOKUP(DraftSheet!$C80,Aggregate!$AR:$BC,11,FALSE()),"") -> 6 | C80: =Aggregate!AR33 -> Colby Parkinson | D80: =VLOOKUP(DraftSheet!$C80,Aggregate!AR:BD,4,FALSE()) -> LAR/11 | E80: =IFERROR(VLOOKUP($C80,Aggregate!$AR:$BC,8,FALSE()),"") -> 64.824569 | F80: =IF(Scoring!$K$6="Auction",IFERROR(VLOOKUP($C80,Aggregate!$AR:$BC,10,FALSE()),""),IFERROR(VLOOKUP($C80,Aggregate!$AR:$BC,9,FALSE()),"")) -> 1 | G80: =SUMIFS(J80:$J$85,I80:$I$85,"<>x",I80:$I$85,"<>o",J80:$J$85,">0")/Aggregate!$AZ$1 -> 0 | H80: {=IFERROR(INDEX(ECR!$K:$K,MATCH(DraftSheet!$C80,ECR!$C:$C,0)),"ND")} -> 237 | J80: =VLOOKUP(C80,Aggregate!AR:AZ,9,FALSE()) -> -16.713763 | L80: =IFERROR(VLOOKUP(DraftSheet!$M80,Aggregate!$P:$AA,11,FALSE()),"") -> 9 | M80: =Aggregate!P62 -> Sean Tucker | N80: =VLOOKUP(DraftSheet!$M80,Aggregate!P:AA,4,FALSE()) -> TB/10 | O80: =IFERROR(VLOOKUP(DraftSheet!$M80,Aggregate!$P:$AA,8,FALSE()),"") -> 32.655578 | P80: =IF(Scoring!$K$6="Auction",IFERROR(VLOOKUP(DraftSheet!$M80,Aggregate!$P:$AA,10,FALSE()),""),IFERROR(VLOOKUP(DraftSheet!$M80,Aggregate!$P:$AA,9,FALSE()),"")) -> 1 | Q80: =SUMIFS($T81:T$84,$S81:S$84,"<>x",$S81:S$84,"<>o",$T81:T$84,">0")/Aggregate!$X$1 -> 0 | R80: {=IFERROR(INDEX(ECR!$K:$K,MATCH(DraftSheet!$M80,ECR!$C:$C,0)),"ND")} -> 183 | T80: =VLOOKUP(M80,Aggregate!P:X,9,FALSE()) -> -45.735311 | V80: =IFERROR(VLOOKUP(DraftSheet!$W80,Aggregate!$AD:$AO,11,FALSE()),"") -> 7 | W80: =Aggregate!AD66 -> Tre' Harris | X80: =VLOOKUP(DraftSheet!$W80,Aggregate!AD:AO,4,FALSE()) -> LAC/7 | Y80: =IFERROR(VLOOKUP(DraftSheet!$W80,Aggregate!$AD:$AO,8,FALSE()),"") -> 60.833774 | Z80: =IF(Scoring!$K$6="Auction",IFERROR(VLOOKUP(DraftSheet!$W80,Aggregate!$AD:$AO,10,FALSE()),""),IFERROR(VLOOKUP(DraftSheet!$W80,Aggregate!$AD:$AO,9,FALSE()),"")) -> 1 | AA80: =SUMIFS($AD81:AD$84,$AC81:AC$84,"<>x",$AC81:AC$84,"<>o",$AD81:AD$84,">0")/Aggregate!$AL$1 -> 0 | AB80: {=IFERROR(INDEX(ECR!$K:$K,MATCH(DraftSheet!$W80,ECR!$C:$C,0)),"ND")} -> 170 | AD80: =VLOOKUP(W80,Aggregate!AD:AL,9,FALSE()) -> -20.687153
B81: =IFERROR(VLOOKUP(DraftSheet!$C81,Aggregate!$AR:$BC,11,FALSE()),"") -> 6 | C81: =Aggregate!AR35 -> Mason Taylor | D81: =VLOOKUP(DraftSheet!$C81,Aggregate!AR:BD,4,FALSE()) -> NYJ/13 | E81: =IFERROR(VLOOKUP($C81,Aggregate!$AR:$BC,8,FALSE()),"") -> 62.476715 | F81: =IF(Scoring!$K$6="Auction",IFERROR(VLOOKUP($C81,Aggregate!$AR:$BC,10,FALSE()),""),IFERROR(VLOOKUP($C81,Aggregate!$AR:$BC,9,FALSE()),"")) -> 1 | G81: =SUMIFS($J82:J$84,$I82:I$84,"<>x",$I82:I$84,"<>o",$J82:J$84,">0")/Aggregate!$AZ$1 -> 0 | H81: {=IFERROR(INDEX(ECR!$K:$K,MATCH(DraftSheet!$C81,ECR!$C:$C,0)),"ND")} -> 280 | J81: =VLOOKUP(C81,Aggregate!AR:AZ,9,FALSE()) -> -19.061616 | L81: =IFERROR(VLOOKUP(DraftSheet!$M81,Aggregate!$P:$AA,11,FALSE()),"") -> 9 | M81: =Aggregate!P82 -> Malik Davis | N81: =VLOOKUP(DraftSheet!$M81,Aggregate!P:AA,4,FALSE()) -> DAL/14 | O81: =IFERROR(VLOOKUP(DraftSheet!$M81,Aggregate!$P:$AA,8,FALSE()),"") -> 31.591146 | P81: =IF(Scoring!$K$6="Auction",IFERROR(VLOOKUP(DraftSheet!$M81,Aggregate!$P:$AA,10,FALSE()),""),IFERROR(VLOOKUP(DraftSheet!$M81,Aggregate!$P:$AA,9,FALSE()),"")) -> 1 | Q81: =SUMIFS(T81:$T$85,S81:$S$85,"<>x",S81:$S$85,"<>o",T81:$T$85,">0")/Aggregate!$X$1 -> 0 | R81: {=IFERROR(INDEX(ECR!$K:$K,MATCH(DraftSheet!$M81,ECR!$C:$C,0)),"ND")} -> 274 | T81: =VLOOKUP(M81,Aggregate!P:X,9,FALSE()) -> -46.799743 | V81: =IFERROR(VLOOKUP(DraftSheet!$W81,Aggregate!$AD:$AO,11,FALSE()),"") -> 7 | W81: =Aggregate!AD71 -> Ryan Flournoy | X81: =VLOOKUP(DraftSheet!$W81,Aggregate!AD:AO,4,FALSE()) -> DAL/14 | Y81: =IFERROR(VLOOKUP(DraftSheet!$W81,Aggregate!$AD:$AO,8,FALSE()),"") -> 59.609779 | Z81: =IF(Scoring!$K$6="Auction",IFERROR(VLOOKUP(DraftSheet!$W81,Aggregate!$AD:$AO,10,FALSE()),""),IFERROR(VLOOKUP(DraftSheet!$W81,Aggregate!$AD:$AO,9,FALSE()),"")) -> 1 | AA81: =SUMIFS($AD82:AD$84,$AC82:AC$84,"<>x",$AC82:AC$84,"<>o",$AD82:AD$84,">0")/Aggregate!$AL$1 -> 0 | AB81: {=IFERROR(INDEX(ECR!$K:$K,MATCH(DraftSheet!$W81,ECR!$C:$C,0)),"ND")} -> 180 | AD81: =VLOOKUP(W81,Aggregate!AD:AL,9,FALSE()) -> -21.911148
B82: =IFERROR(VLOOKUP(DraftSheet!$C82,Aggregate!$AR:$BC,11,FALSE()),"") -> 6 | C82: =Aggregate!AR36 -> Theo Johnson | D82: =VLOOKUP(DraftSheet!$C82,Aggregate!AR:BD,4,FALSE()) -> NYG/8 | E82: =IFERROR(VLOOKUP($C82,Aggregate!$AR:$BC,8,FALSE()),"") -> 55.553712 | F82: =IF(Scoring!$K$6="Auction",IFERROR(VLOOKUP($C82,Aggregate!$AR:$BC,10,FALSE()),""),IFERROR(VLOOKUP($C82,Aggregate!$AR:$BC,9,FALSE()),"")) -> 1 | G82: =SUMIFS($J83:J$84,$I83:I$84,"<>x",$I83:I$84,"<>o",$J83:J$84,">0")/Aggregate!$AZ$1 -> 0 | H82: {=IFERROR(INDEX(ECR!$K:$K,MATCH(DraftSheet!$C82,ECR!$C:$C,0)),"ND")} -> 283 | J82: =VLOOKUP(C82,Aggregate!AR:AZ,9,FALSE()) -> -25.984619 | L82: =IFERROR(VLOOKUP(DraftSheet!$M82,Aggregate!$P:$AA,11,FALSE()),"") -> 9 | M82: =Aggregate!P75 -> Isaiah Davis | N82: =VLOOKUP(DraftSheet!$M82,Aggregate!P:AA,4,FALSE()) -> NYJ/13 | O82: =IFERROR(VLOOKUP(DraftSheet!$M82,Aggregate!$P:$AA,8,FALSE()),"") -> 30.679041 | P82: =IF(Scoring!$K$6="Auction",IFERROR(VLOOKUP(DraftSheet!$M82,Aggregate!$P:$AA,10,FALSE()),""),IFERROR(VLOOKUP(DraftSheet!$M82,Aggregate!$P:$AA,9,FALSE()),"")) -> 1 | Q82: =SUMIFS($T83:T$84,$S83:S$84,"<>x",$S83:S$84,"<>o",$T83:T$84,">0")/Aggregate!$X$1 -> 0 | R82: {=IFERROR(INDEX(ECR!$K:$K,MATCH(DraftSheet!$M82,ECR!$C:$C,0)),"ND")} -> 250 | T82: =VLOOKUP(M82,Aggregate!P:X,9,FALSE()) -> -47.711848 | V82: =IFERROR(VLOOKUP(DraftSheet!$W82,Aggregate!$AD:$AO,11,FALSE()),"") -> 7 | W82: =Aggregate!AD80 -> Isaac TeSlaa | X82: =VLOOKUP(DraftSheet!$W82,Aggregate!AD:AO,4,FALSE()) -> DET/6 | Y82: =IFERROR(VLOOKUP(DraftSheet!$W82,Aggregate!$AD:$AO,8,FALSE()),"") -> 56.299632 | Z82: =IF(Scoring!$K$6="Auction",IFERROR(VLOOKUP(DraftSheet!$W82,Aggregate!$AD:$AO,10,FALSE()),""),IFERROR(VLOOKUP(DraftSheet!$W82,Aggregate!$AD:$AO,9,FALSE()),"")) -> 1 | AA82: =SUMIFS($AD83:AD$84,$AC83:AC$84,"<>x",$AC83:AC$84,"<>o",$AD83:AD$84,">0")/Aggregate!$AL$1 -> 0 | AB82: {=IFERROR(INDEX(ECR!$K:$K,MATCH(DraftSheet!$W82,ECR!$C:$C,0)),"ND")} -> 199 | AD82: =VLOOKUP(W82,Aggregate!AD:AL,9,FALSE()) -> -25.221295
B83: =IFERROR(VLOOKUP(DraftSheet!$C83,Aggregate!$AR:$BC,11,FALSE()),"") -> 7 | C83: =Aggregate!AR37 -> Eli Stowers | D83: =VLOOKUP(DraftSheet!$C83,Aggregate!AR:BD,4,FALSE()) -> PHI/10 | E83: =IFERROR(VLOOKUP($C83,Aggregate!$AR:$BC,8,FALSE()),"") -> 39.024849 | F83: =IF(Scoring!$K$6="Auction",IFERROR(VLOOKUP($C83,Aggregate!$AR:$BC,10,FALSE()),""),IFERROR(VLOOKUP($C83,Aggregate!$AR:$BC,9,FALSE()),"")) -> 1 | G83: 0 | H83: {=IFERROR(INDEX(ECR!$K:$K,MATCH(DraftSheet!$C83,ECR!$C:$C,0)),"ND")} -> 296 | J83: =VLOOKUP(C83,Aggregate!AR:AZ,9,FALSE()) -> -42.513483 | L83: =IFERROR(VLOOKUP(DraftSheet!$M83,Aggregate!$P:$AA,11,FALSE()),"") -> 9 | M83: =Aggregate!P71 -> Ollie Gordon II | N83: =VLOOKUP(DraftSheet!$M83,Aggregate!P:AA,4,FALSE()) -> MIA/6 | O83: =IFERROR(VLOOKUP(DraftSheet!$M83,Aggregate!$P:$AA,8,FALSE()),"") -> 28.552035 | P83: =IF(Scoring!$K$6="Auction",IFERROR(VLOOKUP(DraftSheet!$M83,Aggregate!$P:$AA,10,FALSE()),""),IFERROR(VLOOKUP(DraftSheet!$M83,Aggregate!$P:$AA,9,FALSE()),"")) -> 1 | Q83: =SUMIFS($T84:T$84,$S84:S$84,"<>x",$S84:S$84,"<>o",$T84:T$84,">0")/Aggregate!$X$1 -> 0 | R83: {=IFERROR(INDEX(ECR!$K:$K,MATCH(DraftSheet!$M83,ECR!$C:$C,0)),"ND")} -> 239 | T83: =VLOOKUP(M83,Aggregate!P:X,9,FALSE()) -> -49.838854 | V83: =IFERROR(VLOOKUP(DraftSheet!$W83,Aggregate!$AD:$AO,11,FALSE()),"") -> 7 | W83: =Aggregate!AD70 -> Pat Bryant | X83: =VLOOKUP(DraftSheet!$W83,Aggregate!AD:AO,4,FALSE()) -> DEN/10 | Y83: =IFERROR(VLOOKUP(DraftSheet!$W83,Aggregate!$AD:$AO,8,FALSE()),"") -> 52.000565 | Z83: =IF(Scoring!$K$6="Auction",IFERROR(VLOOKUP(DraftSheet!$W83,Aggregate!$AD:$AO,10,FALSE()),""),IFERROR(VLOOKUP(DraftSheet!$W83,Aggregate!$AD:$AO,9,FALSE()),"")) -> 1 | AA83: =SUMIFS($AD84:AD$84,$AC84:AC$84,"<>x",$AC84:AC$84,"<>o",$AD84:AD$84,">0")/Aggregate!$AL$1 -> 0 | AB83: {=IFERROR(INDEX(ECR!$K:$K,MATCH(DraftSheet!$W83,ECR!$C:$C,0)),"ND")} -> 179 | AD83: =VLOOKUP(W83,Aggregate!AD:AL,9,FALSE()) -> -29.520362
B84: =IFERROR(VLOOKUP(DraftSheet!$C84,Aggregate!$AR:$BC,11,FALSE()),"") -> 7 | C84: =Aggregate!AR39 -> Jake Tonges | D84: =VLOOKUP(DraftSheet!$C84,Aggregate!AR:BD,4,FALSE()) -> SF/8 | E84: =IFERROR(VLOOKUP($C84,Aggregate!$AR:$BC,8,FALSE()),"") -> 36.480853 | F84: =IF(Scoring!$K$6="Auction",IFERROR(VLOOKUP($C84,Aggregate!$AR:$BC,10,FALSE()),""),IFERROR(VLOOKUP($C84,Aggregate!$AR:$BC,9,FALSE()),"")) -> 1 | G84: =SUMIFS(J84:$J$85,I84:$I$85,"<>x",I84:$I$85,"<>o",J84:$J$85,">0")/Aggregate!$AZ$1 -> 0 | H84: {=IFERROR(INDEX(ECR!$K:$K,MATCH(DraftSheet!$C84,ECR!$C:$C,0)),"ND")} -> 321 | J84: =VLOOKUP(C84,Aggregate!AR:AZ,9,FALSE()) -> -45.057478 | L84: =IFERROR(VLOOKUP(DraftSheet!$M84,Aggregate!$P:$AA,11,FALSE()),"") -> 9 | M84: =Aggregate!P81 -> LeQuint Allen Jr. | N84: =VLOOKUP(DraftSheet!$M84,Aggregate!P:AA,4,FALSE()) -> JAC/7 | O84: =IFERROR(VLOOKUP(DraftSheet!$M84,Aggregate!$P:$AA,8,FALSE()),"") -> 27.078921 | P84: =IF(Scoring!$K$6="Auction",IFERROR(VLOOKUP(DraftSheet!$M84,Aggregate!$P:$AA,10,FALSE()),""),IFERROR(VLOOKUP(DraftSheet!$M84,Aggregate!$P:$AA,9,FALSE()),"")) -> 1 | Q84: =SUMIFS(T84:$T$85,S84:$S$85,"<>x",S84:$S$85,"<>o",T84:$T$85,">0")/Aggregate!$X$1 -> 0 | R84: {=IFERROR(INDEX(ECR!$K:$K,MATCH(DraftSheet!$M84,ECR!$C:$C,0)),"ND")} -> 266 | T84: =VLOOKUP(M84,Aggregate!P:X,9,FALSE()) -> -51.311968 | V84: =IFERROR(VLOOKUP(DraftSheet!$W84,Aggregate!$AD:$AO,11,FALSE()),"") -> 7 | W84: =Aggregate!AD81 -> Darnell Mooney | X84: =VLOOKUP(DraftSheet!$W84,Aggregate!AD:AO,4,FALSE()) -> NYG/8 | Y84: =IFERROR(VLOOKUP(DraftSheet!$W84,Aggregate!$AD:$AO,8,FALSE()),"") -> 45.658324 | Z84: =IF(Scoring!$K$6="Auction",IFERROR(VLOOKUP(DraftSheet!$W84,Aggregate!$AD:$AO,10,FALSE()),""),IFERROR(VLOOKUP(DraftSheet!$W84,Aggregate!$AD:$AO,9,FALSE()),"")) -> 1 | AA84: =SUMIFS(AD84:$AD$85,AC84:$AC$85,"<>x",AC84:$AC$85,"<>o",AD84:$AD$85,">0")/Aggregate!$AL$1 -> 0 | AB84: {=IFERROR(INDEX(ECR!$K:$K,MATCH(DraftSheet!$W84,ECR!$C:$C,0)),"ND")} -> 216 | AD84: =VLOOKUP(W84,Aggregate!AD:AL,9,FALSE()) -> -35.862604

Sheet Aggregate
A1: Baseline: | B1: =Scoring!B43 -> 12 | C1: =LARGE(I3:I50, $B$1) -> 221.64681 | J1: =SUMIF(Aggregate!$J$3:$J$52,">0") -> 192.23476 | O1: Baseline: | P1: =Scoring!C43 -> 48 | Q1: =LARGE($W$3:$W$102,P1) -> 78.390889 | X1: =SUMIF(Aggregate!$X$3:$X$102,">0") -> 3214.2289 | AC1: Baseline: | AD1: =Scoring!D43 -> 65 | AE1: =LARGE(Aggregate!$AK$3:$AK$102,AD1) -> 81.520927 | AL1: =SUMIF(Aggregate!$AL$3:$AL$102,">0") -> 3066.1023 | AQ1: Baseline: | AR1: =Scoring!E43 -> 24 | AS1: =IF(AR1=0,AE1,LARGE($AY$3:$AY$202,AR1)) -> 81.538331 | AZ1: =SUMIF(Aggregate!$AZ$3:$AZ$52,">0") -> 664.20043
B2: PLAYER | C2: Team | D2: Bye | E2: Team/Bye | F2: LOW | G2: AVG | H2: HIGH | I2: Zscore Projection | J2: VBD | K2: Auc | L2: Tier | M2: Missed Games | P2: PLAYER | Q2: Team | R2: Bye | S2: Team/Bye | T2: LOW | U2: AVG | V2: HIGH | W2: Zscore Projection | X2: VBD | Y2: Auction | Z2: Tier | AA2: Missed Games | AD2: PLAYER | AE2: Team | AF2: Bye | AG2: Team/Bye | AH2: LOW | AI2: AVG | AJ2: HIGH | AK2: Zscore Projection | AL2: VBD | AM2: Auction | AN2: Tier | AO2: Missed Games | AR2: PLAYER | AS2: Team | AT2: Bye | AU2: Team/Bye | AV2: LOW | AW2: AVG | AX2: HIGH | AY2: Zscore Projection | AZ2: VBD | BA2: Auction | BB2: Tier | BC2: Missed Games | BD2: V/R | BF2: QBRank | BG2: QBPts | BH2: QB | BI2: QBTier | BJ2: Tier | BK2: RBRank | BL2: RBPts | BM2: RB | BN2: RB Tier | BO2: Tier | BP2: WRRank | BQ2: WRPts | BR2: WR | BS2: WRTier | BT2: Tier | BU2: TERank | BV2: TEPts | BW2: TE | BX2: TETier | BY2: Tier
A3: QB1 | B3: =VLOOKUP(A3,ECR!E:L,8,FALSE()) -> Josh Allen | C3: =IFERROR(VLOOKUP(Aggregate!$B3,ECR!C:F,2,FALSE()),"-") -> BUF | D3: =IFERROR(VLOOKUP(Aggregate!$B3,ECR!C:F,4,FALSE()),"-") -> 7 | E3: =Aggregate!$C3 & "/" & Aggregate!$D3 -> BUF/7 | F3: =IFERROR(VLOOKUP(Aggregate!$B3,QB!A:Q,15,FALSE())/17*(16-Aggregate!$M3),0) -> 266.18623 | G3: =IFERROR(VLOOKUP(Aggregate!$B3,QB!A:Q,16,FALSE())/17*(16-Aggregate!$M3),0) -> 283.64238 | H3: =IFERROR(VLOOKUP(Aggregate!$B3,QB!A:Q,17,FALSE())/17*(16-Aggregate!$M3),0) -> 308.27948 | I3: =AVERAGE(Aggregate!$F3,Aggregate!$G3,Aggregate!$H3,VLOOKUP(Aggregate!$B3,ECR!L:N,3,FALSE)) -> 285.43762 | J3: =Aggregate!$I3-$C$1 -> 63.790813 | K3: =MAX(Aggregate!$J3*Scoring!$B$48+1,1) -> 17.714688 | L3: =VLOOKUP(Aggregate!$J3,BH:BJ,3,FALSE) -> 1 | M3: {=VLOOKUP(INDEX(ECR!$E:$E,MATCH(B3,ECR!$C:$C,0)),RISK!A:B,2,FALSE())} -> 1.7985 | O3: RB1 | P3: =VLOOKUP(O3,ECR!E:L,8,FALSE()) -> Jahmyr Gibbs | Q3: =IFERROR(VLOOKUP(Aggregate!$P3,ECR!C:F,2,FALSE()),"-") -> DET | R3: =IFERROR(VLOOKUP(Aggregate!$P3,ECR!C:F,4,FALSE()),"-") -> 6 | S3: =Aggregate!$Q3 & "/" & Aggregate!$R3 -> DET/6 | T3: =IFERROR(VLOOKUP(Aggregate!$P3,RB!A:Q,13,FALSE())/17*(16-Aggregate!$AA3),0) -> 239.80412 | U3: =IFERROR(VLOOKUP(Aggregate!$P3,RB!A:Q,14,FALSE())/17*(16-Aggregate!$AA3),0) -> 257.85882 | V3: =IFERROR(VLOOKUP(Aggregate!$P3,RB!A:Q,15,FALSE())/17*(16-Aggregate!$AA3),0) -> 275.06471 | W3: =AVERAGE(Aggregate!$T3,Aggregate!$U3,Aggregate!$V3,VLOOKUP(Aggregate!$P3,ECR!L:N,3,FALSE)) -> 257.64662 | X3: =Aggregate!$W3-$Q$1 -> 179.25573 | Y3: =MAX(Aggregate!$X3*Scoring!$B$48+1,1) -> 47.969201 | Z3: =VLOOKUP(Aggregate!$X3,BM:BO,3,FALSE) -> 1 | AA3: {=VLOOKUP(INDEX(ECR!$E:$E,MATCH(P3,ECR!$C:$C,0)),RISK!A:B,2,FALSE())} -> 3 | AC3: WR1 | AD3: =VLOOKUP(AC3,ECR!E:L,8,FALSE()) -> Ja'Marr Chase | AE3: =IFERROR(VLOOKUP(Aggregate!$AD3,ECR!C:F,2,FALSE()),"-") -> CIN | AF3: =IFERROR(VLOOKUP(Aggregate!$AD3,ECR!C:F,4,FALSE()),"-") -> 6 | AG3: =Aggregate!$AE3 & "/" & Aggregate!$AF3 -> CIN/6 | AH3: =IFERROR(VLOOKUP(Aggregate!$AD3,WR!A:Q,13,FALSE())/17*(16-Aggregate!$AO3),0) -> 224.11707 | AI3: =IFERROR(VLOOKUP(Aggregate!$AD3,WR!A:Q,14,FALSE())/17*(16-Aggregate!$AO3),0) -> 233.03939 | AJ3: =IFERROR(VLOOKUP(Aggregate!$AD3,WR!A:Q,15,FALSE())/17*(16-Aggregate!$AO3),0) -> 242.32606 | AK3: =AVERAGE(Aggregate!$AH3,Aggregate!$AI3,Aggregate!$AJ3,VLOOKUP(Aggregate!$AD3,ECR!L:N,3,FALSE)) -> 234.13723 | AL3: =Aggregate!$AK3-$AE$1 -> 152.6163 | AM3: =MAX(Aggregate!$AL3*Scoring!$B$48+1,1) -> 40.989047 | AN3: =VLOOKUP(Aggregate!$AL3,BR:BT,3,FALSE) -> 1 | AO3: {=VLOOKUP(INDEX(ECR!$E:$E,MATCH(AD3,ECR!$C:$C,0)),RISK!A:B,2,FALSE())} -> 1.5955 | AQ3: TE1 | AR3: =VLOOKUP(AQ3,ECR!E:L,8,FALSE()) -> Brock Bowers | AS3: =IFERROR(VLOOKUP(Aggregate!$AR3,ECR!C:F,2,FALSE()),"-") -> LV | AT3: =IFERROR(VLOOKUP(Aggregate!$AR3,ECR!C:F,4,FALSE()),"-") -> 13 | AU3: =Aggregate!$AS3 & "/" & Aggregate!$AT3 -> LV/13 | AV3: =IFERROR(VLOOKUP(Aggregate!$AR3,TE!A:K,9,FALSE())/17*(16-Aggregate!$BC3),0) -> 146.10426 | AW3: =IFERROR(VLOOKUP(Aggregate!$AR3,TE!A:K,10,FALSE())/17*(16-Aggregate!$BC3),0) -> 165.39649 | AX3: =IFERROR(VLOOKUP(Aggregate!$AR3,TE!A:K,11,FALSE())/17*(16-Aggregate!$BC3),0) -> 178.15034 | AY3: =AVERAGE(Aggregate!$AV3,Aggregate!$AW3,Aggregate!$AX3,VLOOKUP(Aggregate!$AR3,ECR!L:N,3,FALSE)) -> 163.76189 | AZ3: =Aggregate!$AY3-$AS$1 -> 82.223562 | BA3: =MAX(Aggregate!$AZ3*Scoring!$B$48+1,1) -> 22.5445 | BB3: =VLOOKUP(Aggregate!$AZ3,BW:BY,3,FALSE) -> 1 | BC3: {=VLOOKUP(INDEX(ECR!$E:$E,MATCH(AR3,ECR!$C:$C,0)),RISK!A:B,2,FALSE())} -> 2.2775 | BF3: 1 | BG3: =IFERROR(LARGE($G$3:$G$52,BF3),"") -> 283.64238 | BH3: =IFERROR(LARGE($J$3:$J$52,1),"") -> 63.790813 | BI3: =BH3 -> 63.790813 | BJ3: 1 | BK3: 1 | BL3: =IFERROR(LARGE($U$3:$U$102,BK3),"") -> 257.85882 | BM3: =IFERROR(LARGE($X$3:$X$102,1),"") -> 179.25573 | BN3: =BM3 -> 179.25573 | BO3: 1 | BP3: 1 | BQ3: =IFERROR(LARGE($AI$3:$AI$102,BP3),"") -> 237.0664 | BR3: =IFERROR(LARGE($AL$3:$AL$102,1),"") -> 154.79155 | BS3: =BR3 -> 154.79155 | BT3: 1 | BU3: 1 | BV3: =IFERROR(LARGE($AW$3:$AW$52,BU3),"") -> 165.39649 | BW3: =IFERROR(LARGE($AZ$3:$AZ$52,1),"") -> 82.223562 | BX3: =BW3 -> 82.223562 | BY3: 1
A4: QB2 | B4: =VLOOKUP(A4,ECR!E:L,8,FALSE()) -> Lamar Jackson | C4: =IFERROR(VLOOKUP(Aggregate!$B4,ECR!C:F,2,FALSE()),"-") -> BAL | D4: =IFERROR(VLOOKUP(Aggregate!$B4,ECR!C:F,4,FALSE()),"-") -> 13 | E4: =Aggregate!$C4 & "/" & Aggregate!$D4 -> BAL/13 | F4: =IFERROR(VLOOKUP(Aggregate!$B4,QB!A:Q,15,FALSE())/17*(16-Aggregate!$M4),0) -> 227.01276 | G4: =IFERROR(VLOOKUP(Aggregate!$B4,QB!A:Q,16,FALSE())/17*(16-Aggregate!$M4),0) -> 249.94348 | H4: =IFERROR(VLOOKUP(Aggregate!$B4,QB!A:Q,17,FALSE())/17*(16-Aggregate!$M4),0) -> 285.60399 | I4: =AVERAGE(Aggregate!$F4,Aggregate!$G4,Aggregate!$H4,VLOOKUP(Aggregate!$B4,ECR!L:N,3,FALSE)) -> 253.12593 | J4: =Aggregate!$I4-$C$1 -> 31.479122 | K4: =MAX(Aggregate!$J4*Scoring!$B$48+1,1) -> 9.2482674 | L4: =VLOOKUP(Aggregate!$J4,BH:BJ,3,FALSE) -> 2 | M4: {=VLOOKUP(INDEX(ECR!$E:$E,MATCH(B4,ECR!$C:$C,0)),RISK!A:B,2,FALSE())} -> 1.7646 | O4: RB2 | P4: =VLOOKUP(O4,ECR!E:L,8,FALSE()) -> Bijan Robinson | Q4: =IFERROR(VLOOKUP(Aggregate!$P4,ECR!C:F,2,FALSE()),"-") -> ATL | R4: =IFERROR(VLOOKUP(Aggregate!$P4,ECR!C:F,4,FALSE()),"-") -> 11 | S4: =Aggregate!$Q4 & "/" & Aggregate!$R4 -> ATL/11 | T4: =IFERROR(VLOOKUP(Aggregate!$P4,RB!A:Q,13,FALSE())/17*(16-Aggregate!$AA4),0) -> 235.33059 | U4: =IFERROR(VLOOKUP(Aggregate!$P4,RB!A:Q,14,FALSE())/17*(16-Aggregate!$AA4),0) -> 243.62 | V4: =IFERROR(VLOOKUP(Aggregate!$P4,RB!A:Q,15,FALSE())/17*(16-Aggregate!$AA4),0) -> 250.64765 | W4: =AVERAGE(Aggregate!$T4,Aggregate!$U4,Aggregate!$V4,VLOOKUP(Aggregate!$P4,ECR!L:N,3,FALSE)) -> 243.30456 | X4: =Aggregate!$W4-$Q$1 -> 164.91367 | Y4: =MAX(Aggregate!$X4*Scoring!$B$48+1,1) -> 44.211245 | Z4: =VLOOKUP(Aggregate!$X4,BM:BO,3,FALSE) -> 1 | AA4: {=VLOOKUP(INDEX(ECR!$E:$E,MATCH(P4,ECR!$C:$C,0)),RISK!A:B,2,FALSE())} -> 3 | AC4: WR2 | AD4: =VLOOKUP(AC4,ECR!E:L,8,FALSE()) -> Puka Nacua | AE4: =IFERROR(VLOOKUP(Aggregate!$AD4,ECR!C:F,2,FALSE()),"-") -> LAR | AF4: =IFERROR(VLOOKUP(Aggregate!$AD4,ECR!C:F,4,FALSE()),"-") -> 11 | AG4: =Aggregate!$AE4 & "/" & Aggregate!$AF4 -> LAR/11 | AH4: =IFERROR(VLOOKUP(Aggregate!$AD4,WR!A:Q,13,FALSE())/17*(16-Aggregate!$AO4),0) -> 235.0438 | AI4: =IFERROR(VLOOKUP(Aggregate!$AD4,WR!A:Q,14,FALSE())/17*(16-Aggregate!$AO4),0) -> 237.0664 | AJ4: =IFERROR(VLOOKUP(Aggregate!$AD4,WR!A:Q,15,FALSE())/17*(16-Aggregate!$AO4),0) -> 240.10031 | AK4: =AVERAGE(Aggregate!$AH4,Aggregate!$AI4,Aggregate!$AJ4,VLOOKUP(Aggregate!$AD4,ECR!L:N,3,FALSE)) -> 236.31248 | AL4: =Aggregate!$AK4-$AE$1 -> 154.79155 | AM4: =MAX(Aggregate!$AL4*Scoring!$B$48+1,1) -> 41.559012 | AN4: =VLOOKUP(Aggregate!$AL4,BR:BT,3,FALSE) -> 1 | AO4: {=VLOOKUP(INDEX(ECR!$E:$E,MATCH(AD4,ECR!$C:$C,0)),RISK!A:B,2,FALSE())} -> 1.6732 | AQ4: TE2 | AR4: =VLOOKUP(AQ4,ECR!E:L,8,FALSE()) -> Trey McBride | AS4: =IFERROR(VLOOKUP(Aggregate!$AR4,ECR!C:F,2,FALSE()),"-") -> ARI | AT4: =IFERROR(VLOOKUP(Aggregate!$AR4,ECR!C:F,4,FALSE()),"-") -> 14 | AU4: =Aggregate!$AS4 & "/" & Aggregate!$AT4 -> ARI/14 | AV4: =IFERROR(VLOOKUP(Aggregate!$AR4,TE!A:K,9,FALSE())/17*(16-Aggregate!$BC4),0) -> 149.04723 | AW4: =IFERROR(VLOOKUP(Aggregate!$AR4,TE!A:K,10,FALSE())/17*(16-Aggregate!$BC4),0) -> 161.91121 | AX4: =IFERROR(VLOOKUP(Aggregate!$AR4,TE!A:K,11,FALSE())/17*(16-Aggregate!$BC4),0) -> 175.74621 | AY4: =AVERAGE(Aggregate!$AV4,Aggregate!$AW4,Aggregate!$AX4,VLOOKUP(Aggregate!$AR4,ECR!L:N,3,FALSE)) -> 162.15397 | AZ4: =Aggregate!$AY4-$AS$1 -> 80.615636 | BA4: =MAX(Aggregate!$AZ4*Scoring!$B$48+1,1) -> 22.123185 | BB4: =VLOOKUP(Aggregate!$AZ4,BW:BY,3,FALSE) -> 1 | BC4: {=VLOOKUP(INDEX(ECR!$E:$E,MATCH(AR4,ECR!$C:$C,0)),RISK!A:B,2,FALSE())} -> 2.3576 | BF4: 2 | BG4: =IFERROR(LARGE($G$3:$G$52,BF4),"") -> 249.94348 | BH4: =IFERROR(LARGE($J$3:$J$52,2),"") -> 31.479122 | BI4: =IF(BH4="",BI3,IF((BI3-BH4)>0.4*LARGE($J$3:$J$52,2),BH4,BI3)) -> 31.479122 | BJ4: =MIN(IF(BH4="",BJ3,IF((BI3-BH4)>0.4*LARGE($J$3:$J$52,2),BJ3+1,BJ3)),15) -> 2 | BK4: 2 | BL4: =IFERROR(LARGE($U$3:$U$102,BK4),"") -> 243.62 | BM4: =IFERROR(LARGE($X$3:$X$102,2),"") -> 164.91367 | BN4: =IF(BM4="",BN3,IF((BN3-BM4)>0.15*LARGE($X$3:$X$102,2),BM4,BN3)) -> 179.25573 | BO4: =IF(BM4="",BO3,IF((BN3-BM4)>0.15*LARGE($X$3:$X$102,2),BO3+1,BO3)) -> 1 | BP4: 2 | BQ4: =IFERROR(LARGE($AI$3:$AI$102,BP4),"") -> 233.03939 | BR4: =IFERROR(LARGE($AL$3:$AL$102,2),"") -> 152.6163 | BS4: =IF(BR4="",BS3,IF((BS3-BR4)>0.15*LARGE($AL$3:$AL$102,2),BR4,BS3)) -> 154.79155 | BT4: =IF(BR4="",BT3,IF((BS3-BR4)>0.15*LARGE($AL$3:$AL$102,2),BT3+1,BT3)) -> 1 | BU4: 2 | BV4: =IFERROR(LARGE($AW$3:$AW$52,BU4),"") -> 161.91121 | BW4: =IFERROR(LARGE($AZ$3:$AZ$52,2),"") -> 80.615636 | BX4: =IF(BW4="",BX3,IF((BX3-BW4)>0.2*LARGE($AZ$3:$AZ$52,2),BW4,BX3)) -> 82.223562 | BY4: =IF(BW4="",BY3,IF((BX3-BW4)>0.2*LARGE($AZ$3:$AZ$52,2),BY3+1,BY3)) -> 1
A5: QB3 | B5: =VLOOKUP(A5,ECR!E:L,8,FALSE()) -> Drake Maye | C5: =IFERROR(VLOOKUP(Aggregate!$B5,ECR!C:F,2,FALSE()),"-") -> NE | D5: =IFERROR(VLOOKUP(Aggregate!$B5,ECR!C:F,4,FALSE()),"-") -> 11 | E5: =Aggregate!$C5 & "/" & Aggregate!$D5 -> NE/11 | F5: =IFERROR(VLOOKUP(Aggregate!$B5,QB!A:Q,15,FALSE())/17*(16-Aggregate!$M5),0) -> 222.93783 | G5: =IFERROR(VLOOKUP(Aggregate!$B5,QB!A:Q,16,FALSE())/17*(16-Aggregate!$M5),0) -> 241.60461 | H5: =IFERROR(VLOOKUP(Aggregate!$B5,QB!A:Q,17,FALSE())/17*(16-Aggregate!$M5),0) -> 257.00173 | I5: =AVERAGE(Aggregate!$F5,Aggregate!$G5,Aggregate!$H5,VLOOKUP(Aggregate!$B5,ECR!L:N,3,FALSE)) -> 241.33652 | J5: =Aggregate!$I5-$C$1 -> 19.689709 | K5: =MAX(Aggregate!$J5*Scoring!$B$48+1,1) -> 6.1591651 | L5: =VLOOKUP(Aggregate!$J5,BH:BJ,3,FALSE) -> 2 | M5: {=VLOOKUP(INDEX(ECR!$E:$E,MATCH(B5,ECR!$C:$C,0)),RISK!A:B,2,FALSE())} -> 1.7403 | O5: RB3 | P5: =VLOOKUP(O5,ECR!E:L,8,FALSE()) -> Christian McCaffrey | Q5: =IFERROR(VLOOKUP(Aggregate!$P5,ECR!C:F,2,FALSE()),"-") -> SF | R5: =IFERROR(VLOOKUP(Aggregate!$P5,ECR!C:F,4,FALSE()),"-") -> 8 | S5: =Aggregate!$Q5 & "/" & Aggregate!$R5 -> SF/8 | T5: =IFERROR(VLOOKUP(Aggregate!$P5,RB!A:Q,13,FALSE())/17*(16-Aggregate!$AA5),0) -> 210.6 | U5: =IFERROR(VLOOKUP(Aggregate!$P5,RB!A:Q,14,FALSE())/17*(16-Aggregate!$AA5),0) -> 225.98588 | V5: =IFERROR(VLOOKUP(Aggregate!$P5,RB!A:Q,15,FALSE())/17*(16-Aggregate!$AA5),0) -> 237.13529 | W5: =AVERAGE(Aggregate!$T5,Aggregate!$U5,Aggregate!$V5,VLOOKUP(Aggregate!$P5,ECR!L:N,3,FALSE)) -> 224.92676 | X5: =Aggregate!$W5-$Q$1 -> 146.53588 | Y5: =MAX(Aggregate!$X5*Scoring!$B$48+1,1) -> 39.395833 | Z5: =VLOOKUP(Aggregate!$X5,BM:BO,3,FALSE) -> 2 | AA5: {=VLOOKUP(INDEX(ECR!$E:$E,MATCH(P5,ECR!$C:$C,0)),RISK!A:B,2,FALSE())} -> 3 | AC5: WR3 | AD5: =VLOOKUP(AC5,ECR!E:L,8,FALSE()) -> Jaxon Smith-Njigba | AE5: =IFERROR(VLOOKUP(Aggregate!$AD5,ECR!C:F,2,FALSE()),"-") -> SEA | AF5: =IFERROR(VLOOKUP(Aggregate!$AD5,ECR!C:F,4,FALSE()),"-") -> 11 | AG5: =Aggregate!$AE5 & "/" & Aggregate!$AF5 -> SEA/11 | AH5: =IFERROR(VLOOKUP(Aggregate!$AD5,WR!A:Q,13,FALSE())/17*(16-Aggregate!$AO5),0) -> 211.83734 | AI5: =IFERROR(VLOOKUP(Aggregate!$AD5,WR!A:Q,14,FALSE())/17*(16-Aggregate!$AO5),0) -> 227.06797 | AJ5: =IFERROR(VLOOKUP(Aggregate!$AD5,WR!A:Q,15,FALSE())/17*(16-Aggregate!$AO5),0) -> 247.40341 | AK5: =AVERAGE(Aggregate!$AH5,Aggregate!$AI5,Aggregate!$AJ5,VLOOKUP(Aggregate!$AD5,ECR!L:N,3,FALSE)) -> 228.34417 | AL5: =Aggregate!$AK5-$AE$1 -> 146.82324 | AM5: =MAX(Aggregate!$AL5*Scoring!$B$48+1,1) -> 39.47113 | AN5: =VLOOKUP(Aggregate!$AL5,BR:BT,3,FALSE) -> 1 | AO5: {=VLOOKUP(INDEX(ECR!$E:$E,MATCH(AD5,ECR!$C:$C,0)),RISK!A:B,2,FALSE())} -> 1.7501 | AQ5: TE3 | AR5: =VLOOKUP(AQ5,ECR!E:L,8,FALSE()) -> Colston Loveland | AS5: =IFERROR(VLOOKUP(Aggregate!$AR5,ECR!C:F,2,FALSE()),"-") -> CHI | AT5: =IFERROR(VLOOKUP(Aggregate!$AR5,ECR!C:F,4,FALSE()),"-") -> 10 | AU5: =Aggregate!$AS5 & "/" & Aggregate!$AT5 -> CHI/10 | AV5: =IFERROR(VLOOKUP(Aggregate!$AR5,TE!A:K,9,FALSE())/17*(16-Aggregate!$BC5),0) -> 124.91186 | AW5: =IFERROR(VLOOKUP(Aggregate!$AR5,TE!A:K,10,FALSE())/17*(16-Aggregate!$BC5),0) -> 137.33121 | AX5: =IFERROR(VLOOKUP(Aggregate!$AR5,TE!A:K,11,FALSE())/17*(16-Aggregate!$BC5),0) -> 154.52355 | AY5: =AVERAGE(Aggregate!$AV5,Aggregate!$AW5,Aggregate!$AX5,VLOOKUP(Aggregate!$AR5,ECR!L:N,3,FALSE)) -> 138.52445 | AZ5: =Aggregate!$AY5-$AS$1 -> 56.986123 | BA5: =MAX(Aggregate!$AZ5*Scoring!$B$48+1,1) -> 15.931699 | BB5: =VLOOKUP(Aggregate!$AZ5,BW:BY,3,FALSE) -> 2 | BC5: {=VLOOKUP(INDEX(ECR!$E:$E,MATCH(AR5,ECR!$C:$C,0)),RISK!A:B,2,FALSE())} -> 2.4313 | BF5: 3 | BG5: =IFERROR(LARGE($G$3:$G$52,BF5),"") -> 243.80189 | BH5: =IFERROR(LARGE($J$3:$J$52,3),"") -> 21.736932 | BI5: =IF(BH5="",BI4,IF((BI4-BH5)>0.4*LARGE($J$3:$J$52,2),BH5,BI4)) -> 31.479122 | BJ5: =MIN(IF(BH5="",BJ4,IF((BI4-BH5)>0.4*LARGE($J$3:$J$52,2),BJ4+1,BJ4)),15) -> 2 | BK5: 3 | BL5: =IFERROR(LARGE($U$3:$U$102,BK5),"") -> 225.98588 | BM5: =IFERROR(LARGE($X$3:$X$102,3),"") -> 146.53588 | BN5: =IF(BM5="",BN4,IF((BN4-BM5)>0.15*LARGE($X$3:$X$102,2),BM5,BN4)) -> 146.53588 | BO5: =IF(BM5="",BO4,IF((BN4-BM5)>0.15*LARGE($X$3:$X$102,2),BO4+1,BO4)) -> 2 | BP5: 3 | BQ5: =IFERROR(LARGE($AI$3:$AI$102,BP5),"") -> 227.06797 | BR5: =IFERROR(LARGE($AL$3:$AL$102,3),"") -> 146.82324 | BS5: =IF(BR5="",BS4,IF((BS4-BR5)>0.15*LARGE($AL$3:$AL$102,2),BR5,BS4)) -> 154.79155 | BT5: =IF(BR5="",BT4,IF((BS4-BR5)>0.15*LARGE($AL$3:$AL$102,2),BT4+1,BT4)) -> 1 | BU5: 3 | BV5: =IFERROR(LARGE($AW$3:$AW$52,BU5),"") -> 137.33121 | BW5: =IFERROR(LARGE($AZ$3:$AZ$52,3),"") -> 56.986123 | BX5: =IF(BW5="",BX4,IF((BX4-BW5)>0.2*LARGE($AZ$3:$AZ$52,2),BW5,BX4)) -> 56.986123 | BY5: =IF(BW5="",BY4,IF((BX4-BW5)>0.2*LARGE($AZ$3:$AZ$52,2),BY4+1,BY4)) -> 2
A6: QB4 | B6: =VLOOKUP(A6,ECR!E:L,8,FALSE()) -> Joe Burrow | C6: =IFERROR(VLOOKUP(Aggregate!$B6,ECR!C:F,2,FALSE()),"-") -> CIN | D6: =IFERROR(VLOOKUP(Aggregate!$B6,ECR!C:F,4,FALSE()),"-") -> 6 | E6: =Aggregate!$C6 & "/" & Aggregate!$D6 -> CIN/6 | F6: =IFERROR(VLOOKUP(Aggregate!$B6,QB!A:Q,15,FALSE())/17*(16-Aggregate!$M6),0) -> 226.0897 | G6: =IFERROR(VLOOKUP(Aggregate!$B6,QB!A:Q,16,FALSE())/17*(16-Aggregate!$M6),0) -> 237.2506 | H6: =IFERROR(VLOOKUP(Aggregate!$B6,QB!A:Q,17,FALSE())/17*(16-Aggregate!$M6),0) -> 252.53933 | I6: =AVERAGE(Aggregate!$F6,Aggregate!$G6,Aggregate!$H6,VLOOKUP(Aggregate!$B6,ECR!L:N,3,FALSE)) -> 239.37106 | J6: =Aggregate!$I6-$C$1 -> 17.724256 | K6: =MAX(Aggregate!$J6*Scoring!$B$48+1,1) -> 5.6441702 | L6: =VLOOKUP(Aggregate!$J6,BH:BJ,3,FALSE) -> 3 | M6: {=VLOOKUP(INDEX(ECR!$E:$E,MATCH(B6,ECR!$C:$C,0)),RISK!A:B,2,FALSE())} -> 1.7256 | O6: RB4 | P6: =VLOOKUP(O6,ECR!E:L,8,FALSE()) -> Jonathan Taylor | Q6: =IFERROR(VLOOKUP(Aggregate!$P6,ECR!C:F,2,FALSE()),"-") -> IND | R6: =IFERROR(VLOOKUP(Aggregate!$P6,ECR!C:F,4,FALSE()),"-") -> 13 | S6: =Aggregate!$Q6 & "/" & Aggregate!$R6 -> IND/13 | T6: =IFERROR(VLOOKUP(Aggregate!$P6,RB!A:Q,13,FALSE())/17*(16-Aggregate!$AA6),0) -> 200.42941 | U6: =IFERROR(VLOOKUP(Aggregate!$P6,RB!A:Q,14,FALSE())/17*(16-Aggregate!$AA6),0) -> 221.04588 | V6: =IFERROR(VLOOKUP(Aggregate!$P6,RB!A:Q,15,FALSE())/17*(16-Aggregate!$AA6),0) -> 245.61588 | W6: =AVERAGE(Aggregate!$T6,Aggregate!$U6,Aggregate!$V6,VLOOKUP(Aggregate!$P6,ECR!L:N,3,FALSE)) -> 222.03426 | X6: =Aggregate!$W6-$Q$1 -> 143.64338 | Y6: =MAX(Aggregate!$X6*Scoring!$B$48+1,1) -> 38.63793 | Z6: =VLOOKUP(Aggregate!$X6,BM:BO,3,FALSE) -> 2 | AA6: {=VLOOKUP(INDEX(ECR!$E:$E,MATCH(P6,ECR!$C:$C,0)),RISK!A:B,2,FALSE())} -> 3 | AC6: WR4 | AD6: =VLOOKUP(AC6,ECR!E:L,8,FALSE()) -> Amon-Ra St. Brown | AE6: =IFERROR(VLOOKUP(Aggregate!$AD6,ECR!C:F,2,FALSE()),"-") -> DET | AF6: =IFERROR(VLOOKUP(Aggregate!$AD6,ECR!C:F,4,FALSE()),"-") -> 6 | AG6: =Aggregate!$AE6 & "/" & Aggregate!$AF6 -> DET/6 | AH6: =IFERROR(VLOOKUP(Aggregate!$AD6,WR!A:Q,13,FALSE())/17*(16-Aggregate!$AO6),0) -> 211.52312 | AI6: =IFERROR(VLOOKUP(Aggregate!$AD6,WR!A:Q,14,FALSE())/17*(16-Aggregate!$AO6),0) -> 217.75126 | AJ6: =IFERROR(VLOOKUP(Aggregate!$AD6,WR!A:Q,15,FALSE())/17*(16-Aggregate!$AO6),0) -> 225.16332 | AK6: =AVERAGE(Aggregate!$AH6,Aggregate!$AI6,Aggregate!$AJ6,VLOOKUP(Aggregate!$AD6,ECR!L:N,3,FALSE)) -> 218.04724 | AL6: =Aggregate!$AK6-$AE$1 -> 136.52631 | AM6: =MAX(Aggregate!$AL6*Scoring!$B$48+1,1) -> 36.773092 | AN6: =VLOOKUP(Aggregate!$AL6,BR:BT,3,FALSE) -> 1 | AO6: {=VLOOKUP(INDEX(ECR!$E:$E,MATCH(AD6,ECR!$C:$C,0)),RISK!A:B,2,FALSE())} -> 1.8262 | AQ6: TE4 | AR6: =VLOOKUP(AQ6,ECR!E:L,8,FALSE()) -> Tyler Warren | AS6: =IFERROR(VLOOKUP(Aggregate!$AR6,ECR!C:F,2,FALSE()),"-") -> IND | AT6: =IFERROR(VLOOKUP(Aggregate!$AR6,ECR!C:F,4,FALSE()),"-") -> 13 | AU6: =Aggregate!$AS6 & "/" & Aggregate!$AT6 -> IND/13 | AV6: =IFERROR(VLOOKUP(Aggregate!$AR6,TE!A:K,9,FALSE())/17*(16-Aggregate!$BC6),0) -> 118.65348 | AW6: =IFERROR(VLOOKUP(Aggregate!$AR6,TE!A:K,10,FALSE())/17*(16-Aggregate!$BC6),0) -> 126.87345 | AX6: =IFERROR(VLOOKUP(Aggregate!$AR6,TE!A:K,11,FALSE())/17*(16-Aggregate!$BC6),0) -> 134.2198 | AY6: =AVERAGE(Aggregate!$AV6,Aggregate!$AW6,Aggregate!$AX6,VLOOKUP(Aggregate!$AR6,ECR!L:N,3,FALSE)) -> 126.65505 | AZ6: =Aggregate!$AY6-$AS$1 -> 45.116714 | BA6: =MAX(Aggregate!$AZ6*Scoring!$B$48+1,1) -> 12.821636 | BB6: =VLOOKUP(Aggregate!$AZ6,BW:BY,3,FALSE) -> 2 | BC6: {=VLOOKUP(INDEX(ECR!$E:$E,MATCH(AR6,ECR!$C:$C,0)),RISK!A:B,2,FALSE())} -> 2.4986 | BF6: 4 | BG6: =IFERROR(LARGE($G$3:$G$52,BF6),"") -> 241.60461 | BH6: =IFERROR(LARGE($J$3:$J$52,4),"") -> 19.689709 | BI6: =IF(BH6="",BI5,IF((BI5-BH6)>0.4*LARGE($J$3:$J$52,2),BH6,BI5)) -> 31.479122 | BJ6: =MIN(IF(BH6="",BJ5,IF((BI5-BH6)>0.4*LARGE($J$3:$J$52,2),BJ5+1,BJ5)),15) -> 2 | BK6: 4 | BL6: =IFERROR(LARGE($U$3:$U$102,BK6),"") -> 221.04588 | BM6: =IFERROR(LARGE($X$3:$X$102,4),"") -> 143.64338 | BN6: =IF(BM6="",BN5,IF((BN5-BM6)>0.15*LARGE($X$3:$X$102,2),BM6,BN5)) -> 146.53588 | BO6: =IF(BM6="",BO5,IF((BN5-BM6)>0.15*LARGE($X$3:$X$102,2),BO5+1,BO5)) -> 2 | BP6: 4 | BQ6: =IFERROR(LARGE($AI$3:$AI$102,BP6),"") -> 217.75126 | BR6: =IFERROR(LARGE($AL$3:$AL$102,4),"") -> 136.52631 | BS6: =IF(BR6="",BS5,IF((BS5-BR6)>0.15*LARGE($AL$3:$AL$102,2),BR6,BS5)) -> 154.79155 | BT6: =IF(BR6="",BT5,IF((BS5-BR6)>0.15*LARGE($AL$3:$AL$102,2),BT5+1,BT5)) -> 1 | BU6: 4 | BV6: =IFERROR(LARGE($AW$3:$AW$52,BU6),"") -> 126.87345 | BW6: =IFERROR(LARGE($AZ$3:$AZ$52,4),"") -> 45.116714 | BX6: =IF(BW6="",BX5,IF((BX5-BW6)>0.2*LARGE($AZ$3:$AZ$52,2),BW6,BX5)) -> 56.986123 | BY6: =IF(BW6="",BY5,IF((BX5-BW6)>0.2*LARGE($AZ$3:$AZ$52,2),BY5+1,BY5)) -> 2
A7: QB5 | B7: =VLOOKUP(A7,ECR!E:L,8,FALSE()) -> Jayden Daniels | C7: =IFERROR(VLOOKUP(Aggregate!$B7,ECR!C:F,2,FALSE()),"-") -> WAS | D7: =IFERROR(VLOOKUP(Aggregate!$B7,ECR!C:F,4,FALSE()),"-") -> 7 | E7: =Aggregate!$C7 & "/" & Aggregate!$D7 -> WAS/7 | F7: =IFERROR(VLOOKUP(Aggregate!$B7,QB!A:Q,15,FALSE())/17*(16-Aggregate!$M7),0) -> 218.02277 | G7: =IFERROR(VLOOKUP(Aggregate!$B7,QB!A:Q,16,FALSE())/17*(16-Aggregate!$M7),0) -> 239.04891 | H7: =IFERROR(VLOOKUP(Aggregate!$B7,QB!A:Q,17,FALSE())/17*(16-Aggregate!$M7),0) -> 263.25854 | I7: =AVERAGE(Aggregate!$F7,Aggregate!$G7,Aggregate!$H7,VLOOKUP(Aggregate!$B7,ECR!L:N,3,FALSE)) -> 239.84478 | J7: =Aggregate!$I7-$C$1 -> 18.197976 | K7: =MAX(Aggregate!$J7*Scoring!$B$48+1,1) -> 5.768296 | L7: =VLOOKUP(Aggregate!$J7,BH:BJ,3,FALSE) -> 3 | M7: {=VLOOKUP(INDEX(ECR!$E:$E,MATCH(B7,ECR!$C:$C,0)),RISK!A:B,2,FALSE())} -> 1.7205 | O7: RB5 | P7: =VLOOKUP(O7,ECR!E:L,8,FALSE()) -> James Cook III | Q7: =IFERROR(VLOOKUP(Aggregate!$P7,ECR!C:F,2,FALSE()),"-") -> BUF | R7: =IFERROR(VLOOKUP(Aggregate!$P7,ECR!C:F,4,FALSE()),"-") -> 7 | S7: =Aggregate!$Q7 & "/" & Aggregate!$R7 -> BUF/7 | T7: =IFERROR(VLOOKUP(Aggregate!$P7,RB!A:Q,13,FALSE())/17*(16-Aggregate!$AA7),0) -> 182.53529 | U7: =IFERROR(VLOOKUP(Aggregate!$P7,RB!A:Q,14,FALSE())/17*(16-Aggregate!$AA7),0) -> 194.18176 | V7: =IFERROR(VLOOKUP(Aggregate!$P7,RB!A:Q,15,FALSE())/17*(16-Aggregate!$AA7),0) -> 203.61059 | W7: =AVERAGE(Aggregate!$T7,Aggregate!$U7,Aggregate!$V7,VLOOKUP(Aggregate!$P7,ECR!L:N,3,FALSE)) -> 195.69397 | X7: =Aggregate!$W7-$Q$1 -> 117.30308 | Y7: =MAX(Aggregate!$X7*Scoring!$B$48+1,1) -> 31.736156 | Z7: =VLOOKUP(Aggregate!$X7,BM:BO,3,FALSE) -> 3 | AA7: {=VLOOKUP(INDEX(ECR!$E:$E,MATCH(P7,ECR!$C:$C,0)),RISK!A:B,2,FALSE())} -> 3 | AC7: WR5 | AD7: =VLOOKUP(AC7,ECR!E:L,8,FALSE()) -> CeeDee Lamb | AE7: =IFERROR(VLOOKUP(Aggregate!$AD7,ECR!C:F,2,FALSE()),"-") -> DAL | AF7: =IFERROR(VLOOKUP(Aggregate!$AD7,ECR!C:F,4,FALSE()),"-") -> 14 | AG7: =Aggregate!$AE7 & "/" & Aggregate!$AF7 -> DAL/14 | AH7: =IFERROR(VLOOKUP(Aggregate!$AD7,WR!A:Q,13,FALSE())/17*(16-Aggregate!$AO7),0) -> 162.38155 | AI7: =IFERROR(VLOOKUP(Aggregate!$AD7,WR!A:Q,14,FALSE())/17*(16-Aggregate!$AO7),0) -> 185.7353 | AJ7: =IFERROR(VLOOKUP(Aggregate!$AD7,WR!A:Q,15,FALSE())/17*(16-Aggregate!$AO7),0) -> 202.31348 | AK7: =AVERAGE(Aggregate!$AH7,Aggregate!$AI7,Aggregate!$AJ7,VLOOKUP(Aggregate!$AD7,ECR!L:N,3,FALSE)) -> 184.0414 | AL7: =Aggregate!$AK7-$AE$1 -> 102.52048 | AM7: =MAX(Aggregate!$AL7*Scoring!$B$48+1,1) -> 27.862767 | AN7: =VLOOKUP(Aggregate!$AL7,BR:BT,3,FALSE) -> 2 | AO7: {=VLOOKUP(INDEX(ECR!$E:$E,MATCH(AD7,ECR!$C:$C,0)),RISK!A:B,2,FALSE())} -> 1.9015 | AQ7: TE5 | AR7: =VLOOKUP(AQ7,ECR!E:L,8,FALSE()) -> Tucker Kraft | AS7: =IFERROR(VLOOKUP(Aggregate!$AR7,ECR!C:F,2,FALSE()),"-") -> GB | AT7: =IFERROR(VLOOKUP(Aggregate!$AR7,ECR!C:F,4,FALSE()),"-") -> 11 | AU7: =Aggregate!$AS7 & "/" & Aggregate!$AT7 -> GB/11 | AV7: =IFERROR(VLOOKUP(Aggregate!$AR7,TE!A:K,9,FALSE())/17*(16-Aggregate!$BC7),0) -> 99.4597 | AW7: =IFERROR(VLOOKUP(Aggregate!$AR7,TE!A:K,10,FALSE())/17*(16-Aggregate!$BC7),0) -> 116.95607 | AX7: =IFERROR(VLOOKUP(Aggregate!$AR7,TE!A:K,11,FALSE())/17*(16-Aggregate!$BC7),0) -> 140.36626 | AY7: =AVERAGE(Aggregate!$AV7,Aggregate!$AW7,Aggregate!$AX7,VLOOKUP(Aggregate!$AR7,ECR!L:N,3,FALSE)) -> 119.17227 | AZ7: =Aggregate!$AY7-$AS$1 -> 37.633941 | BA7: =MAX(Aggregate!$AZ7*Scoring!$B$48+1,1) -> 10.860974 | BB7: =VLOOKUP(Aggregate!$AZ7,BW:BY,3,FALSE) -> 3 | BC7: {=VLOOKUP(INDEX(ECR!$E:$E,MATCH(AR7,ECR!$C:$C,0)),RISK!A:B,2,FALSE())} -> 2.5595 | BF7: 5 | BG7: =IFERROR(LARGE($G$3:$G$52,BF7),"") -> 239.04891 | BH7: =IFERROR(LARGE($J$3:$J$52,5),"") -> 18.197976 | BI7: =IF(BH7="",BI6,IF((BI6-BH7)>0.4*LARGE($J$3:$J$52,2),BH7,BI6)) -> 18.197976 | BJ7: =MIN(IF(BH7="",BJ6,IF((BI6-BH7)>0.4*LARGE($J$3:$J$52,2),BJ6+1,BJ6)),15) -> 3 | BK7: 5 | BL7: =IFERROR(LARGE($U$3:$U$102,BK7),"") -> 202.44824 | BM7: =IFERROR(LARGE($X$3:$X$102,5),"") -> 119.34293 | BN7: =IF(BM7="",BN6,IF((BN6-BM7)>0.15*LARGE($X$3:$X$102,2),BM7,BN6)) -> 119.34293 | BO7: =IF(BM7="",BO6,IF((BN6-BM7)>0.15*LARGE($X$3:$X$102,2),BO6+1,BO6)) -> 3 | BP7: 5 | BQ7: =IFERROR(LARGE($AI$3:$AI$102,BP7),"") -> 185.7353 | BR7: =IFERROR(LARGE($AL$3:$AL$102,5),"") -> 103.71136 | BS7: =IF(BR7="",BS6,IF((BS6-BR7)>0.15*LARGE($AL$3:$AL$102,2),BR7,BS6)) -> 103.71136 | BT7: =IF(BR7="",BT6,IF((BS6-BR7)>0.15*LARGE($AL$3:$AL$102,2),BT6+1,BT6)) -> 2 | BU7: 5 | BV7: =IFERROR(LARGE($AW$3:$AW$52,BU7),"") -> 119.90706 | BW7: =IFERROR(LARGE($AZ$3:$AZ$52,5),"") -> 38.135248 | BX7: =IF(BW7="",BX6,IF((BX6-BW7)>0.2*LARGE($AZ$3:$AZ$52,2),BW7,BX6)) -> 38.135248 | BY7: =IF(BW7="",BY6,IF((BX6-BW7)>0.2*LARGE($AZ$3:$AZ$52,2),BY6+1,BY6)) -> 3
A8: QB6 | B8: =VLOOKUP(A8,ECR!E:L,8,FALSE()) -> Jalen Hurts | C8: =IFERROR(VLOOKUP(Aggregate!$B8,ECR!C:F,2,FALSE()),"-") -> PHI | D8: =IFERROR(VLOOKUP(Aggregate!$B8,ECR!C:F,4,FALSE()),"-") -> 10 | E8: =Aggregate!$C8 & "/" & Aggregate!$D8 -> PHI/10 | F8: =IFERROR(VLOOKUP(Aggregate!$B8,QB!A:Q,15,FALSE())/17*(16-Aggregate!$M8),0) -> 227.32518 | G8: =IFERROR(VLOOKUP(Aggregate!$B8,QB!A:Q,16,FALSE())/17*(16-Aggregate!$M8),0) -> 243.80189 | H8: =IFERROR(VLOOKUP(Aggregate!$B8,QB!A:Q,17,FALSE())/17*(16-Aggregate!$M8),0) -> 265.15729 | I8: =AVERAGE(Aggregate!$F8,Aggregate!$G8,Aggregate!$H8,VLOOKUP(Aggregate!$B8,ECR!L:N,3,FALSE)) -> 243.38374 | J8: =Aggregate!$I8-$C$1 -> 21.736932 | K8: =MAX(Aggregate!$J8*Scoring!$B$48+1,1) -> 6.6955854 | L8: =VLOOKUP(Aggregate!$J8,BH:BJ,3,FALSE) -> 2 | M8: {=VLOOKUP(INDEX(ECR!$E:$E,MATCH(B8,ECR!$C:$C,0)),RISK!A:B,2,FALSE())} -> 1.725 | O8: RB6 | P8: =VLOOKUP(O8,ECR!E:L,8,FALSE()) -> Chase Brown | Q8: =IFERROR(VLOOKUP(Aggregate!$P8,ECR!C:F,2,FALSE()),"-") -> CIN | R8: =IFERROR(VLOOKUP(Aggregate!$P8,ECR!C:F,4,FALSE()),"-") -> 6 | S8: =Aggregate!$Q8 & "/" & Aggregate!$R8 -> CIN/6 | T8: =IFERROR(VLOOKUP(Aggregate!$P8,RB!A:Q,13,FALSE())/17*(16-Aggregate!$AA8),0) -> 170.52941 | U8: =IFERROR(VLOOKUP(Aggregate!$P8,RB!A:Q,14,FALSE())/17*(16-Aggregate!$AA8),0) -> 188.89 | V8: =IFERROR(VLOOKUP(Aggregate!$P8,RB!A:Q,15,FALSE())/17*(16-Aggregate!$AA8),0) -> 207.77059 | W8: =AVERAGE(Aggregate!$T8,Aggregate!$U8,Aggregate!$V8,VLOOKUP(Aggregate!$P8,ECR!L:N,3,FALSE)) -> 191.45368 | X8: =Aggregate!$W8-$Q$1 -> 113.06279 | Y8: =MAX(Aggregate!$X8*Scoring!$B$48+1,1) -> 30.625099 | Z8: =VLOOKUP(Aggregate!$X8,BM:BO,3,FALSE) -> 3 | AA8: {=VLOOKUP(INDEX(ECR!$E:$E,MATCH(P8,ECR!$C:$C,0)),RISK!A:B,2,FALSE())} -> 3 | AC8: WR6 | AD8: =VLOOKUP(AC8,ECR!E:L,8,FALSE()) -> Justin Jefferson | AE8: =IFERROR(VLOOKUP(Aggregate!$AD8,ECR!C:F,2,FALSE()),"-") -> MIN | AF8: =IFERROR(VLOOKUP(Aggregate!$AD8,ECR!C:F,4,FALSE()),"-") -> 6 | AG8: =Aggregate!$AE8 & "/" & Aggregate!$AF8 -> MIN/6 | AH8: =IFERROR(VLOOKUP(Aggregate!$AD8,WR!A:Q,13,FALSE())/17*(16-Aggregate!$AO8),0) -> 175.71247 | AI8: =IFERROR(VLOOKUP(Aggregate!$AD8,WR!A:Q,14,FALSE())/17*(16-Aggregate!$AO8),0) -> 184.03613 | AJ8: =IFERROR(VLOOKUP(Aggregate!$AD8,WR!A:Q,15,FALSE())/17*(16-Aggregate!$AO8),0) -> 197.14444 | AK8: =AVERAGE(Aggregate!$AH8,Aggregate!$AI8,Aggregate!$AJ8,VLOOKUP(Aggregate!$AD8,ECR!L:N,3,FALSE)) -> 185.23229 | AL8: =Aggregate!$AK8-$AE$1 -> 103.71136 | AM8: =MAX(Aggregate!$AL8*Scoring!$B$48+1,1) -> 28.174807 | AN8: =VLOOKUP(Aggregate!$AL8,BR:BT,3,FALSE) -> 2 | AO8: {=VLOOKUP(INDEX(ECR!$E:$E,MATCH(AD8,ECR!$C:$C,0)),RISK!A:B,2,FALSE())} -> 1.976 | AQ8: TE6 | AR8: =VLOOKUP(AQ8,ECR!E:L,8,FALSE()) -> Harold Fannin Jr. | AS8: =IFERROR(VLOOKUP(Aggregate!$AR8,ECR!C:F,2,FALSE()),"-") -> CLE | AT8: =IFERROR(VLOOKUP(Aggregate!$AR8,ECR!C:F,4,FALSE()),"-") -> 11 | AU8: =Aggregate!$AS8 & "/" & Aggregate!$AT8 -> CLE/11 | AV8: =IFERROR(VLOOKUP(Aggregate!$AR8,TE!A:K,9,FALSE())/17*(16-Aggregate!$BC8),0) -> 106.93052 | AW8: =IFERROR(VLOOKUP(Aggregate!$AR8,TE!A:K,10,FALSE())/17*(16-Aggregate!$BC8),0) -> 119.90706 | AX8: =IFERROR(VLOOKUP(Aggregate!$AR8,TE!A:K,11,FALSE())/17*(16-Aggregate!$BC8),0) -> 134.80489 | AY8: =AVERAGE(Aggregate!$AV8,Aggregate!$AW8,Aggregate!$AX8,VLOOKUP(Aggregate!$AR8,ECR!L:N,3,FALSE)) -> 119.67358 | AZ8: =Aggregate!$AY8-$AS$1 -> 38.135248 | BA8: =MAX(Aggregate!$AZ8*Scoring!$B$48+1,1) -> 10.992328 | BB8: =VLOOKUP(Aggregate!$AZ8,BW:BY,3,FALSE) -> 3 | BC8: {=VLOOKUP(INDEX(ECR!$E:$E,MATCH(AR8,ECR!$C:$C,0)),RISK!A:B,2,FALSE())} -> 2.614 | BF8: 6 | BG8: =IFERROR(LARGE($G$3:$G$52,BF8),"") -> 237.2506 | BH8: =IFERROR(LARGE($J$3:$J$52,6),"") -> 17.724256 | BI8: =IF(BH8="",BI7,IF((BI7-BH8)>0.4*LARGE($J$3:$J$52,2),BH8,BI7)) -> 18.197976 | BJ8: =MIN(IF(BH8="",BJ7,IF((BI7-BH8)>0.4*LARGE($J$3:$J$52,2),BJ7+1,BJ7)),15) -> 3 | BK8: 6 | BL8: =IFERROR(LARGE($U$3:$U$102,BK8),"") -> 198.62471 | BM8: =IFERROR(LARGE($X$3:$X$102,6),"") -> 118.49029 | BN8: =IF(BM8="",BN7,IF((BN7-BM8)>0.15*LARGE($X$3:$X$102,2),BM8,BN7)) -> 119.34293 | BO8: =IF(BM8="",BO7,IF((BN7-BM8)>0.15*LARGE($X$3:$X$102,2),BO7+1,BO7)) -> 3 | BP8: 6 | BQ8: =IFERROR(LARGE($AI$3:$AI$102,BP8),"") -> 184.03613 | BR8: =IFERROR(LARGE($AL$3:$AL$102,6),"") -> 102.52048 | BS8: =IF(BR8="",BS7,IF((BS7-BR8)>0.15*LARGE($AL$3:$AL$102,2),BR8,BS7)) -> 103.71136 | BT8: =IF(BR8="",BT7,IF((BS7-BR8)>0.15*LARGE($AL$3:$AL$102,2),BT7+1,BT7)) -> 2 | BU8: 6 | BV8: =IFERROR(LARGE($AW$3:$AW$52,BU8),"") -> 117.05184 | BW8: =IFERROR(LARGE($AZ$3:$AZ$52,6),"") -> 37.633941 | BX8: =IF(BW8="",BX7,IF((BX7-BW8)>0.2*LARGE($AZ$3:$AZ$52,2),BW8,BX7)) -> 38.135248 | BY8: =IF(BW8="",BY7,IF((BX7-BW8)>0.2*LARGE($AZ$3:$AZ$52,2),BY7+1,BY7)) -> 3
